Workbook

Sheet Financial Dashboard
A1: Personal Wealth Notebook
A2: NYC earnings, taxes, savings, account-bucket growth, and house-aware retirement planning in one visible model. Use the selected-year input on Model Inputs and hover chart markers in Excel for point values.
A4: Working Years Entered | E4: Baseline Retirement Spend | I4: Base Liquid After Close | M4: Base All-In Draw Rate
A5: ='Savings Projection'!$B$12 -> 10 | E5: ='Savings Projection'!$B$13 -> 200000 | I5: ='Scenario Lab'!$H$14 -> 3736659.2 | M5: ='Scenario Lab'!$H$18 -> 0.13878238
A8: Ending Taxable | D8: Ending 401(k) | G8: Ending Roth | J8: Ending HSA | M8: Ending Total Wealth @ Base
A9: ='Savings Projection'!$AE$58 -> 18697878 | D9: ='Savings Projection'!$AF$58 -> 1854742.6 | G9: ='Savings Projection'!$AG$58 -> 567778.35 | J9: ='Savings Projection'!$AH$58 -> 0 | M9: ='Savings Projection'!$AI$58 -> 21120399
A13: Wealth Path Through Work And Retirement ($mm)
A33: Wealth By Account @ Base Return ($mm) | I33: Savings vs. Retirement Draws ($mm)
A55: Ending Wealth Mix @ Base Return | G55: Base House + Retirement
A56: Taxable | B56: ='Savings Projection'!$AE$58 -> 18697878 | C56: =IF($B$60=0,0,B56/$B$60) -> 0.88529947 | G56: Baseline retirement spend | M56: ='Scenario Lab'!$H$8 -> 200000
A57: 401(k) | B57: ='Savings Projection'!$AF$58 -> 1854742.6 | C57: =IF($B$60=0,0,B57/$B$60) -> 0.087817593 | G57: Liquid wealth after close | M57: ='Scenario Lab'!$H$14 -> 3736659.2
A58: Roth | B58: ='Savings Projection'!$AG$58 -> 567778.35 | C58: =IF($B$60=0,0,B58/$B$60) -> 0.026882937 | G58: Annual housing carry (all recurring housing costs) | M58: ='Scenario Lab'!$H$15 -> 318582.45
A59: HSA | B59: ='Savings Projection'!$AH$58 -> 0 | C59: =IF($B$60=0,0,B59/$B$60) -> 0 | G59: Total retirement need | M59: ='Scenario Lab'!$H$16 -> 518582.45
A60: Total | B60: =SUM(B56:B59) -> 21120399 | G60: All-in draw rate | M60: ='Scenario Lab'!$H$18 -> 0.13878238
G61: Max non-housing spend @ target draw | M61: ='Scenario Lab'!$H$19 -> 0
G62: Planning max house by draw / carry rules | M62: ='Scenario Lab'!$H$22 -> 1690179.6
G64: Selected Year Snapshot
G65: Selected year | J65: =MAX(1,MIN(ROUND('Model Inputs'!$B$15,0),ROWS('Savings Projection'!$A$19:$A$58))) -> 10 | L65: Phase | O65: =INDEX('Savings Projection'!$C$19:$C$58,MAX(1,MIN(ROUND('Model Inputs'!$B$15,0),ROWS('Savings Projection'!$A$19:$A$58)))) -> Working
G66: Gross comp | J66: =INDEX('Savings Projection'!$B$19:$B$58,MAX(1,MIN(ROUND('Model Inputs'!$B$15,0),ROWS('Savings Projection'!$A$19:$A$58)))) -> 2595495.8 | L66: Total tax / deductions | O66: =INDEX('Savings Projection'!$Q$19:$Q$58,MAX(1,MIN(ROUND('Model Inputs'!$B$15,0),ROWS('Savings Projection'!$A$19:$A$58)))) -> 1286105
G67: Wealth @ 0% | J67: =INDEX('Savings Projection'!$AJ$19:$AJ$58,MAX(1,MIN(ROUND('Model Inputs'!$B$15,0),ROWS('Savings Projection'!$A$19:$A$58)))) -> 5317592.2 | L67: Wealth @ Base | O67: =INDEX('Savings Projection'!$AI$19:$AI$58,MAX(1,MIN(ROUND('Model Inputs'!$B$15,0),ROWS('Savings Projection'!$A$19:$A$58)))) -> 6430241.6
G68: Wealth @ 8% | J68: =INDEX('Savings Projection'!$AK$19:$AK$58,MAX(1,MIN(ROUND('Model Inputs'!$B$15,0),ROWS('Savings Projection'!$A$19:$A$58)))) -> 6876892.3 | L68: Taxable balance | O68: =INDEX('Savings Projection'!$AE$19:$AE$58,MAX(1,MIN(ROUND('Model Inputs'!$B$15,0),ROWS('Savings Projection'!$A$19:$A$58)))) -> 6008456.2
G69: Total annual savings | J69: =INDEX('Savings Projection'!$X$19:$X$58,MAX(1,MIN(ROUND('Model Inputs'!$B$15,0),ROWS('Savings Projection'!$A$19:$A$58)))) -> 1139770.3 | L69: Actual withdrawal | O69: =INDEX('Savings Projection'!$Z$19:$Z$58,MAX(1,MIN(ROUND('Model Inputs'!$B$15,0),ROWS('Savings Projection'!$A$19:$A$58)))) -> 0
A70: Scenario Comparison
A71: Metric | B71: Downside | C71: Base | D71: Upside | F71: Scenario Liquid Wealth Comparison ($mm)
A72: Gross comp multiplier | B72: ='Scenario Lab'!G6 -> 0.75 | C72: ='Scenario Lab'!H6 -> 1 | D72: ='Scenario Lab'!I6 -> 1.2
A73: Return assumption | B73: ='Scenario Lab'!G7 -> 0.04 | C73: ='Scenario Lab'!H7 -> 0.06 | D73: ='Scenario Lab'!I7 -> 0.09
A74: Baseline retirement spend | B74: ='Scenario Lab'!G8 -> 170000 | C74: ='Scenario Lab'!H8 -> 200000 | D74: ='Scenario Lab'!I8 -> 240000
A75: Home purchase price | B75: ='Scenario Lab'!G10 -> 5000000 | C75: ='Scenario Lab'!H10 -> 5000000 | D75: ='Scenario Lab'!I10 -> 5000000
A76: Cash required at close | B76: ='Scenario Lab'!G11 -> 2025000 | C76: ='Scenario Lab'!H11 -> 2375000 | D76: ='Scenario Lab'!I11 -> 2125000
A77: Liquid wealth after close | B77: ='Scenario Lab'!G14 -> 1797689.5 | C77: ='Scenario Lab'!H14 -> 3736659.2 | D77: ='Scenario Lab'!I14 -> 4726250.9
A78: Annual housing carry at retirement | B78: ='Scenario Lab'!G15 -> 345129.3 | C78: ='Scenario Lab'!H15 -> 318582.45 | D78: ='Scenario Lab'!I15 -> 0
A79: Total retirement need | B79: ='Scenario Lab'!G16 -> 515129.3 | C79: ='Scenario Lab'!H16 -> 518582.45 | D79: ='Scenario Lab'!I16 -> 240000
A80: All-in draw rate at retirement | B80: ='Scenario Lab'!G18 -> 0.28655077 | C80: ='Scenario Lab'!H18 -> 0.13878238 | D80: ='Scenario Lab'!I18 -> 0.035214323
A81: Max non-housing spend @ target draw | B81: ='Scenario Lab'!G19 -> 0 | C81: ='Scenario Lab'!H19 -> 0 | D81: ='Scenario Lab'!I19 -> 238539.3
A82: Planning max house price | B82: ='Scenario Lab'!G22 -> 1326147.3 | C82: ='Scenario Lab'!H22 -> 1690179.6 | D82: ='Scenario Lab'!I22 -> 1914277.6
A83: Retired years funded | B83: ='Scenario Lab'!G23 -> 3 | C83: ='Scenario Lab'!H23 -> 9 | D83: ='Scenario Lab'!I23 -> 15
A84: First shortfall year | B84: ='Scenario Lab'!G24 -> 14 | C84: ='Scenario Lab'!H24 -> 20 | D84: ='Scenario Lab'!I24 -> 25
A85: Planning max house uses purchase-year liquidity for the close and retirement-year draw / carry rules for sustainability. | B85: ='Scenario Lab'!G25 -> 0 | C85: ='Scenario Lab'!H25 -> 0 | D85: ='Scenario Lab'!I25 -> 0
A86: Base Sensitivity Frontier | I86: How To Read It
A87: Reference-case liquidity margin | F87: ='Scenario Lab'!$N$217 -> 4519714 | I87: The frontier is centered on the smaller of your current target house and the base planning max house. Planning max house is not your close-funding limit; it is the tighter of the liquidity-floor cap and the annual housing-budget cap under the draw-rate rules.
A88: Max tested house @ reference spend | F88: ='Scenario Lab'!$N$218 -> 2028215.5
A89: Max tested spend @ reference house | F89: ='Scenario Lab'!$N$219 -> 260000
A90: Best tested liquidity margin | F90: ='Scenario Lab'!$N$220 -> 4883925.1
A91: Worst tested liquidity margin | F91: ='Scenario Lab'!$N$221 -> -836524.64
A92: Reference-case ending liquid wealth | F92: ='Scenario Lab'!$N$222 -> 6153377.2
A93: Reference-case ending net worth | F93: ='Scenario Lab'!$N$223 -> 10255887
A95: Gross comp now comes from the visible compensation schedule on Savings Projection, which models a 2026 stub year with prorated base and guaranteed bonus, a 2026 sign-on, a two-stage post-2027 bonus ramp, and a visible annual fluctuation layer that you can override row by row.

Sheet Model Inputs
A1: Model Inputs
A2: Edit global assumptions and scenario parameters here. Year-by-year compensation, HSA, after-tax payroll, rent, and living costs now live visibly on Savings Projection.
A4: Base Inputs | E4: Scenario, Retirement, And House Inputs | J4: Baseline retirement spend excludes house-related costs. Housing carry means the recurring housing cash costs that sit on top of that baseline spend: mortgage payments, property tax, insurance, maintenance, HOA / common charges, and home services / utilities. One-time purchase cash and move / furnish reserve are modeled separately.
A5: Filing status | B5: Single | E5: Scenario | F5: Downside | G5: Base | H5: Upside
A6: Resident city | B6: New York City | E6: Gross comp multiplier | F6: 0.75 | G6: 1 | H6: 1.2
A7: Starting taxable assets | B7: 150000 | E7: Tax multiplier | F7: 1.04 | G7: 1 | H7: 0.97
A8: Starting 401(k) balance | B8: 0 | E8: Rent multiplier | F8: 1 | G8: 1 | H8: 1.05
A9: Starting Roth balance | B9: 0 | E9: Living multiplier | F9: 0.95 | G9: 1 | H9: 1.08
A10: Starting HSA balance | B10: 0 | E10: Return assumption | F10: 0.04 | G10: 0.06 | H10: 0.09
A11: Baseline retirement spend (non-housing) | B11: 200000 | E11: Retire after YOE cap (defaults from modeled years) | F11: =MAX(1,$B$19+2) -> 12 | G11: =$B$19 -> 10 | H11: =MAX(1,$B$19-1) -> 9
A12: No-growth return | B12: 0 | E12: Baseline retirement spend (non-housing) | F12: 170000 | G12: 200000 | H12: 240000
A13: Base return | B13: 0.06 | E13: Home purchase year | F13: 10 | G13: 10 | H13: 10 | J13: The base projection treats any nonblank gross-comp row on Savings Projection as a working year and any blank row as retired. Use Dashboard selected year for point-in-time readouts, and use the planning draw rate / housing share / liquidity floor to stress what house price and non-housing retirement spend look reasonable. Home leverage now uses a visible policy: the effective down payment scales up as the purchase gets closer to retirement, and you can still force a fixed down payment with a manual override.
A14: Upside return | B14: 0.08 | E14: Home purchase price | F14: 5000000 | G14: 5000000 | H14: 5000000
A15: Dashboard selected year | B15: 10 | E15: Minimum down payment % | F15: 0.2 | G15: 0.2 | H15: 0.2
A16: Planning draw rate target | B16: 0.035 | E16: Mortgage rate | F16: 0.065 | G16: 0.065 | H16: 0.065
A17: Target housing share of total spend | B17: 0.35 | E17: Mortgage term (years) | F17: 30 | G17: 30 | H17: 30
A18: Minimum liquid reserve after purchase | B18: 1000000 | E18: Closing costs % | F18: 0.025 | G18: 0.025 | H18: 0.025
A19: Derived working years | B19: ='Savings Projection'!$B$12 -> 10 | E19: Property tax rate | F19: 0.01 | G19: 0.01 | H19: 0.01
E20: Home insurance rate | F20: 0.002 | G20: 0.002 | H20: 0.002
A21: Compensation Assumptions | E21: Home maintenance rate | F21: 0.01 | G21: 0.01 | H21: 0.01
A22: Start calendar year | B22: 2026 | E22: Annual HOA / common charges | F22: 0 | G22: 0 | H22: 0
A23: Start month | B23: 9 | E23: Annual home services / utilities | F23: 0 | G23: 0 | H23: 0
A24: Default modeled working years | B24: 10 | E24: One-time move / furnish reserve | F24: 0 | G24: 0 | H24: 0 | J24: Compensation reflects actual Jump Trading offer terms. September 14, 2026 start: prorated base + $450K sign-on paid in 2026 - no guaranteed bonus cash in 2026. FY2026 pro-rated guaranteed bonus ($450K x 4/12 = $150K) is received in calendar 2027. FY2027 full guaranteed bonus ($450K) is received in calendar 2028. From 2029 onward bonuses are discretionary, modeled growing from $450K at the early ramp rate. Bonus Overrides (AX col) lock years 1-3; the Trend Bonus formula starts the growth clock from Year 3. Session 3 refined this to a tranche-aware 50/25/25 split so each FY bonus pays 75% in the next CY and 25% in the CY after, and added Savings Projection columns BJ (cash received) and BK (unvested YE). 2026-04-11 IC quant median calibration: early bonus growth is about 45.3% and later growth about 27.1%, which makes the pre-swing trend total comp approximately $1.25M in projection year 5 and $2.25M in projection year 8. Those targets reflect the discussed median IC ranges of $1.0M-$1.5M by Y5 and $1.5M-$3.0M by Y8; Savings Projection column B remains cash received and therefore lags the accrued trend under the deferral schedule.
A25: Standard annual base salary | B25: 300000 | E25: Home appreciation | F25: 0.03 | G25: 0.03 | H25: 0.03
A26: Stub-year sign-on bonus | B26: 450000 | E26: Down payment % if buying at / after retirement | F26: 0.5 | G26: 0.45 | H26: 0.4
A27: Guaranteed annual bonus (FY2026–27, paid following yr) | B27: 450000 | E27: Working years until minimum down payment | F27: 5 | G27: 5 | H27: 4
A28: Early bonus growth rate | B28: 0.45296631 | E28: Manual down payment override %
A29: Later bonus growth rate | B29: 0.27087744
A30: Switch to later growth after proj. year | B30: 4
A31: Annual base growth | B31: 0
A32: Bonus fluctuation amplitude | B32: 0.12
A33: Bonus fluctuation cycle (years) | B33: 3
A34: Bonus fluctuation phase shift | B34: 0
A35: Rent inflation (annual) | B35: 0.03
A36: Living cost inflation (annual) | B36: 0.03

Sheet Savings Projection
A1: Savings And Retirement Projection
A2: Blue cells in the yearly table are inputs. Gross comp now flows from the visible compensation schedule on the right, while this sheet keeps all tax math and year-by-year savings / retirement logic visible.
A4: Setup | F4: Interpretation | M4: Tax And Retirement Modeling Notes | AN4: Compensation Schedule (Feeds Gross Comp)
A5: Filing status | B5: ='Model Inputs'!$B$5 -> Single | F5: The 401(k) column auto-fills from the visible annual limit in the tax sheet and reduces federal, NY State, and NYC taxable income. | M5: Talent.com showed about $674,633 net on $1.2M in New York as of 2026-04-03. | AN5: Edit the comp logic here instead of typing raw gross comp into the main output column. Per the Jump Trading offer letter (Addendum PDF): base $300K, guaranteed annual bonus $450K for FY2026 and FY2027, $450K sign-on in 2026 only. Start date Sep 2026 so FY2026 guarantee is prorated by 4/12 = $150K (accrued). Bonuses are paid on a deferred 50/25/25 schedule: 50% by March 15 following FY end, 25% six months later, 25% twelve months later. This splits each FY bonus across TWO calendar years (75% / 25%). Columns: AY = FY accrued (this is the accrual-basis number, pinned via AX for FY2026 and FY2027), BJ = CY cash received (tranche sum), BB = total CY cash gross comp (uses BJ, not AY). BK = year-end unvested deferred comp ('golden handcuffs' walk-away cost). BD:BI = Realized Comp (Actuals) input block; fill BE with actual accrued FY bonuses as they are announced and they will flow through the same 75/25 tranche logic to BD (which overrides BB when non-blank).
A6: Resident city | B6: ='Model Inputs'!$B$6 -> New York City | F6: HSA contributions reduce federal taxable income and FICA wages, but New York generally adds them back for state and city income tax. | M6: This workbook stays lower because it models NYC resident tax separately and uses the 2026 SSA wage base.
A7: Starting taxable assets | B7: ='Model Inputs'!$B$7 -> 150000 | F7: Roth IRA is modeled as a post-tax transfer from working-year cash flow; at this income level, treat it as a backdoor Roth assumption. | M7: The front-page graphs now continue through retirement years instead of falling to zero after work stops.
A8: Starting 401(k) balance | B8: ='Model Inputs'!$B$8 -> 0 | F8: Any nonblank gross-comp row is treated as Working, and any blank gross-comp row is treated as Retired. | M8: Bucket balances are base-return only; total-wealth paths are shown for 0%, base, and upside return assumptions.
A9: Starting Roth balance | B9: ='Model Inputs'!$B$9 -> 0 | F9: Retirement withdrawals start automatically on retired rows and fund baseline non-housing spending from taxable, then 401(k), then Roth, then HSA. | M9: Starting wealth can be split across taxable, 401(k), Roth, and HSA buckets so the dashboard reflects your real account mix.
A10: Starting HSA balance | B10: ='Model Inputs'!$B$10 -> 0 | F10: House purchase and housing carry are modeled on Scenario Lab so retirement housing costs sit on top of this baseline spend instead of being buried inside it. | M10: The retirement section is designed for directional planning rather than full distribution-tax optimization.
A11: Total starting investable assets | B11: =SUM(B7:B10) -> 150000 | F11: The compensation schedule on the right models a September 2026 stub year with prorated base and guaranteed bonus, then a faster early bonus ramp, a slower later ramp, and a visible deterministic fluctuation layer. To extend beyond the default working years, fill Gross Comp Input or the other override cells on later rows. The main Gross Comp column is output-only and feeds from the modeled schedule plus the visible input column. | M11: Scenario and house assumptions are edited on Model Inputs and flow through Scenario Lab as linked calculations.
A12: Working years entered | B12: =IFERROR(LOOKUP(2,1/($C$19:$C$58="Working"),$A$19:$A$58),0) -> 10
A13: Baseline retirement spend (non-housing) | B13: ='Model Inputs'!$B$11 -> 200000
A14: No-growth return | B14: ='Model Inputs'!$B$12 -> 0
A15: Base return | B15: ='Model Inputs'!$B$13 -> 0.06
A16: Upside return | B16: ='Model Inputs'!$B$14 -> 0.08
A17: Dashboard selected year | B17: ='Model Inputs'!$B$15 -> 10
A18: Year | B18: Gross Comp (output) | C18: Phase | D18: 401(k) / Trad | E18: HSA | F18: After-Tax Payroll | G18: Fed Taxable Income | H18: Federal Tax | I18: Social Security | J18: Medicare | K18: Add'l Medicare | L18: NY PFL | M18: NY Disability | N18: NY Taxable Income | O18: NY State Tax | P18: NYC Tax | Q18: Total Tax / Deductions | R18: Post-Tax Cash | S18: Rent (nominal) | T18: Other Living Costs (nominal) | U18: Cash After Living | V18: Roth IRA / Backdoor Roth | W18: Taxable Savings / (Draw) | X18: Total Annual Savings | Y18: Planned Retirement Withdrawal | Z18: Actual Withdrawal | AA18: Taxable Withdrawal | AB18: 401(k) Withdrawal | AC18: Roth Withdrawal | AD18: HSA Withdrawal | AE18: Taxable Balance | AF18: 401(k) Balance | AG18: Roth Balance | AH18: HSA Balance | AI18: Total Wealth @ Base | AJ18: Total Wealth @ 0% | AK18: Total Wealth @ 8% | AL18: Taxable Savings Rate | AM18: Total Savings Rate | AN18: Proj. Year | AO18: Calendar Year | AP18: Work Fraction | AQ18: Default Base | AR18: Base Override | AS18: Base Used | AT18: Base Earned | AU18: Trend Bonus | AV18: Default Swing % | AW18: Swing Override % | AX18: FY Bonus Accrual Override | AY18: FY Bonus Accrued | AZ18: Sign-On / One-Time | BA18: Other Cash Comp | BB18: Modeled Gross Comp | BC18: Gross Comp Input | BD18: Actual CY Gross Comp | BE18: FY Bonus Earned (paid next CY) | BF18: CY Base Actual | BG18: CY Other / Sign-On Actual | BH18: Confirmed? | BI18: Notes | BJ18: Bonus Cash Received | BK18: Unvested Deferred Comp (YE) | BL18: Rent (real $) | BM18: Living (real $)
A19: 1 | B19: =IF(BB19="","",BB19) -> 550000 | C19: =IF(B19="","Retired","Working") -> Working | D19: =IF(OR(C19="Retired",B19=""),0,MIN(B19,'Tax Assumptions'!$B$19)) -> 24500 | E19: 0 | F19: 0 | G19: =IF(C19="Working",MAX(B19-D19-E19-'Tax Assumptions'!$B$8,0),0) -> 509400 | H19: =IF(G19=0,0,LOOKUP(G19,'Tax Assumptions'!$F$9:$F$15,'Tax Assumptions'!$I$9:$I$15)+(G19-LOOKUP(G19,'Tax Assumptions'!$F$9:$F$15,'Tax Assumptions'!$F$9:$F$15))*LOOKUP(G19,'Tax Assumptions'!$F$9:$F$15,'Tax Assumptions'!$H$9:$H$15)) -> 147059.25 | I19: =IF(C19="Working",MIN(MAX(B19-E19,0),'Tax Assumptions'!$B$11)*'Tax Assumptions'!$B$10,0) -> 11439 | J19: =IF(C19="Working",MAX(B19-E19,0)*'Tax Assumptions'!$B$12,0) -> 7975 | K19: =IF(C19="Working",MAX(MAX(B19-E19,0)-'Tax Assumptions'!$B$14,0)*'Tax Assumptions'!$B$13,0) -> 3150 | L19: =IF(C19="Working",MIN(B19*'Tax Assumptions'!$B$15,'Tax Assumptions'!$B$16),0) -> 411.91 | M19: =IF(C19="Working",MIN(B19*'Tax Assumptions'!$B$17,'Tax Assumptions'!$B$18),0) -> 31.2 | N19: =IF(C19="Working",MAX(B19-D19-'Tax Assumptions'!$B$9,0),0) -> 517500 | O19: =IF(N19=0,0,LOOKUP(N19,'Tax Assumptions'!$K$9:$K$17,'Tax Assumptions'!$N$9:$N$17)+(N19-LOOKUP(N19,'Tax Assumptions'!$K$9:$K$17,'Tax Assumptions'!$K$9:$K$17))*LOOKUP(N19,'Tax Assumptions'!$K$9:$K$17,'Tax Assumptions'!$M$9:$M$17)) -> 32834.7 | P19: =IF(N19=0,0,LOOKUP(N19,'Tax Assumptions'!$P$9:$P$12,'Tax Assumptions'!$S$9:$S$12)+(N19-LOOKUP(N19,'Tax Assumptions'!$P$9:$P$12,'Tax Assumptions'!$P$9:$P$12))*LOOKUP(N19,'Tax Assumptions'!$P$9:$P$12,'Tax Assumptions'!$R$9:$R$12)) -> 19933.47 | Q19: =H19+I19+J19+K19+L19+M19+O19+P19 -> 222834.53 | R19: =IF(C19="Working",B19-D19-E19-F19-Q19,0) -> 302665.47 | S19: =IF(C19="Working",IF(BL19="","",BL19*(1+'Model Inputs'!$B$35)^(AN19-1)),"") -> 78000 | T19: =IF(C19="Working",IF(BM19="","",BM19*(1+'Model Inputs'!$B$36)^(AN19-1)),"") -> 40000 | U19: =IF(C19="Working",R19-S19-T19,0) -> 184665.47 | V19: =IF(C19="Working",MIN(MAX(U19,0),'Tax Assumptions'!$B$20),0) -> 7500 | W19: =IF(C19="Working",U19-V19,0) -> 177165.47 | X19: =IF(C19="Working",W19+V19+D19+E19,0) -> 209165.47 | Y19: =IF(C19="Retired",$B$13,0) -> 0 | Z19: =AA19+AB19+AC19+AD19 -> 0 | AA19: =IF(C19="Retired",MIN(Y19,(($B$7)*(1+$B$15)+IF(C19="Working",W19,0))),0) -> 0 | AB19: =IF(C19="Retired",MIN(MAX(Y19-AA19,0),(($B$8)*(1+$B$15)+IF(C19="Working",D19,0))),0) -> 0 | AC19: =IF(C19="Retired",MIN(MAX(Y19-AA19-AB19,0),(($B$9)*(1+$B$15)+IF(C19="Working",V19,0))),0) -> 0 | AD19: =IF(C19="Retired",MIN(MAX(Y19-AA19-AB19-AC19,0),(($B$10)*(1+$B$15)+IF(C19="Working",E19,0))),0) -> 0 | AE19: =MAX((($B$7)*(1+$B$15)+IF(C19="Working",W19,0))-AA19,0) -> 336165.47 | AF19: =MAX((($B$8)*(1+$B$15)+IF(C19="Working",D19,0))-AB19,0) -> 24500 | AG19: =MAX((($B$9)*(1+$B$15)+IF(C19="Working",V19,0))-AC19,0) -> 7500 | AH19: =MAX((($B$10)*(1+$B$15)+IF(C19="Working",E19,0))-AD19,0) -> 0 | AI19: =AE19+AF19+AG19+AH19 -> 368165.47 | AJ19: =IF(C19="Working",SUM($B$7:$B$10)+X19,MAX(SUM($B$7:$B$10)-MIN(Y19,SUM($B$7:$B$10)),0)) -> 359165.47 | AK19: =IF(C19="Working",SUM($B$7:$B$10)*(1+$B$16)+X19,MAX(SUM($B$7:$B$10)*(1+$B$16)-MIN(Y19,SUM($B$7:$B$10)*(1+$B$16)),0)) -> 371165.47 | AL19: =IF(C19="Working",IF(B19=0,0,W19/B19),0) -> 0.32211904 | AM19: =IF(C19="Working",IF(B19=0,0,X19/B19),0) -> 0.38030085 | AN19: =A19 -> 1 | AO19: ='Model Inputs'!$B$22+AN19-1 -> 2026 | AP19: =IF(AND(AQ19="",AR19="",AX19="",BA19="",BC19=""),"",IF(AN19=1,(13-'Model Inputs'!$B$23)/12,1)) -> 0.33333333 | AQ19: =IF(OR(AN19<='Model Inputs'!$B$24,AR19<>"",AX19<>"",BA19<>"",BC19<>""),'Model Inputs'!$B$25*(1+'Model Inputs'!$B$31)^(AN19-1),"") -> 300000 | AS19: =IF(AP19="","",IF(AR19="",AQ19,AR19)) -> 300000 | AT19: =IF(AS19="","",AP19*AS19) -> 100000 | AU19: =IF(AP19="","",IF(AN19=1,(13-'Model Inputs'!$B$23)/12*'Model Inputs'!$B$27,IF(AN19=2,'Model Inputs'!$B$27,IF(AN19<=MAX(3,'Model Inputs'!$B$30+1),'Model Inputs'!$B$27*(1+'Model Inputs'!$B$28)^(AN19-3),'Model Inputs'!$B$27*(1+'Model Inputs'!$B$28)^(MAX(3,'Model Inputs'!$B$30+1)-3)*(1+'Model Inputs'!$B$29)^(AN19-MAX(3,'Model Inputs'!$B$30+1)))))) -> 150000 | AV19: =IF(AU19="","",IF(AN19<=2,0,'Model Inputs'!$B$32*SIN(2*PI()*(AN19-3+'Model Inputs'!$B$34)/MAX(1,'Model Inputs'!$B$33)))) -> 0 | AX19: 150000 | AY19: =IF(AP19="","",IF(AX19<>"",AX19,AU19*(1+IF(AW19="",AV19,AW19)))) -> 150000 | AZ19: =IF(AN19=1,'Model Inputs'!$B$26,"") -> 450000 | BA19: 0 | BB19: =IF(AND(AS19="",BJ19="",AZ19="",BA19="",BC19="",BD19=""),"",IF(BD19<>"",BD19,IF(BC19<>"",BC19,AT19+IF(BJ19="",0,BJ19)+IF(AZ19="",0,AZ19)+IF(BA19="",0,BA19)))) -> 550000 | BD19: =IF(AND(BF19="",BG19=""),"",IF(BF19<>"",BF19,IF(AT19="",0,AT19))+IF(BG19<>"",BG19,IF(AZ19="",0,AZ19)+IF(BA19="",0,BA19))) | BJ19: =IF(AP19="","",0) -> 0 | BK19: =IF(AP19="","",IF(AY19="",0,AY19)) -> 150000 | BL19: 78000 | BM19: 40000
A20: 2 | B20: =IF(BB20="","",BB20) -> 412500 | C20: =IF(B20="","Retired","Working") -> Working | D20: =IF(OR(C20="Retired",B20=""),0,MIN(B20,'Tax Assumptions'!$B$19)) -> 24500 | E20: 0 | F20: 0 | G20: =IF(C20="Working",MAX(B20-D20-E20-'Tax Assumptions'!$B$8,0),0) -> 371900 | H20: =IF(G20=0,0,LOOKUP(G20,'Tax Assumptions'!$F$9:$F$15,'Tax Assumptions'!$I$9:$I$15)+(G20-LOOKUP(G20,'Tax Assumptions'!$F$9:$F$15,'Tax Assumptions'!$F$9:$F$15))*LOOKUP(G20,'Tax Assumptions'!$F$9:$F$15,'Tax Assumptions'!$H$9:$H$15)) -> 98934.25 | I20: =IF(C20="Working",MIN(MAX(B20-E20,0),'Tax Assumptions'!$B$11)*'Tax Assumptions'!$B$10,0) -> 11439 | J20: =IF(C20="Working",MAX(B20-E20,0)*'Tax Assumptions'!$B$12,0) -> 5981.25 | K20: =IF(C20="Working",MAX(MAX(B20-E20,0)-'Tax Assumptions'!$B$14,0)*'Tax Assumptions'!$B$13,0) -> 1912.5 | L20: =IF(C20="Working",MIN(B20*'Tax Assumptions'!$B$15,'Tax Assumptions'!$B$16),0) -> 411.91 | M20: =IF(C20="Working",MIN(B20*'Tax Assumptions'!$B$17,'Tax Assumptions'!$B$18),0) -> 31.2 | N20: =IF(C20="Working",MAX(B20-D20-'Tax Assumptions'!$B$9,0),0) -> 380000 | O20: =IF(N20=0,0,LOOKUP(N20,'Tax Assumptions'!$K$9:$K$17,'Tax Assumptions'!$N$9:$N$17)+(N20-LOOKUP(N20,'Tax Assumptions'!$K$9:$K$17,'Tax Assumptions'!$K$9:$K$17))*LOOKUP(N20,'Tax Assumptions'!$K$9:$K$17,'Tax Assumptions'!$M$9:$M$17)) -> 23415.95 | P20: =IF(N20=0,0,LOOKUP(N20,'Tax Assumptions'!$P$9:$P$12,'Tax Assumptions'!$S$9:$S$12)+(N20-LOOKUP(N20,'Tax Assumptions'!$P$9:$P$12,'Tax Assumptions'!$P$9:$P$12))*LOOKUP(N20,'Tax Assumptions'!$P$9:$P$12,'Tax Assumptions'!$R$9:$R$12)) -> 14603.97 | Q20: =H20+I20+J20+K20+L20+M20+O20+P20 -> 156730.03 | R20: =IF(C20="Working",B20-D20-E20-F20-Q20,0) -> 231269.97 | S20: =IF(C20="Working",IF(BL20="","",BL20*(1+'Model Inputs'!$B$35)^(AN20-1)),"") -> 80340 | T20: =IF(C20="Working",IF(BM20="","",BM20*(1+'Model Inputs'!$B$36)^(AN20-1)),"") -> 41200 | U20: =IF(C20="Working",R20-S20-T20,0) -> 109729.97 | V20: =IF(C20="Working",MIN(MAX(U20,0),'Tax Assumptions'!$B$20),0) -> 7500 | W20: =IF(C20="Working",U20-V20,0) -> 102229.97 | X20: =IF(C20="Working",W20+V20+D20+E20,0) -> 134229.97 | Y20: =IF(C20="Retired",$B$13,0) -> 0 | Z20: =AA20+AB20+AC20+AD20 -> 0 | AA20: =IF(C20="Retired",MIN(Y20,((AE19)*(1+$B$15)+IF(C20="Working",W20,0))),0) -> 0 | AB20: =IF(C20="Retired",MIN(MAX(Y20-AA20,0),((AF19)*(1+$B$15)+IF(C20="Working",D20,0))),0) -> 0 | AC20: =IF(C20="Retired",MIN(MAX(Y20-AA20-AB20,0),((AG19)*(1+$B$15)+IF(C20="Working",V20,0))),0) -> 0 | AD20: =IF(C20="Retired",MIN(MAX(Y20-AA20-AB20-AC20,0),((AH19)*(1+$B$15)+IF(C20="Working",E20,0))),0) -> 0 | AE20: =MAX(((AE19)*(1+$B$15)+IF(C20="Working",W20,0))-AA20,0) -> 458565.37 | AF20: =MAX(((AF19)*(1+$B$15)+IF(C20="Working",D20,0))-AB20,0) -> 50470 | AG20: =MAX(((AG19)*(1+$B$15)+IF(C20="Working",V20,0))-AC20,0) -> 15450 | AH20: =MAX(((AH19)*(1+$B$15)+IF(C20="Working",E20,0))-AD20,0) -> 0 | AI20: =AE20+AF20+AG20+AH20 -> 524485.37 | AJ20: =IF(C20="Working",AJ19+X20,MAX(AJ19-MIN(Y20,AJ19),0)) -> 493395.44 | AK20: =IF(C20="Working",AK19*(1+$B$16)+X20,MAX(AK19*(1+$B$16)-MIN(Y20,AK19*(1+$B$16)),0)) -> 535088.68 | AL20: =IF(C20="Working",IF(B20=0,0,W20/B20),0) -> 0.24783023 | AM20: =IF(C20="Working",IF(B20=0,0,X20/B20),0) -> 0.32540599 | AN20: =A20 -> 2 | AO20: ='Model Inputs'!$B$22+AN20-1 -> 2027 | AP20: =IF(AND(AQ20="",AR20="",AX20="",BA20="",BC20=""),"",IF(AN20=1,(13-'Model Inputs'!$B$23)/12,1)) -> 1 | AQ20: =IF(OR(AN20<='Model Inputs'!$B$24,AR20<>"",AX20<>"",BA20<>"",BC20<>""),'Model Inputs'!$B$25*(1+'Model Inputs'!$B$31)^(AN20-1),"") -> 300000 | AS20: =IF(AP20="","",IF(AR20="",AQ20,AR20)) -> 300000 | AT20: =IF(AS20="","",AP20*AS20) -> 300000 | AU20: =IF(AP20="","",IF(AN20=1,(13-'Model Inputs'!$B$23)/12*'Model Inputs'!$B$27,IF(AN20=2,'Model Inputs'!$B$27,IF(AN20<=MAX(3,'Model Inputs'!$B$30+1),'Model Inputs'!$B$27*(1+'Model Inputs'!$B$28)^(AN20-3),'Model Inputs'!$B$27*(1+'Model Inputs'!$B$28)^(MAX(3,'Model Inputs'!$B$30+1)-3)*(1+'Model Inputs'!$B$29)^(AN20-MAX(3,'Model Inputs'!$B$30+1)))))) -> 450000 | AV20: =IF(AU20="","",IF(AN20<=2,0,'Model Inputs'!$B$32*SIN(2*PI()*(AN20-3+'Model Inputs'!$B$34)/MAX(1,'Model Inputs'!$B$33)))) -> 0 | AX20: 450000 | AY20: =IF(AP20="","",IF(AX20<>"",AX20,AU20*(1+IF(AW20="",AV20,AW20)))) -> 450000 | AZ20: =IF(AN20=1,'Model Inputs'!$B$26,"") | BA20: 0 | BB20: =IF(AND(AS20="",BJ20="",AZ20="",BA20="",BC20="",BD20=""),"",IF(BD20<>"",BD20,IF(BC20<>"",BC20,AT20+IF(BJ20="",0,BJ20)+IF(AZ20="",0,AZ20)+IF(BA20="",0,BA20)))) -> 412500 | BD20: =IF(AND(BF20="",BG20="",BE19=""),"",IF(BF20<>"",BF20,IF(AT20="",0,AT20))+0.75*IF(BE19<>"",BE19,IF(AY19="",0,AY19))+IF(BG20<>"",BG20,IF(AZ20="",0,AZ20)+IF(BA20="",0,BA20))) | BJ20: =IF(AP20="","",0.75*IF(AY19="",0,AY19)) -> 112500 | BK20: =IF(AP20="","",IF(AY20="",0,AY20)+0.25*IF(AY19="",0,AY19)) -> 487500 | BL20: 78000 | BM20: 40000
A21: 3 | B21: =IF(BB21="","",BB21) -> 675000 | C21: =IF(B21="","Retired","Working") -> Working | D21: =IF(OR(C21="Retired",B21=""),0,MIN(B21,'Tax Assumptions'!$B$19)) -> 24500 | E21: 0 | F21: 0 | G21: =IF(C21="Working",MAX(B21-D21-E21-'Tax Assumptions'!$B$8,0),0) -> 634400 | H21: =IF(G21=0,0,LOOKUP(G21,'Tax Assumptions'!$F$9:$F$15,'Tax Assumptions'!$I$9:$I$15)+(G21-LOOKUP(G21,'Tax Assumptions'!$F$9:$F$15,'Tax Assumptions'!$F$9:$F$15))*LOOKUP(G21,'Tax Assumptions'!$F$9:$F$15,'Tax Assumptions'!$H$9:$H$15)) -> 190809.25 | I21: =IF(C21="Working",MIN(MAX(B21-E21,0),'Tax Assumptions'!$B$11)*'Tax Assumptions'!$B$10,0) -> 11439 | J21: =IF(C21="Working",MAX(B21-E21,0)*'Tax Assumptions'!$B$12,0) -> 9787.5 | K21: =IF(C21="Working",MAX(MAX(B21-E21,0)-'Tax Assumptions'!$B$14,0)*'Tax Assumptions'!$B$13,0) -> 4275 | L21: =IF(C21="Working",MIN(B21*'Tax Assumptions'!$B$15,'Tax Assumptions'!$B$16),0) -> 411.91 | M21: =IF(C21="Working",MIN(B21*'Tax Assumptions'!$B$17,'Tax Assumptions'!$B$18),0) -> 31.2 | N21: =IF(C21="Working",MAX(B21-D21-'Tax Assumptions'!$B$9,0),0) -> 642500 | O21: =IF(N21=0,0,LOOKUP(N21,'Tax Assumptions'!$K$9:$K$17,'Tax Assumptions'!$N$9:$N$17)+(N21-LOOKUP(N21,'Tax Assumptions'!$K$9:$K$17,'Tax Assumptions'!$K$9:$K$17))*LOOKUP(N21,'Tax Assumptions'!$K$9:$K$17,'Tax Assumptions'!$M$9:$M$17)) -> 41397.2 | P21: =IF(N21=0,0,LOOKUP(N21,'Tax Assumptions'!$P$9:$P$12,'Tax Assumptions'!$S$9:$S$12)+(N21-LOOKUP(N21,'Tax Assumptions'!$P$9:$P$12,'Tax Assumptions'!$P$9:$P$12))*LOOKUP(N21,'Tax Assumptions'!$P$9:$P$12,'Tax Assumptions'!$R$9:$R$12)) -> 24778.47 | Q21: =H21+I21+J21+K21+L21+M21+O21+P21 -> 282929.53 | R21: =IF(C21="Working",B21-D21-E21-F21-Q21,0) -> 367570.47 | S21: =IF(C21="Working",IF(BL21="","",BL21*(1+'Model Inputs'!$B$35)^(AN21-1)),"") -> 82750.2 | T21: =IF(C21="Working",IF(BM21="","",BM21*(1+'Model Inputs'!$B$36)^(AN21-1)),"") -> 53045 | U21: =IF(C21="Working",R21-S21-T21,0) -> 231775.27 | V21: =IF(C21="Working",MIN(MAX(U21,0),'Tax Assumptions'!$B$20),0) -> 7500 | W21: =IF(C21="Working",U21-V21,0) -> 224275.27 | X21: =IF(C21="Working",W21+V21+D21+E21,0) -> 256275.27 | Y21: =IF(C21="Retired",$B$13,0) -> 0 | Z21: =AA21+AB21+AC21+AD21 -> 0 | AA21: =IF(C21="Retired",MIN(Y21,((AE20)*(1+$B$15)+IF(C21="Working",W21,0))),0) -> 0 | AB21: =IF(C21="Retired",MIN(MAX(Y21-AA21,0),((AF20)*(1+$B$15)+IF(C21="Working",D21,0))),0) -> 0 | AC21: =IF(C21="Retired",MIN(MAX(Y21-AA21-AB21,0),((AG20)*(1+$B$15)+IF(C21="Working",V21,0))),0) -> 0 | AD21: =IF(C21="Retired",MIN(MAX(Y21-AA21-AB21-AC21,0),((AH20)*(1+$B$15)+IF(C21="Working",E21,0))),0) -> 0 | AE21: =MAX(((AE20)*(1+$B$15)+IF(C21="Working",W21,0))-AA21,0) -> 710354.56 | AF21: =MAX(((AF20)*(1+$B$15)+IF(C21="Working",D21,0))-AB21,0) -> 77998.2 | AG21: =MAX(((AG20)*(1+$B$15)+IF(C21="Working",V21,0))-AC21,0) -> 23877 | AH21: =MAX(((AH20)*(1+$B$15)+IF(C21="Working",E21,0))-AD21,0) -> 0 | AI21: =AE21+AF21+AG21+AH21 -> 812229.76 | AJ21: =IF(C21="Working",AJ20+X21,MAX(AJ20-MIN(Y21,AJ20),0)) -> 749670.71 | AK21: =IF(C21="Working",AK20*(1+$B$16)+X21,MAX(AK20*(1+$B$16)-MIN(Y21,AK20*(1+$B$16)),0)) -> 834171.04 | AL21: =IF(C21="Working",IF(B21=0,0,W21/B21),0) -> 0.33225966 | AM21: =IF(C21="Working",IF(B21=0,0,X21/B21),0) -> 0.37966707 | AN21: =A21 -> 3 | AO21: ='Model Inputs'!$B$22+AN21-1 -> 2028 | AP21: =IF(AND(AQ21="",AR21="",AX21="",BA21="",BC21=""),"",IF(AN21=1,(13-'Model Inputs'!$B$23)/12,1)) -> 1 | AQ21: =IF(OR(AN21<='Model Inputs'!$B$24,AR21<>"",AX21<>"",BA21<>"",BC21<>""),'Model Inputs'!$B$25*(1+'Model Inputs'!$B$31)^(AN21-1),"") -> 300000 | AS21: =IF(AP21="","",IF(AR21="",AQ21,AR21)) -> 300000 | AT21: =IF(AS21="","",AP21*AS21) -> 300000 | AU21: =IF(AP21="","",IF(AN21=1,(13-'Model Inputs'!$B$23)/12*'Model Inputs'!$B$27,IF(AN21=2,'Model Inputs'!$B$27,IF(AN21<=MAX(3,'Model Inputs'!$B$30+1),'Model Inputs'!$B$27*(1+'Model Inputs'!$B$28)^(AN21-3),'Model Inputs'!$B$27*(1+'Model Inputs'!$B$28)^(MAX(3,'Model Inputs'!$B$30+1)-3)*(1+'Model Inputs'!$B$29)^(AN21-MAX(3,'Model Inputs'!$B$30+1)))))) -> 450000 | AV21: =IF(AU21="","",IF(AN21<=2,0,'Model Inputs'!$B$32*SIN(2*PI()*(AN21-3+'Model Inputs'!$B$34)/MAX(1,'Model Inputs'!$B$33)))) -> 0 | AY21: =IF(AP21="","",IF(AX21<>"",AX21,AU21*(1+IF(AW21="",AV21,AW21)))) -> 450000 | AZ21: =IF(AN21=1,'Model Inputs'!$B$26,"") | BA21: 0 | BB21: =IF(AND(AS21="",BJ21="",AZ21="",BA21="",BC21="",BD21=""),"",IF(BD21<>"",BD21,IF(BC21<>"",BC21,AT21+IF(BJ21="",0,BJ21)+IF(AZ21="",0,AZ21)+IF(BA21="",0,BA21)))) -> 675000 | BD21: =IF(AND(BF21="",BG21="",BE20="",BE19=""),"",IF(BF21<>"",BF21,IF(AT21="",0,AT21))+0.75*IF(BE20<>"",BE20,IF(AY20="",0,AY20))+0.25*IF(BE19<>"",BE19,IF(AY19="",0,AY19))+IF(BG21<>"",BG21,IF(AZ21="",0,AZ21)+IF(BA21="",0,BA21))) | BJ21: =IF(AP21="","",0.75*IF(AY20="",0,AY20)+0.25*IF(AY19="",0,AY19)) -> 375000 | BK21: =IF(AP21="","",IF(AY21="",0,AY21)+0.25*IF(AY20="",0,AY20)) -> 562500 | BL21: 78000 | BM21: 50000
A22: 4 | B22: =IF(BB22="","",BB22) -> 750000 | C22: =IF(B22="","Retired","Working") -> Working | D22: =IF(OR(C22="Retired",B22=""),0,MIN(B22,'Tax Assumptions'!$B$19)) -> 24500 | E22: 0 | F22: 0 | G22: =IF(C22="Working",MAX(B22-D22-E22-'Tax Assumptions'!$B$8,0),0) -> 709400 | H22: =IF(G22=0,0,LOOKUP(G22,'Tax Assumptions'!$F$9:$F$15,'Tax Assumptions'!$I$9:$I$15)+(G22-LOOKUP(G22,'Tax Assumptions'!$F$9:$F$15,'Tax Assumptions'!$F$9:$F$15))*LOOKUP(G22,'Tax Assumptions'!$F$9:$F$15,'Tax Assumptions'!$H$9:$H$15)) -> 218435.25 | I22: =IF(C22="Working",MIN(MAX(B22-E22,0),'Tax Assumptions'!$B$11)*'Tax Assumptions'!$B$10,0) -> 11439 | J22: =IF(C22="Working",MAX(B22-E22,0)*'Tax Assumptions'!$B$12,0) -> 10875 | K22: =IF(C22="Working",MAX(MAX(B22-E22,0)-'Tax Assumptions'!$B$14,0)*'Tax Assumptions'!$B$13,0) -> 4950 | L22: =IF(C22="Working",MIN(B22*'Tax Assumptions'!$B$15,'Tax Assumptions'!$B$16),0) -> 411.91 | M22: =IF(C22="Working",MIN(B22*'Tax Assumptions'!$B$17,'Tax Assumptions'!$B$18),0) -> 31.2 | N22: =IF(C22="Working",MAX(B22-D22-'Tax Assumptions'!$B$9,0),0) -> 717500 | O22: =IF(N22=0,0,LOOKUP(N22,'Tax Assumptions'!$K$9:$K$17,'Tax Assumptions'!$N$9:$N$17)+(N22-LOOKUP(N22,'Tax Assumptions'!$K$9:$K$17,'Tax Assumptions'!$K$9:$K$17))*LOOKUP(N22,'Tax Assumptions'!$K$9:$K$17,'Tax Assumptions'!$M$9:$M$17)) -> 46534.7 | P22: =IF(N22=0,0,LOOKUP(N22,'Tax Assumptions'!$P$9:$P$12,'Tax Assumptions'!$S$9:$S$12)+(N22-LOOKUP(N22,'Tax Assumptions'!$P$9:$P$12,'Tax Assumptions'!$P$9:$P$12))*LOOKUP(N22,'Tax Assumptions'!$P$9:$P$12,'Tax Assumptions'!$R$9:$R$12)) -> 27685.47 | Q22: =H22+I22+J22+K22+L22+M22+O22+P22 -> 320362.53 | R22: =IF(C22="Working",B22-D22-E22-F22-Q22,0) -> 405137.47 | S22: =IF(C22="Working",IF(BL22="","",BL22*(1+'Model Inputs'!$B$35)^(AN22-1)),"") -> 85232.706 | T22: =IF(C22="Working",IF(BM22="","",BM22*(1+'Model Inputs'!$B$36)^(AN22-1)),"") -> 54636.35 | U22: =IF(C22="Working",R22-S22-T22,0) -> 265268.41 | V22: =IF(C22="Working",MIN(MAX(U22,0),'Tax Assumptions'!$B$20),0) -> 7500 | W22: =IF(C22="Working",U22-V22,0) -> 257768.41 | X22: =IF(C22="Working",W22+V22+D22+E22,0) -> 289768.41 | Y22: =IF(C22="Retired",$B$13,0) -> 0 | Z22: =AA22+AB22+AC22+AD22 -> 0 | AA22: =IF(C22="Retired",MIN(Y22,((AE21)*(1+$B$15)+IF(C22="Working",W22,0))),0) -> 0 | AB22: =IF(C22="Retired",MIN(MAX(Y22-AA22,0),((AF21)*(1+$B$15)+IF(C22="Working",D22,0))),0) -> 0 | AC22: =IF(C22="Retired",MIN(MAX(Y22-AA22-AB22,0),((AG21)*(1+$B$15)+IF(C22="Working",V22,0))),0) -> 0 | AD22: =IF(C22="Retired",MIN(MAX(Y22-AA22-AB22-AC22,0),((AH21)*(1+$B$15)+IF(C22="Working",E22,0))),0) -> 0 | AE22: =MAX(((AE21)*(1+$B$15)+IF(C22="Working",W22,0))-AA22,0) -> 1010744.2 | AF22: =MAX(((AF21)*(1+$B$15)+IF(C22="Working",D22,0))-AB22,0) -> 107178.09 | AG22: =MAX(((AG21)*(1+$B$15)+IF(C22="Working",V22,0))-AC22,0) -> 32809.62 | AH22: =MAX(((AH21)*(1+$B$15)+IF(C22="Working",E22,0))-AD22,0) -> 0 | AI22: =AE22+AF22+AG22+AH22 -> 1150732 | AJ22: =IF(C22="Working",AJ21+X22,MAX(AJ21-MIN(Y22,AJ21),0)) -> 1039439.1 | AK22: =IF(C22="Working",AK21*(1+$B$16)+X22,MAX(AK21*(1+$B$16)-MIN(Y22,AK21*(1+$B$16)),0)) -> 1190673.1 | AL22: =IF(C22="Working",IF(B22=0,0,W22/B22),0) -> 0.34369122 | AM22: =IF(C22="Working",IF(B22=0,0,X22/B22),0) -> 0.38635789 | AN22: =A22 -> 4 | AO22: ='Model Inputs'!$B$22+AN22-1 -> 2029 | AP22: =IF(AND(AQ22="",AR22="",AX22="",BA22="",BC22=""),"",IF(AN22=1,(13-'Model Inputs'!$B$23)/12,1)) -> 1 | AQ22: =IF(OR(AN22<='Model Inputs'!$B$24,AR22<>"",AX22<>"",BA22<>"",BC22<>""),'Model Inputs'!$B$25*(1+'Model Inputs'!$B$31)^(AN22-1),"") -> 300000 | AS22: =IF(AP22="","",IF(AR22="",AQ22,AR22)) -> 300000 | AT22: =IF(AS22="","",AP22*AS22) -> 300000 | AU22: =IF(AP22="","",IF(AN22=1,(13-'Model Inputs'!$B$23)/12*'Model Inputs'!$B$27,IF(AN22=2,'Model Inputs'!$B$27,IF(AN22<=MAX(3,'Model Inputs'!$B$30+1),'Model Inputs'!$B$27*(1+'Model Inputs'!$B$28)^(AN22-3),'Model Inputs'!$B$27*(1+'Model Inputs'!$B$28)^(MAX(3,'Model Inputs'!$B$30+1)-3)*(1+'Model Inputs'!$B$29)^(AN22-MAX(3,'Model Inputs'!$B$30+1)))))) -> 653834.84 | AV22: =IF(AU22="","",IF(AN22<=2,0,'Model Inputs'!$B$32*SIN(2*PI()*(AN22-3+'Model Inputs'!$B$34)/MAX(1,'Model Inputs'!$B$33)))) -> 0.10392305 | AY22: =IF(AP22="","",IF(AX22<>"",AX22,AU22*(1+IF(AW22="",AV22,AW22)))) -> 721783.35 | AZ22: =IF(AN22=1,'Model Inputs'!$B$26,"") | BA22: 0 | BB22: =IF(AND(AS22="",BJ22="",AZ22="",BA22="",BC22="",BD22=""),"",IF(BD22<>"",BD22,IF(BC22<>"",BC22,AT22+IF(BJ22="",0,BJ22)+IF(AZ22="",0,AZ22)+IF(BA22="",0,BA22)))) -> 750000 | BD22: =IF(AND(BF22="",BG22="",BE21="",BE20=""),"",IF(BF22<>"",BF22,IF(AT22="",0,AT22))+0.75*IF(BE21<>"",BE21,IF(AY21="",0,AY21))+0.25*IF(BE20<>"",BE20,IF(AY20="",0,AY20))+IF(BG22<>"",BG22,IF(AZ22="",0,AZ22)+IF(BA22="",0,BA22))) | BJ22: =IF(AP22="","",0.75*IF(AY21="",0,AY21)+0.25*IF(AY20="",0,AY20)) -> 450000 | BK22: =IF(AP22="","",IF(AY22="",0,AY22)+0.25*IF(AY21="",0,AY21)) -> 834283.35 | BL22: 78000 | BM22: 50000
A23: 5 | B23: =IF(BB23="","",BB23) -> 953837.51 | C23: =IF(B23="","Retired","Working") -> Working | D23: =IF(OR(C23="Retired",B23=""),0,MIN(B23,'Tax Assumptions'!$B$19)) -> 24500 | E23: 0 | F23: 0 | G23: =IF(C23="Working",MAX(B23-D23-E23-'Tax Assumptions'!$B$8,0),0) -> 913237.51 | H23: =IF(G23=0,0,LOOKUP(G23,'Tax Assumptions'!$F$9:$F$15,'Tax Assumptions'!$I$9:$I$15)+(G23-LOOKUP(G23,'Tax Assumptions'!$F$9:$F$15,'Tax Assumptions'!$F$9:$F$15))*LOOKUP(G23,'Tax Assumptions'!$F$9:$F$15,'Tax Assumptions'!$H$9:$H$15)) -> 293855.13 | I23: =IF(C23="Working",MIN(MAX(B23-E23,0),'Tax Assumptions'!$B$11)*'Tax Assumptions'!$B$10,0) -> 11439 | J23: =IF(C23="Working",MAX(B23-E23,0)*'Tax Assumptions'!$B$12,0) -> 13830.644 | K23: =IF(C23="Working",MAX(MAX(B23-E23,0)-'Tax Assumptions'!$B$14,0)*'Tax Assumptions'!$B$13,0) -> 6784.5376 | L23: =IF(C23="Working",MIN(B23*'Tax Assumptions'!$B$15,'Tax Assumptions'!$B$16),0) -> 411.91 | M23: =IF(C23="Working",MIN(B23*'Tax Assumptions'!$B$17,'Tax Assumptions'!$B$18),0) -> 31.2 | N23: =IF(C23="Working",MAX(B23-D23-'Tax Assumptions'!$B$9,0),0) -> 921337.51 | O23: =IF(N23=0,0,LOOKUP(N23,'Tax Assumptions'!$K$9:$K$17,'Tax Assumptions'!$N$9:$N$17)+(N23-LOOKUP(N23,'Tax Assumptions'!$K$9:$K$17,'Tax Assumptions'!$K$9:$K$17))*LOOKUP(N23,'Tax Assumptions'!$K$9:$K$17,'Tax Assumptions'!$M$9:$M$17)) -> 60497.57 | P23: =IF(N23=0,0,LOOKUP(N23,'Tax Assumptions'!$P$9:$P$12,'Tax Assumptions'!$S$9:$S$12)+(N23-LOOKUP(N23,'Tax Assumptions'!$P$9:$P$12,'Tax Assumptions'!$P$9:$P$12))*LOOKUP(N23,'Tax Assumptions'!$P$9:$P$12,'Tax Assumptions'!$R$9:$R$12)) -> 35586.212 | Q23: =H23+I23+J23+K23+L23+M23+O23+P23 -> 422436.2 | R23: =IF(C23="Working",B23-D23-E23-F23-Q23,0) -> 506901.31 | S23: =IF(C23="Working",IF(BL23="","",BL23*(1+'Model Inputs'!$B$35)^(AN23-1)),"") -> 87789.687 | T23: =IF(C23="Working",IF(BM23="","",BM23*(1+'Model Inputs'!$B$36)^(AN23-1)),"") -> 56275.44 | U23: =IF(C23="Working",R23-S23-T23,0) -> 362836.18 | V23: =IF(C23="Working",MIN(MAX(U23,0),'Tax Assumptions'!$B$20),0) -> 7500 | W23: =IF(C23="Working",U23-V23,0) -> 355336.18 | X23: =IF(C23="Working",W23+V23+D23+E23,0) -> 387336.18 | Y23: =IF(C23="Retired",$B$13,0) -> 0 | Z23: =AA23+AB23+AC23+AD23 -> 0 | AA23: =IF(C23="Retired",MIN(Y23,((AE22)*(1+$B$15)+IF(C23="Working",W23,0))),0) -> 0 | AB23: =IF(C23="Retired",MIN(MAX(Y23-AA23,0),((AF22)*(1+$B$15)+IF(C23="Working",D23,0))),0) -> 0 | AC23: =IF(C23="Retired",MIN(MAX(Y23-AA23-AB23,0),((AG22)*(1+$B$15)+IF(C23="Working",V23,0))),0) -> 0 | AD23: =IF(C23="Retired",MIN(MAX(Y23-AA23-AB23-AC23,0),((AH22)*(1+$B$15)+IF(C23="Working",E23,0))),0) -> 0 | AE23: =MAX(((AE22)*(1+$B$15)+IF(C23="Working",W23,0))-AA23,0) -> 1426725.1 | AF23: =MAX(((AF22)*(1+$B$15)+IF(C23="Working",D23,0))-AB23,0) -> 138108.78 | AG23: =MAX(((AG22)*(1+$B$15)+IF(C23="Working",V23,0))-AC23,0) -> 42278.197 | AH23: =MAX(((AH22)*(1+$B$15)+IF(C23="Working",E23,0))-AD23,0) -> 0 | AI23: =AE23+AF23+AG23+AH23 -> 1607112.1 | AJ23: =IF(C23="Working",AJ22+X23,MAX(AJ22-MIN(Y23,AJ22),0)) -> 1426775.3 | AK23: =IF(C23="Working",AK22*(1+$B$16)+X23,MAX(AK22*(1+$B$16)-MIN(Y23,AK22*(1+$B$16)),0)) -> 1673263.2 | AL23: =IF(C23="Working",IF(B23=0,0,W23/B23),0) -> 0.37253324 | AM23: =IF(C23="Working",IF(B23=0,0,X23/B23),0) -> 0.40608193 | AN23: =A23 -> 5 | AO23: ='Model Inputs'!$B$22+AN23-1 -> 2030 | AP23: =IF(AND(AQ23="",AR23="",AX23="",BA23="",BC23=""),"",IF(AN23=1,(13-'Model Inputs'!$B$23)/12,1)) -> 1 | AQ23: =IF(OR(AN23<='Model Inputs'!$B$24,AR23<>"",AX23<>"",BA23<>"",BC23<>""),'Model Inputs'!$B$25*(1+'Model Inputs'!$B$31)^(AN23-1),"") -> 300000 | AS23: =IF(AP23="","",IF(AR23="",AQ23,AR23)) -> 300000 | AT23: =IF(AS23="","",AP23*AS23) -> 300000 | AU23: =IF(AP23="","",IF(AN23=1,(13-'Model Inputs'!$B$23)/12*'Model Inputs'!$B$27,IF(AN23=2,'Model Inputs'!$B$27,IF(AN23<=MAX(3,'Model Inputs'!$B$30+1),'Model Inputs'!$B$27*(1+'Model Inputs'!$B$28)^(AN23-3),'Model Inputs'!$B$27*(1+'Model Inputs'!$B$28)^(MAX(3,'Model Inputs'!$B$30+1)-3)*(1+'Model Inputs'!$B$29)^(AN23-MAX(3,'Model Inputs'!$B$30+1)))))) -> 950000 | AV23: =IF(AU23="","",IF(AN23<=2,0,'Model Inputs'!$B$32*SIN(2*PI()*(AN23-3+'Model Inputs'!$B$34)/MAX(1,'Model Inputs'!$B$33)))) -> -0.10392305 | AY23: =IF(AP23="","",IF(AX23<>"",AX23,AU23*(1+IF(AW23="",AV23,AW23)))) -> 851273.1 | AZ23: =IF(AN23=1,'Model Inputs'!$B$26,"") | BA23: 0 | BB23: =IF(AND(AS23="",BJ23="",AZ23="",BA23="",BC23="",BD23=""),"",IF(BD23<>"",BD23,IF(BC23<>"",BC23,AT23+IF(BJ23="",0,BJ23)+IF(AZ23="",0,AZ23)+IF(BA23="",0,BA23)))) -> 953837.51 | BD23: =IF(AND(BF23="",BG23="",BE22="",BE21=""),"",IF(BF23<>"",BF23,IF(AT23="",0,AT23))+0.75*IF(BE22<>"",BE22,IF(AY22="",0,AY22))+0.25*IF(BE21<>"",BE21,IF(AY21="",0,AY21))+IF(BG23<>"",BG23,IF(AZ23="",0,AZ23)+IF(BA23="",0,BA23))) | BJ23: =IF(AP23="","",0.75*IF(AY22="",0,AY22)+0.25*IF(AY21="",0,AY21)) -> 653837.51 | BK23: =IF(AP23="","",IF(AY23="",0,AY23)+0.25*IF(AY22="",0,AY22)) -> 1031718.9 | BL23: 78000 | BM23: 50000
A24: 6 | B24: =IF(BB24="","",BB24) -> 1118900.7 | C24: =IF(B24="","Retired","Working") -> Working | D24: =IF(OR(C24="Retired",B24=""),0,MIN(B24,'Tax Assumptions'!$B$19)) -> 24500 | E24: 0 | F24: 0 | G24: =IF(C24="Working",MAX(B24-D24-E24-'Tax Assumptions'!$B$8,0),0) -> 1078300.7 | H24: =IF(G24=0,0,LOOKUP(G24,'Tax Assumptions'!$F$9:$F$15,'Tax Assumptions'!$I$9:$I$15)+(G24-LOOKUP(G24,'Tax Assumptions'!$F$9:$F$15,'Tax Assumptions'!$F$9:$F$15))*LOOKUP(G24,'Tax Assumptions'!$F$9:$F$15,'Tax Assumptions'!$H$9:$H$15)) -> 354928.5 | I24: =IF(C24="Working",MIN(MAX(B24-E24,0),'Tax Assumptions'!$B$11)*'Tax Assumptions'!$B$10,0) -> 11439 | J24: =IF(C24="Working",MAX(B24-E24,0)*'Tax Assumptions'!$B$12,0) -> 16224.06 | K24: =IF(C24="Working",MAX(MAX(B24-E24,0)-'Tax Assumptions'!$B$14,0)*'Tax Assumptions'!$B$13,0) -> 8270.106 | L24: =IF(C24="Working",MIN(B24*'Tax Assumptions'!$B$15,'Tax Assumptions'!$B$16),0) -> 411.91 | M24: =IF(C24="Working",MIN(B24*'Tax Assumptions'!$B$17,'Tax Assumptions'!$B$18),0) -> 31.2 | N24: =IF(C24="Working",MAX(B24-D24-'Tax Assumptions'!$B$9,0),0) -> 1086400.7 | O24: =IF(N24=0,0,LOOKUP(N24,'Tax Assumptions'!$K$9:$K$17,'Tax Assumptions'!$N$9:$N$17)+(N24-LOOKUP(N24,'Tax Assumptions'!$K$9:$K$17,'Tax Assumptions'!$K$9:$K$17))*LOOKUP(N24,'Tax Assumptions'!$K$9:$K$17,'Tax Assumptions'!$M$9:$M$17)) -> 72051.719 | P24: =IF(N24=0,0,LOOKUP(N24,'Tax Assumptions'!$P$9:$P$12,'Tax Assumptions'!$S$9:$S$12)+(N24-LOOKUP(N24,'Tax Assumptions'!$P$9:$P$12,'Tax Assumptions'!$P$9:$P$12))*LOOKUP(N24,'Tax Assumptions'!$P$9:$P$12,'Tax Assumptions'!$R$9:$R$12)) -> 41984.06 | Q24: =H24+I24+J24+K24+L24+M24+O24+P24 -> 505340.55 | R24: =IF(C24="Working",B24-D24-E24-F24-Q24,0) -> 589060.11 | S24: =IF(C24="Working",IF(BL24="","",BL24*(1+'Model Inputs'!$B$35)^(AN24-1)),"") -> 92741.926 | T24: =IF(C24="Working",IF(BM24="","",BM24*(1+'Model Inputs'!$B$36)^(AN24-1)),"") -> 57963.704 | U24: =IF(C24="Working",R24-S24-T24,0) -> 438354.49 | V24: =IF(C24="Working",MIN(MAX(U24,0),'Tax Assumptions'!$B$20),0) -> 7500 | W24: =IF(C24="Working",U24-V24,0) -> 430854.49 | X24: =IF(C24="Working",W24+V24+D24+E24,0) -> 462854.49 | Y24: =IF(C24="Retired",$B$13,0) -> 0 | Z24: =AA24+AB24+AC24+AD24 -> 0 | AA24: =IF(C24="Retired",MIN(Y24,((AE23)*(1+$B$15)+IF(C24="Working",W24,0))),0) -> 0 | AB24: =IF(C24="Retired",MIN(MAX(Y24-AA24,0),((AF23)*(1+$B$15)+IF(C24="Working",D24,0))),0) -> 0 | AC24: =IF(C24="Retired",MIN(MAX(Y24-AA24-AB24,0),((AG23)*(1+$B$15)+IF(C24="Working",V24,0))),0) -> 0 | AD24: =IF(C24="Retired",MIN(MAX(Y24-AA24-AB24-AC24,0),((AH23)*(1+$B$15)+IF(C24="Working",E24,0))),0) -> 0 | AE24: =MAX(((AE23)*(1+$B$15)+IF(C24="Working",W24,0))-AA24,0) -> 1943183.1 | AF24: =MAX(((AF23)*(1+$B$15)+IF(C24="Working",D24,0))-AB24,0) -> 170895.3 | AG24: =MAX(((AG23)*(1+$B$15)+IF(C24="Working",V24,0))-AC24,0) -> 52314.889 | AH24: =MAX(((AH23)*(1+$B$15)+IF(C24="Working",E24,0))-AD24,0) -> 0 | AI24: =AE24+AF24+AG24+AH24 -> 2166393.3 | AJ24: =IF(C24="Working",AJ23+X24,MAX(AJ23-MIN(Y24,AJ23),0)) -> 1889629.8 | AK24: =IF(C24="Working",AK23*(1+$B$16)+X24,MAX(AK23*(1+$B$16)-MIN(Y24,AK23*(1+$B$16)),0)) -> 2269978.7 | AL24: =IF(C24="Working",IF(B24=0,0,W24/B24),0) -> 0.38506947 | AM24: =IF(C24="Working",IF(B24=0,0,X24/B24),0) -> 0.41366897 | AN24: =A24 -> 6 | AO24: ='Model Inputs'!$B$22+AN24-1 -> 2031 | AP24: =IF(AND(AQ24="",AR24="",AX24="",BA24="",BC24=""),"",IF(AN24=1,(13-'Model Inputs'!$B$23)/12,1)) -> 1 | AQ24: =IF(OR(AN24<='Model Inputs'!$B$24,AR24<>"",AX24<>"",BA24<>"",BC24<>""),'Model Inputs'!$B$25*(1+'Model Inputs'!$B$31)^(AN24-1),"") -> 300000 | AS24: =IF(AP24="","",IF(AR24="",AQ24,AR24)) -> 300000 | AT24: =IF(AS24="","",AP24*AS24) -> 300000 | AU24: =IF(AP24="","",IF(AN24=1,(13-'Model Inputs'!$B$23)/12*'Model Inputs'!$B$27,IF(AN24=2,'Model Inputs'!$B$27,IF(AN24<=MAX(3,'Model Inputs'!$B$30+1),'Model Inputs'!$B$27*(1+'Model Inputs'!$B$28)^(AN24-3),'Model Inputs'!$B$27*(1+'Model Inputs'!$B$28)^(MAX(3,'Model Inputs'!$B$30+1)-3)*(1+'Model Inputs'!$B$29)^(AN24-MAX(3,'Model Inputs'!$B$30+1)))))) -> 1207333.6 | AV24: =IF(AU24="","",IF(AN24<=2,0,'Model Inputs'!$B$32*SIN(2*PI()*(AN24-3+'Model Inputs'!$B$34)/MAX(1,'Model Inputs'!$B$33)))) -> -2.9391523e-17 | AY24: =IF(AP24="","",IF(AX24<>"",AX24,AU24*(1+IF(AW24="",AV24,AW24)))) -> 1207333.6 | AZ24: =IF(AN24=1,'Model Inputs'!$B$26,"") | BA24: 0 | BB24: =IF(AND(AS24="",BJ24="",AZ24="",BA24="",BC24="",BD24=""),"",IF(BD24<>"",BD24,IF(BC24<>"",BC24,AT24+IF(BJ24="",0,BJ24)+IF(AZ24="",0,AZ24)+IF(BA24="",0,BA24)))) -> 1118900.7 | BD24: =IF(AND(BF24="",BG24="",BE23="",BE22=""),"",IF(BF24<>"",BF24,IF(AT24="",0,AT24))+0.75*IF(BE23<>"",BE23,IF(AY23="",0,AY23))+0.25*IF(BE22<>"",BE22,IF(AY22="",0,AY22))+IF(BG24<>"",BG24,IF(AZ24="",0,AZ24)+IF(BA24="",0,BA24))) | BJ24: =IF(AP24="","",0.75*IF(AY23="",0,AY23)+0.25*IF(AY22="",0,AY22)) -> 818900.67 | BK24: =IF(AP24="","",IF(AY24="",0,AY24)+0.25*IF(AY23="",0,AY23)) -> 1420151.8 | BL24: 80000 | BM24: 50000
A25: 7 | B25: =IF(BB25="","",BB25) -> 1418318.4 | C25: =IF(B25="","Retired","Working") -> Working | D25: =IF(OR(C25="Retired",B25=""),0,MIN(B25,'Tax Assumptions'!$B$19)) -> 24500 | E25: 0 | F25: 0 | G25: =IF(C25="Working",MAX(B25-D25-E25-'Tax Assumptions'!$B$8,0),0) -> 1377718.4 | H25: =IF(G25=0,0,LOOKUP(G25,'Tax Assumptions'!$F$9:$F$15,'Tax Assumptions'!$I$9:$I$15)+(G25-LOOKUP(G25,'Tax Assumptions'!$F$9:$F$15,'Tax Assumptions'!$F$9:$F$15))*LOOKUP(G25,'Tax Assumptions'!$F$9:$F$15,'Tax Assumptions'!$H$9:$H$15)) -> 465713.08 | I25: =IF(C25="Working",MIN(MAX(B25-E25,0),'Tax Assumptions'!$B$11)*'Tax Assumptions'!$B$10,0) -> 11439 | J25: =IF(C25="Working",MAX(B25-E25,0)*'Tax Assumptions'!$B$12,0) -> 20565.618 | K25: =IF(C25="Working",MAX(MAX(B25-E25,0)-'Tax Assumptions'!$B$14,0)*'Tax Assumptions'!$B$13,0) -> 10964.866 | L25: =IF(C25="Working",MIN(B25*'Tax Assumptions'!$B$15,'Tax Assumptions'!$B$16),0) -> 411.91 | M25: =IF(C25="Working",MIN(B25*'Tax Assumptions'!$B$17,'Tax Assumptions'!$B$18),0) -> 31.2 | N25: =IF(C25="Working",MAX(B25-D25-'Tax Assumptions'!$B$9,0),0) -> 1385818.4 | O25: =IF(N25=0,0,LOOKUP(N25,'Tax Assumptions'!$K$9:$K$17,'Tax Assumptions'!$N$9:$N$17)+(N25-LOOKUP(N25,'Tax Assumptions'!$K$9:$K$17,'Tax Assumptions'!$K$9:$K$17))*LOOKUP(N25,'Tax Assumptions'!$K$9:$K$17,'Tax Assumptions'!$M$9:$M$17)) -> 100945.54 | P25: =IF(N25=0,0,LOOKUP(N25,'Tax Assumptions'!$P$9:$P$12,'Tax Assumptions'!$S$9:$S$12)+(N25-LOOKUP(N25,'Tax Assumptions'!$P$9:$P$12,'Tax Assumptions'!$P$9:$P$12))*LOOKUP(N25,'Tax Assumptions'!$P$9:$P$12,'Tax Assumptions'!$R$9:$R$12)) -> 53589.493 | Q25: =H25+I25+J25+K25+L25+M25+O25+P25 -> 663660.7 | R25: =IF(C25="Working",B25-D25-E25-F25-Q25,0) -> 730157.75 | S25: =IF(C25="Working",IF(BL25="","",BL25*(1+'Model Inputs'!$B$35)^(AN25-1)),"") -> 95524.184 | T25: =IF(C25="Working",IF(BM25="","",BM25*(1+'Model Inputs'!$B$36)^(AN25-1)),"") -> 59702.615 | U25: =IF(C25="Working",R25-S25-T25,0) -> 574930.95 | V25: =IF(C25="Working",MIN(MAX(U25,0),'Tax Assumptions'!$B$20),0) -> 7500 | W25: =IF(C25="Working",U25-V25,0) -> 567430.95 | X25: =IF(C25="Working",W25+V25+D25+E25,0) -> 599430.95 | Y25: =IF(C25="Retired",$B$13,0) -> 0 | Z25: =AA25+AB25+AC25+AD25 -> 0 | AA25: =IF(C25="Retired",MIN(Y25,((AE24)*(1+$B$15)+IF(C25="Working",W25,0))),0) -> 0 | AB25: =IF(C25="Retired",MIN(MAX(Y25-AA25,0),((AF24)*(1+$B$15)+IF(C25="Working",D25,0))),0) -> 0 | AC25: =IF(C25="Retired",MIN(MAX(Y25-AA25-AB25,0),((AG24)*(1+$B$15)+IF(C25="Working",V25,0))),0) -> 0 | AD25: =IF(C25="Retired",MIN(MAX(Y25-AA25-AB25-AC25,0),((AH24)*(1+$B$15)+IF(C25="Working",E25,0))),0) -> 0 | AE25: =MAX(((AE24)*(1+$B$15)+IF(C25="Working",W25,0))-AA25,0) -> 2627205 | AF25: =MAX(((AF24)*(1+$B$15)+IF(C25="Working",D25,0))-AB25,0) -> 205649.02 | AG25: =MAX(((AG24)*(1+$B$15)+IF(C25="Working",V25,0))-AC25,0) -> 62953.782 | AH25: =MAX(((AH24)*(1+$B$15)+IF(C25="Working",E25,0))-AD25,0) -> 0 | AI25: =AE25+AF25+AG25+AH25 -> 2895807.8 | AJ25: =IF(C25="Working",AJ24+X25,MAX(AJ24-MIN(Y25,AJ24),0)) -> 2489060.7 | AK25: =IF(C25="Working",AK24*(1+$B$16)+X25,MAX(AK24*(1+$B$16)-MIN(Y25,AK24*(1+$B$16)),0)) -> 3051008 | AL25: =IF(C25="Working",IF(B25=0,0,W25/B25),0) -> 0.40007303 | AM25: =IF(C25="Working",IF(B25=0,0,X25/B25),0) -> 0.42263495 | AN25: =A25 -> 7 | AO25: ='Model Inputs'!$B$22+AN25-1 -> 2032 | AP25: =IF(AND(AQ25="",AR25="",AX25="",BA25="",BC25=""),"",IF(AN25=1,(13-'Model Inputs'!$B$23)/12,1)) -> 1 | AQ25: =IF(OR(AN25<='Model Inputs'!$B$24,AR25<>"",AX25<>"",BA25<>"",BC25<>""),'Model Inputs'!$B$25*(1+'Model Inputs'!$B$31)^(AN25-1),"") -> 300000 | AS25: =IF(AP25="","",IF(AR25="",AQ25,AR25)) -> 300000 | AT25: =IF(AS25="","",AP25*AS25) -> 300000 | AU25: =IF(AP25="","",IF(AN25=1,(13-'Model Inputs'!$B$23)/12*'Model Inputs'!$B$27,IF(AN25=2,'Model Inputs'!$B$27,IF(AN25<=MAX(3,'Model Inputs'!$B$30+1),'Model Inputs'!$B$27*(1+'Model Inputs'!$B$28)^(AN25-3),'Model Inputs'!$B$27*(1+'Model Inputs'!$B$28)^(MAX(3,'Model Inputs'!$B$30+1)-3)*(1+'Model Inputs'!$B$29)^(AN25-MAX(3,'Model Inputs'!$B$30+1)))))) -> 1534373 | AV25: =IF(AU25="","",IF(AN25<=2,0,'Model Inputs'!$B$32*SIN(2*PI()*(AN25-3+'Model Inputs'!$B$34)/MAX(1,'Model Inputs'!$B$33)))) -> 0.10392305 | AY25: =IF(AP25="","",IF(AX25<>"",AX25,AU25*(1+IF(AW25="",AV25,AW25)))) -> 1693829.7 | AZ25: =IF(AN25=1,'Model Inputs'!$B$26,"") | BA25: 0 | BB25: =IF(AND(AS25="",BJ25="",AZ25="",BA25="",BC25="",BD25=""),"",IF(BD25<>"",BD25,IF(BC25<>"",BC25,AT25+IF(BJ25="",0,BJ25)+IF(AZ25="",0,AZ25)+IF(BA25="",0,BA25)))) -> 1418318.4 | BD25: =IF(AND(BF25="",BG25="",BE24="",BE23=""),"",IF(BF25<>"",BF25,IF(AT25="",0,AT25))+0.75*IF(BE24<>"",BE24,IF(AY24="",0,AY24))+0.25*IF(BE23<>"",BE23,IF(AY23="",0,AY23))+IF(BG25<>"",BG25,IF(AZ25="",0,AZ25)+IF(BA25="",0,BA25))) | BJ25: =IF(AP25="","",0.75*IF(AY24="",0,AY24)+0.25*IF(AY23="",0,AY23)) -> 1118318.4 | BK25: =IF(AP25="","",IF(AY25="",0,AY25)+0.25*IF(AY24="",0,AY24)) -> 1995663.1 | BL25: 80000 | BM25: 50000
A26: 8 | B26: =IF(BB26="","",BB26) -> 1872205.7 | C26: =IF(B26="","Retired","Working") -> Working | D26: =IF(OR(C26="Retired",B26=""),0,MIN(B26,'Tax Assumptions'!$B$19)) -> 24500 | E26: 0 | F26: 0 | G26: =IF(C26="Working",MAX(B26-D26-E26-'Tax Assumptions'!$B$8,0),0) -> 1831605.7 | H26: =IF(G26=0,0,LOOKUP(G26,'Tax Assumptions'!$F$9:$F$15,'Tax Assumptions'!$I$9:$I$15)+(G26-LOOKUP(G26,'Tax Assumptions'!$F$9:$F$15,'Tax Assumptions'!$F$9:$F$15))*LOOKUP(G26,'Tax Assumptions'!$F$9:$F$15,'Tax Assumptions'!$H$9:$H$15)) -> 633651.35 | I26: =IF(C26="Working",MIN(MAX(B26-E26,0),'Tax Assumptions'!$B$11)*'Tax Assumptions'!$B$10,0) -> 11439 | J26: =IF(C26="Working",MAX(B26-E26,0)*'Tax Assumptions'!$B$12,0) -> 27146.982 | K26: =IF(C26="Working",MAX(MAX(B26-E26,0)-'Tax Assumptions'!$B$14,0)*'Tax Assumptions'!$B$13,0) -> 15049.851 | L26: =IF(C26="Working",MIN(B26*'Tax Assumptions'!$B$15,'Tax Assumptions'!$B$16),0) -> 411.91 | M26: =IF(C26="Working",MIN(B26*'Tax Assumptions'!$B$17,'Tax Assumptions'!$B$18),0) -> 31.2 | N26: =IF(C26="Working",MAX(B26-D26-'Tax Assumptions'!$B$9,0),0) -> 1839705.7 | O26: =IF(N26=0,0,LOOKUP(N26,'Tax Assumptions'!$K$9:$K$17,'Tax Assumptions'!$N$9:$N$17)+(N26-LOOKUP(N26,'Tax Assumptions'!$K$9:$K$17,'Tax Assumptions'!$K$9:$K$17))*LOOKUP(N26,'Tax Assumptions'!$K$9:$K$17,'Tax Assumptions'!$M$9:$M$17)) -> 144745.65 | P26: =IF(N26=0,0,LOOKUP(N26,'Tax Assumptions'!$P$9:$P$12,'Tax Assumptions'!$S$9:$S$12)+(N26-LOOKUP(N26,'Tax Assumptions'!$P$9:$P$12,'Tax Assumptions'!$P$9:$P$12))*LOOKUP(N26,'Tax Assumptions'!$P$9:$P$12,'Tax Assumptions'!$R$9:$R$12)) -> 71182.162 | Q26: =H26+I26+J26+K26+L26+M26+O26+P26 -> 903658.1 | R26: =IF(C26="Working",B26-D26-E26-F26-Q26,0) -> 944047.56 | S26: =IF(C26="Working",IF(BL26="","",BL26*(1+'Model Inputs'!$B$35)^(AN26-1)),"") -> 98389.909 | T26: =IF(C26="Working",IF(BM26="","",BM26*(1+'Model Inputs'!$B$36)^(AN26-1)),"") -> 61493.693 | U26: =IF(C26="Working",R26-S26-T26,0) -> 784163.96 | V26: =IF(C26="Working",MIN(MAX(U26,0),'Tax Assumptions'!$B$20),0) -> 7500 | W26: =IF(C26="Working",U26-V26,0) -> 776663.96 | X26: =IF(C26="Working",W26+V26+D26+E26,0) -> 808663.96 | Y26: =IF(C26="Retired",$B$13,0) -> 0 | Z26: =AA26+AB26+AC26+AD26 -> 0 | AA26: =IF(C26="Retired",MIN(Y26,((AE25)*(1+$B$15)+IF(C26="Working",W26,0))),0) -> 0 | AB26: =IF(C26="Retired",MIN(MAX(Y26-AA26,0),((AF25)*(1+$B$15)+IF(C26="Working",D26,0))),0) -> 0 | AC26: =IF(C26="Retired",MIN(MAX(Y26-AA26-AB26,0),((AG25)*(1+$B$15)+IF(C26="Working",V26,0))),0) -> 0 | AD26: =IF(C26="Retired",MIN(MAX(Y26-AA26-AB26-AC26,0),((AH25)*(1+$B$15)+IF(C26="Working",E26,0))),0) -> 0 | AE26: =MAX(((AE25)*(1+$B$15)+IF(C26="Working",W26,0))-AA26,0) -> 3561501.3 | AF26: =MAX(((AF25)*(1+$B$15)+IF(C26="Working",D26,0))-AB26,0) -> 242487.96 | AG26: =MAX(((AG25)*(1+$B$15)+IF(C26="Working",V26,0))-AC26,0) -> 74231.009 | AH26: =MAX(((AH25)*(1+$B$15)+IF(C26="Working",E26,0))-AD26,0) -> 0 | AI26: =AE26+AF26+AG26+AH26 -> 3878220.2 | AJ26: =IF(C26="Working",AJ25+X26,MAX(AJ25-MIN(Y26,AJ25),0)) -> 3297724.7 | AK26: =IF(C26="Working",AK25*(1+$B$16)+X26,MAX(AK25*(1+$B$16)-MIN(Y26,AK25*(1+$B$16)),0)) -> 4103752.6 | AL26: =IF(C26="Working",IF(B26=0,0,W26/B26),0) -> 0.41483902 | AM26: =IF(C26="Working",IF(B26=0,0,X26/B26),0) -> 0.43193116 | AN26: =A26 -> 8 | AO26: ='Model Inputs'!$B$22+AN26-1 -> 2033 | AP26: =IF(AND(AQ26="",AR26="",AX26="",BA26="",BC26=""),"",IF(AN26=1,(13-'Model Inputs'!$B$23)/12,1)) -> 1 | AQ26: =IF(OR(AN26<='Model Inputs'!$B$24,AR26<>"",AX26<>"",BA26<>"",BC26<>""),'Model Inputs'!$B$25*(1+'Model Inputs'!$B$31)^(AN26-1),"") -> 300000 | AS26: =IF(AP26="","",IF(AR26="",AQ26,AR26)) -> 300000 | AT26: =IF(AS26="","",AP26*AS26) -> 300000 | AU26: =IF(AP26="","",IF(AN26=1,(13-'Model Inputs'!$B$23)/12*'Model Inputs'!$B$27,IF(AN26=2,'Model Inputs'!$B$27,IF(AN26<=MAX(3,'Model Inputs'!$B$30+1),'Model Inputs'!$B$27*(1+'Model Inputs'!$B$28)^(AN26-3),'Model Inputs'!$B$27*(1+'Model Inputs'!$B$28)^(MAX(3,'Model Inputs'!$B$30+1)-3)*(1+'Model Inputs'!$B$29)^(AN26-MAX(3,'Model Inputs'!$B$30+1)))))) -> 1950000 | AV26: =IF(AU26="","",IF(AN26<=2,0,'Model Inputs'!$B$32*SIN(2*PI()*(AN26-3+'Model Inputs'!$B$34)/MAX(1,'Model Inputs'!$B$33)))) -> -0.10392305 | AY26: =IF(AP26="","",IF(AX26<>"",AX26,AU26*(1+IF(AW26="",AV26,AW26)))) -> 1747350.1 | AZ26: =IF(AN26=1,'Model Inputs'!$B$26,"") | BA26: 0 | BB26: =IF(AND(AS26="",BJ26="",AZ26="",BA26="",BC26="",BD26=""),"",IF(BD26<>"",BD26,IF(BC26<>"",BC26,AT26+IF(BJ26="",0,BJ26)+IF(AZ26="",0,AZ26)+IF(BA26="",0,BA26)))) -> 1872205.7 | BD26: =IF(AND(BF26="",BG26="",BE25="",BE24=""),"",IF(BF26<>"",BF26,IF(AT26="",0,AT26))+0.75*IF(BE25<>"",BE25,IF(AY25="",0,AY25))+0.25*IF(BE24<>"",BE24,IF(AY24="",0,AY24))+IF(BG26<>"",BG26,IF(AZ26="",0,AZ26)+IF(BA26="",0,BA26))) | BJ26: =IF(AP26="","",0.75*IF(AY25="",0,AY25)+0.25*IF(AY24="",0,AY24)) -> 1572205.7 | BK26: =IF(AP26="","",IF(AY26="",0,AY26)+0.25*IF(AY25="",0,AY25)) -> 2170807.5 | BL26: 80000 | BM26: 50000
A27: 9 | B27: =IF(BB27="","",BB27) -> 2033970 | C27: =IF(B27="","Retired","Working") -> Working | D27: =IF(OR(C27="Retired",B27=""),0,MIN(B27,'Tax Assumptions'!$B$19)) -> 24500 | E27: 0 | F27: 0 | G27: =IF(C27="Working",MAX(B27-D27-E27-'Tax Assumptions'!$B$8,0),0) -> 1993370 | H27: =IF(G27=0,0,LOOKUP(G27,'Tax Assumptions'!$F$9:$F$15,'Tax Assumptions'!$I$9:$I$15)+(G27-LOOKUP(G27,'Tax Assumptions'!$F$9:$F$15,'Tax Assumptions'!$F$9:$F$15))*LOOKUP(G27,'Tax Assumptions'!$F$9:$F$15,'Tax Assumptions'!$H$9:$H$15)) -> 693504.14 | I27: =IF(C27="Working",MIN(MAX(B27-E27,0),'Tax Assumptions'!$B$11)*'Tax Assumptions'!$B$10,0) -> 11439 | J27: =IF(C27="Working",MAX(B27-E27,0)*'Tax Assumptions'!$B$12,0) -> 29492.565 | K27: =IF(C27="Working",MAX(MAX(B27-E27,0)-'Tax Assumptions'!$B$14,0)*'Tax Assumptions'!$B$13,0) -> 16505.73 | L27: =IF(C27="Working",MIN(B27*'Tax Assumptions'!$B$15,'Tax Assumptions'!$B$16),0) -> 411.91 | M27: =IF(C27="Working",MIN(B27*'Tax Assumptions'!$B$17,'Tax Assumptions'!$B$18),0) -> 31.2 | N27: =IF(C27="Working",MAX(B27-D27-'Tax Assumptions'!$B$9,0),0) -> 2001470 | O27: =IF(N27=0,0,LOOKUP(N27,'Tax Assumptions'!$K$9:$K$17,'Tax Assumptions'!$N$9:$N$17)+(N27-LOOKUP(N27,'Tax Assumptions'!$K$9:$K$17,'Tax Assumptions'!$K$9:$K$17))*LOOKUP(N27,'Tax Assumptions'!$K$9:$K$17,'Tax Assumptions'!$M$9:$M$17)) -> 160355.91 | P27: =IF(N27=0,0,LOOKUP(N27,'Tax Assumptions'!$P$9:$P$12,'Tax Assumptions'!$S$9:$S$12)+(N27-LOOKUP(N27,'Tax Assumptions'!$P$9:$P$12,'Tax Assumptions'!$P$9:$P$12))*LOOKUP(N27,'Tax Assumptions'!$P$9:$P$12,'Tax Assumptions'!$R$9:$R$12)) -> 77452.146 | Q27: =H27+I27+J27+K27+L27+M27+O27+P27 -> 989192.59 | R27: =IF(C27="Working",B27-D27-E27-F27-Q27,0) -> 1020277.4 | S27: =IF(C27="Working",IF(BL27="","",BL27*(1+'Model Inputs'!$B$35)^(AN27-1)),"") -> 101341.61 | T27: =IF(C27="Working",IF(BM27="","",BM27*(1+'Model Inputs'!$B$36)^(AN27-1)),"") -> 63338.504 | U27: =IF(C27="Working",R27-S27-T27,0) -> 855597.26 | V27: =IF(C27="Working",MIN(MAX(U27,0),'Tax Assumptions'!$B$20),0) -> 7500 | W27: =IF(C27="Working",U27-V27,0) -> 848097.26 | X27: =IF(C27="Working",W27+V27+D27+E27,0) -> 880097.26 | Y27: =IF(C27="Retired",$B$13,0) -> 0 | Z27: =AA27+AB27+AC27+AD27 -> 0 | AA27: =IF(C27="Retired",MIN(Y27,((AE26)*(1+$B$15)+IF(C27="Working",W27,0))),0) -> 0 | AB27: =IF(C27="Retired",MIN(MAX(Y27-AA27,0),((AF26)*(1+$B$15)+IF(C27="Working",D27,0))),0) -> 0 | AC27: =IF(C27="Retired",MIN(MAX(Y27-AA27-AB27,0),((AG26)*(1+$B$15)+IF(C27="Working",V27,0))),0) -> 0 | AD27: =IF(C27="Retired",MIN(MAX(Y27-AA27-AB27-AC27,0),((AH26)*(1+$B$15)+IF(C27="Working",E27,0))),0) -> 0 | AE27: =MAX(((AE26)*(1+$B$15)+IF(C27="Working",W27,0))-AA27,0) -> 4623288.6 | AF27: =MAX(((AF26)*(1+$B$15)+IF(C27="Working",D27,0))-AB27,0) -> 281537.24 | AG27: =MAX(((AG26)*(1+$B$15)+IF(C27="Working",V27,0))-AC27,0) -> 86184.87 | AH27: =MAX(((AH26)*(1+$B$15)+IF(C27="Working",E27,0))-AD27,0) -> 0 | AI27: =AE27+AF27+AG27+AH27 -> 4991010.7 | AJ27: =IF(C27="Working",AJ26+X27,MAX(AJ26-MIN(Y27,AJ26),0)) -> 4177822 | AK27: =IF(C27="Working",AK26*(1+$B$16)+X27,MAX(AK26*(1+$B$16)-MIN(Y27,AK26*(1+$B$16)),0)) -> 5312150 | AL27: =IF(C27="Working",IF(B27=0,0,W27/B27),0) -> 0.41696646 | AM27: =IF(C27="Working",IF(B27=0,0,X27/B27),0) -> 0.43269924 | AN27: =A27 -> 9 | AO27: ='Model Inputs'!$B$22+AN27-1 -> 2034 | AP27: =IF(AND(AQ27="",AR27="",AX27="",BA27="",BC27=""),"",IF(AN27=1,(13-'Model Inputs'!$B$23)/12,1)) -> 1 | AQ27: =IF(OR(AN27<='Model Inputs'!$B$24,AR27<>"",AX27<>"",BA27<>"",BC27<>""),'Model Inputs'!$B$25*(1+'Model Inputs'!$B$31)^(AN27-1),"") -> 300000 | AS27: =IF(AP27="","",IF(AR27="",AQ27,AR27)) -> 300000 | AT27: =IF(AS27="","",AP27*AS27) -> 300000 | AU27: =IF(AP27="","",IF(AN27=1,(13-'Model Inputs'!$B$23)/12*'Model Inputs'!$B$27,IF(AN27=2,'Model Inputs'!$B$27,IF(AN27<=MAX(3,'Model Inputs'!$B$30+1),'Model Inputs'!$B$27*(1+'Model Inputs'!$B$28)^(AN27-3),'Model Inputs'!$B$27*(1+'Model Inputs'!$B$28)^(MAX(3,'Model Inputs'!$B$30+1)-3)*(1+'Model Inputs'!$B$29)^(AN27-MAX(3,'Model Inputs'!$B$30+1)))))) -> 2478211 | AV27: =IF(AU27="","",IF(AN27<=2,0,'Model Inputs'!$B$32*SIN(2*PI()*(AN27-3+'Model Inputs'!$B$34)/MAX(1,'Model Inputs'!$B$33)))) -> -5.8783046e-17 | AY27: =IF(AP27="","",IF(AX27<>"",AX27,AU27*(1+IF(AW27="",AV27,AW27)))) -> 2478211 | AZ27: =IF(AN27=1,'Model Inputs'!$B$26,"") | BA27: 0 | BB27: =IF(AND(AS27="",BJ27="",AZ27="",BA27="",BC27="",BD27=""),"",IF(BD27<>"",BD27,IF(BC27<>"",BC27,AT27+IF(BJ27="",0,BJ27)+IF(AZ27="",0,AZ27)+IF(BA27="",0,BA27)))) -> 2033970 | BD27: =IF(AND(BF27="",BG27="",BE26="",BE25=""),"",IF(BF27<>"",BF27,IF(AT27="",0,AT27))+0.75*IF(BE26<>"",BE26,IF(AY26="",0,AY26))+0.25*IF(BE25<>"",BE25,IF(AY25="",0,AY25))+IF(BG27<>"",BG27,IF(AZ27="",0,AZ27)+IF(BA27="",0,BA27))) | BJ27: =IF(AP27="","",0.75*IF(AY26="",0,AY26)+0.25*IF(AY25="",0,AY25)) -> 1733970 | BK27: =IF(AP27="","",IF(AY27="",0,AY27)+0.25*IF(AY26="",0,AY26)) -> 2915048.5 | BL27: 80000 | BM27: 50000
A28: 10 | B28: =IF(BB28="","",BB28) -> 2595495.8 | C28: =IF(B28="","Retired","Working") -> Working | D28: =IF(OR(C28="Retired",B28=""),0,MIN(B28,'Tax Assumptions'!$B$19)) -> 24500 | E28: 0 | F28: 0 | G28: =IF(C28="Working",MAX(B28-D28-E28-'Tax Assumptions'!$B$8,0),0) -> 2554895.8 | H28: =IF(G28=0,0,LOOKUP(G28,'Tax Assumptions'!$F$9:$F$15,'Tax Assumptions'!$I$9:$I$15)+(G28-LOOKUP(G28,'Tax Assumptions'!$F$9:$F$15,'Tax Assumptions'!$F$9:$F$15))*LOOKUP(G28,'Tax Assumptions'!$F$9:$F$15,'Tax Assumptions'!$H$9:$H$15)) -> 901268.68 | I28: =IF(C28="Working",MIN(MAX(B28-E28,0),'Tax Assumptions'!$B$11)*'Tax Assumptions'!$B$10,0) -> 11439 | J28: =IF(C28="Working",MAX(B28-E28,0)*'Tax Assumptions'!$B$12,0) -> 37634.689 | K28: =IF(C28="Working",MAX(MAX(B28-E28,0)-'Tax Assumptions'!$B$14,0)*'Tax Assumptions'!$B$13,0) -> 21559.462 | L28: =IF(C28="Working",MIN(B28*'Tax Assumptions'!$B$15,'Tax Assumptions'!$B$16),0) -> 411.91 | M28: =IF(C28="Working",MIN(B28*'Tax Assumptions'!$B$17,'Tax Assumptions'!$B$18),0) -> 31.2 | N28: =IF(C28="Working",MAX(B28-D28-'Tax Assumptions'!$B$9,0),0) -> 2562995.8 | O28: =IF(N28=0,0,LOOKUP(N28,'Tax Assumptions'!$K$9:$K$17,'Tax Assumptions'!$N$9:$N$17)+(N28-LOOKUP(N28,'Tax Assumptions'!$K$9:$K$17,'Tax Assumptions'!$K$9:$K$17))*LOOKUP(N28,'Tax Assumptions'!$K$9:$K$17,'Tax Assumptions'!$M$9:$M$17)) -> 214543.15 | P28: =IF(N28=0,0,LOOKUP(N28,'Tax Assumptions'!$P$9:$P$12,'Tax Assumptions'!$S$9:$S$12)+(N28-LOOKUP(N28,'Tax Assumptions'!$P$9:$P$12,'Tax Assumptions'!$P$9:$P$12))*LOOKUP(N28,'Tax Assumptions'!$P$9:$P$12,'Tax Assumptions'!$R$9:$R$12)) -> 99216.886 | Q28: =H28+I28+J28+K28+L28+M28+O28+P28 -> 1286105 | R28: =IF(C28="Working",B28-D28-E28-F28-Q28,0) -> 1284890.8 | S28: =IF(C28="Working",IF(BL28="","",BL28*(1+'Model Inputs'!$B$35)^(AN28-1)),"") -> 104381.85 | T28: =IF(C28="Working",IF(BM28="","",BM28*(1+'Model Inputs'!$B$36)^(AN28-1)),"") -> 65238.659 | U28: =IF(C28="Working",R28-S28-T28,0) -> 1115270.3 | V28: =IF(C28="Working",MIN(MAX(U28,0),'Tax Assumptions'!$B$20),0) -> 7500 | W28: =IF(C28="Working",U28-V28,0) -> 1107770.3 | X28: =IF(C28="Working",W28+V28+D28+E28,0) -> 1139770.3 | Y28: =IF(C28="Retired",$B$13,0) -> 0 | Z28: =AA28+AB28+AC28+AD28 -> 0 | AA28: =IF(C28="Retired",MIN(Y28,((AE27)*(1+$B$15)+IF(C28="Working",W28,0))),0) -> 0 | AB28: =IF(C28="Retired",MIN(MAX(Y28-AA28,0),((AF27)*(1+$B$15)+IF(C28="Working",D28,0))),0) -> 0 | AC28: =IF(C28="Retired",MIN(MAX(Y28-AA28-AB28,0),((AG27)*(1+$B$15)+IF(C28="Working",V28,0))),0) -> 0 | AD28: =IF(C28="Retired",MIN(MAX(Y28-AA28-AB28-AC28,0),((AH27)*(1+$B$15)+IF(C28="Working",E28,0))),0) -> 0 | AE28: =MAX(((AE27)*(1+$B$15)+IF(C28="Working",W28,0))-AA28,0) -> 6008456.2 | AF28: =MAX(((AF27)*(1+$B$15)+IF(C28="Working",D28,0))-AB28,0) -> 322929.48 | AG28: =MAX(((AG27)*(1+$B$15)+IF(C28="Working",V28,0))-AC28,0) -> 98855.962 | AH28: =MAX(((AH27)*(1+$B$15)+IF(C28="Working",E28,0))-AD28,0) -> 0 | AI28: =AE28+AF28+AG28+AH28 -> 6430241.6 | AJ28: =IF(C28="Working",AJ27+X28,MAX(AJ27-MIN(Y28,AJ27),0)) -> 5317592.2 | AK28: =IF(C28="Working",AK27*(1+$B$16)+X28,MAX(AK27*(1+$B$16)-MIN(Y28,AK27*(1+$B$16)),0)) -> 6876892.3 | AL28: =IF(C28="Working",IF(B28=0,0,W28/B28),0) -> 0.42680489 | AM28: =IF(C28="Working",IF(B28=0,0,X28/B28),0) -> 0.43913394 | AN28: =A28 -> 10 | AO28: ='Model Inputs'!$B$22+AN28-1 -> 2035 | AP28: =IF(AND(AQ28="",AR28="",AX28="",BA28="",BC28=""),"",IF(AN28=1,(13-'Model Inputs'!$B$23)/12,1)) -> 1 | AQ28: =IF(OR(AN28<='Model Inputs'!$B$24,AR28<>"",AX28<>"",BA28<>"",BC28<>""),'Model Inputs'!$B$25*(1+'Model Inputs'!$B$31)^(AN28-1),"") -> 300000 | AS28: =IF(AP28="","",IF(AR28="",AQ28,AR28)) -> 300000 | AT28: =IF(AS28="","",AP28*AS28) -> 300000 | AU28: =IF(AP28="","",IF(AN28=1,(13-'Model Inputs'!$B$23)/12*'Model Inputs'!$B$27,IF(AN28=2,'Model Inputs'!$B$27,IF(AN28<=MAX(3,'Model Inputs'!$B$30+1),'Model Inputs'!$B$27*(1+'Model Inputs'!$B$28)^(AN28-3),'Model Inputs'!$B$27*(1+'Model Inputs'!$B$28)^(MAX(3,'Model Inputs'!$B$30+1)-3)*(1+'Model Inputs'!$B$29)^(AN28-MAX(3,'Model Inputs'!$B$30+1)))))) -> 3149502.4 | AV28: =IF(AU28="","",IF(AN28<=2,0,'Model Inputs'!$B$32*SIN(2*PI()*(AN28-3+'Model Inputs'!$B$34)/MAX(1,'Model Inputs'!$B$33)))) -> 0.10392305 | AY28: =IF(AP28="","",IF(AX28<>"",AX28,AU28*(1+IF(AW28="",AV28,AW28)))) -> 3476808.3 | AZ28: =IF(AN28=1,'Model Inputs'!$B$26,"") | BA28: 0 | BB28: =IF(AND(AS28="",BJ28="",AZ28="",BA28="",BC28="",BD28=""),"",IF(BD28<>"",BD28,IF(BC28<>"",BC28,AT28+IF(BJ28="",0,BJ28)+IF(AZ28="",0,AZ28)+IF(BA28="",0,BA28)))) -> 2595495.8 | BD28: =IF(AND(BF28="",BG28="",BE27="",BE26=""),"",IF(BF28<>"",BF28,IF(AT28="",0,AT28))+0.75*IF(BE27<>"",BE27,IF(AY27="",0,AY27))+0.25*IF(BE26<>"",BE26,IF(AY26="",0,AY26))+IF(BG28<>"",BG28,IF(AZ28="",0,AZ28)+IF(BA28="",0,BA28))) | BJ28: =IF(AP28="","",0.75*IF(AY27="",0,AY27)+0.25*IF(AY26="",0,AY26)) -> 2295495.8 | BK28: =IF(AP28="","",IF(AY28="",0,AY28)+0.25*IF(AY27="",0,AY27)) -> 4096361.1 | BL28: 80000 | BM28: 50000
A29: 11 | B29: =IF(BB29="","",BB29) | C29: =IF(B29="","Retired","Working") -> Retired | D29: =IF(OR(C29="Retired",B29=""),0,MIN(B29,'Tax Assumptions'!$B$19)) -> 0 | G29: =IF(C29="Working",MAX(B29-D29-E29-'Tax Assumptions'!$B$8,0),0) -> 0 | H29: =IF(G29=0,0,LOOKUP(G29,'Tax Assumptions'!$F$9:$F$15,'Tax Assumptions'!$I$9:$I$15)+(G29-LOOKUP(G29,'Tax Assumptions'!$F$9:$F$15,'Tax Assumptions'!$F$9:$F$15))*LOOKUP(G29,'Tax Assumptions'!$F$9:$F$15,'Tax Assumptions'!$H$9:$H$15)) -> 0 | I29: =IF(C29="Working",MIN(MAX(B29-E29,0),'Tax Assumptions'!$B$11)*'Tax Assumptions'!$B$10,0) -> 0 | J29: =IF(C29="Working",MAX(B29-E29,0)*'Tax Assumptions'!$B$12,0) -> 0 | K29: =IF(C29="Working",MAX(MAX(B29-E29,0)-'Tax Assumptions'!$B$14,0)*'Tax Assumptions'!$B$13,0) -> 0 | L29: =IF(C29="Working",MIN(B29*'Tax Assumptions'!$B$15,'Tax Assumptions'!$B$16),0) -> 0 | M29: =IF(C29="Working",MIN(B29*'Tax Assumptions'!$B$17,'Tax Assumptions'!$B$18),0) -> 0 | N29: =IF(C29="Working",MAX(B29-D29-'Tax Assumptions'!$B$9,0),0) -> 0 | O29: =IF(N29=0,0,LOOKUP(N29,'Tax Assumptions'!$K$9:$K$17,'Tax Assumptions'!$N$9:$N$17)+(N29-LOOKUP(N29,'Tax Assumptions'!$K$9:$K$17,'Tax Assumptions'!$K$9:$K$17))*LOOKUP(N29,'Tax Assumptions'!$K$9:$K$17,'Tax Assumptions'!$M$9:$M$17)) -> 0 | P29: =IF(N29=0,0,LOOKUP(N29,'Tax Assumptions'!$P$9:$P$12,'Tax Assumptions'!$S$9:$S$12)+(N29-LOOKUP(N29,'Tax Assumptions'!$P$9:$P$12,'Tax Assumptions'!$P$9:$P$12))*LOOKUP(N29,'Tax Assumptions'!$P$9:$P$12,'Tax Assumptions'!$R$9:$R$12)) -> 0 | Q29: =H29+I29+J29+K29+L29+M29+O29+P29 -> 0 | R29: =IF(C29="Working",B29-D29-E29-F29-Q29,0) -> 0 | S29: =IF(C29="Working",IF(BL29="","",BL29*(1+'Model Inputs'!$B$35)^(AN29-1)),"") | T29: =IF(C29="Working",IF(BM29="","",BM29*(1+'Model Inputs'!$B$36)^(AN29-1)),"") | U29: =IF(C29="Working",R29-S29-T29,0) -> 0 | V29: =IF(C29="Working",MIN(MAX(U29,0),'Tax Assumptions'!$B$20),0) -> 0 | W29: =IF(C29="Working",U29-V29,0) -> 0 | X29: =IF(C29="Working",W29+V29+D29+E29,0) -> 0 | Y29: =IF(C29="Retired",$B$13,0) -> 200000 | Z29: =AA29+AB29+AC29+AD29 -> 200000 | AA29: =IF(C29="Retired",MIN(Y29,((AE28)*(1+$B$15)+IF(C29="Working",W29,0))),0) -> 200000 | AB29: =IF(C29="Retired",MIN(MAX(Y29-AA29,0),((AF28)*(1+$B$15)+IF(C29="Working",D29,0))),0) -> 0 | AC29: =IF(C29="Retired",MIN(MAX(Y29-AA29-AB29,0),((AG28)*(1+$B$15)+IF(C29="Working",V29,0))),0) -> 0 | AD29: =IF(C29="Retired",MIN(MAX(Y29-AA29-AB29-AC29,0),((AH28)*(1+$B$15)+IF(C29="Working",E29,0))),0) -> 0 | AE29: =MAX(((AE28)*(1+$B$15)+IF(C29="Working",W29,0))-AA29,0) -> 6168963.6 | AF29: =MAX(((AF28)*(1+$B$15)+IF(C29="Working",D29,0))-AB29,0) -> 342305.24 | AG29: =MAX(((AG28)*(1+$B$15)+IF(C29="Working",V29,0))-AC29,0) -> 104787.32 | AH29: =MAX(((AH28)*(1+$B$15)+IF(C29="Working",E29,0))-AD29,0) -> 0 | AI29: =AE29+AF29+AG29+AH29 -> 6616056.1 | AJ29: =IF(C29="Working",AJ28+X29,MAX(AJ28-MIN(Y29,AJ28),0)) -> 5117592.2 | AK29: =IF(C29="Working",AK28*(1+$B$16)+X29,MAX(AK28*(1+$B$16)-MIN(Y29,AK28*(1+$B$16)),0)) -> 7227043.7 | AL29: =IF(C29="Working",IF(B29=0,0,W29/B29),0) -> 0 | AM29: =IF(C29="Working",IF(B29=0,0,X29/B29),0) -> 0 | AN29: =A29 -> 11 | AO29: ='Model Inputs'!$B$22+AN29-1 -> 2036 | AP29: =IF(AND(AQ29="",AR29="",AX29="",BA29="",BC29=""),"",IF(AN29=1,(13-'Model Inputs'!$B$23)/12,1)) | AQ29: =IF(OR(AN29<='Model Inputs'!$B$24,AR29<>"",AX29<>"",BA29<>"",BC29<>""),'Model Inputs'!$B$25*(1+'Model Inputs'!$B$31)^(AN29-1),"") | AS29: =IF(AP29="","",IF(AR29="",AQ29,AR29)) | AT29: =IF(AS29="","",AP29*AS29) | AU29: =IF(AP29="","",IF(AN29=1,(13-'Model Inputs'!$B$23)/12*'Model Inputs'!$B$27,IF(AN29=2,'Model Inputs'!$B$27,IF(AN29<=MAX(3,'Model Inputs'!$B$30+1),'Model Inputs'!$B$27*(1+'Model Inputs'!$B$28)^(AN29-3),'Model Inputs'!$B$27*(1+'Model Inputs'!$B$28)^(MAX(3,'Model Inputs'!$B$30+1)-3)*(1+'Model Inputs'!$B$29)^(AN29-MAX(3,'Model Inputs'!$B$30+1)))))) | AV29: =IF(AU29="","",IF(AN29<=2,0,'Model Inputs'!$B$32*SIN(2*PI()*(AN29-3+'Model Inputs'!$B$34)/MAX(1,'Model Inputs'!$B$33)))) | AY29: =IF(AP29="","",IF(AX29<>"",AX29,AU29*(1+IF(AW29="",AV29,AW29)))) | AZ29: =IF(AN29=1,'Model Inputs'!$B$26,"") | BB29: =IF(AND(AS29="",BJ29="",AZ29="",BA29="",BC29="",BD29=""),"",IF(BD29<>"",BD29,IF(BC29<>"",BC29,AT29+IF(BJ29="",0,BJ29)+IF(AZ29="",0,AZ29)+IF(BA29="",0,BA29)))) | BD29: =IF(AND(BF29="",BG29="",BE28="",BE27=""),"",IF(BF29<>"",BF29,IF(AT29="",0,AT29))+0.75*IF(BE28<>"",BE28,IF(AY28="",0,AY28))+0.25*IF(BE27<>"",BE27,IF(AY27="",0,AY27))+IF(BG29<>"",BG29,IF(AZ29="",0,AZ29)+IF(BA29="",0,BA29))) | BJ29: =IF(AP29="","",0.75*IF(AY28="",0,AY28)+0.25*IF(AY27="",0,AY27)) | BK29: =IF(AP29="","",IF(AY29="",0,AY29)+0.25*IF(AY28="",0,AY28)) | BL29: =IF(C29="Working",LOOKUP(2,1/($BL$19:BL28<>""),$BL$19:BL28),"") | BM29: =IF(C29="Working",LOOKUP(2,1/($BM$19:BM28<>""),$BM$19:BM28),"")
A30: 12 | B30: =IF(BB30="","",BB30) | C30: =IF(B30="","Retired","Working") -> Retired | D30: =IF(OR(C30="Retired",B30=""),0,MIN(B30,'Tax Assumptions'!$B$19)) -> 0 | G30: =IF(C30="Working",MAX(B30-D30-E30-'Tax Assumptions'!$B$8,0),0) -> 0 | H30: =IF(G30=0,0,LOOKUP(G30,'Tax Assumptions'!$F$9:$F$15,'Tax Assumptions'!$I$9:$I$15)+(G30-LOOKUP(G30,'Tax Assumptions'!$F$9:$F$15,'Tax Assumptions'!$F$9:$F$15))*LOOKUP(G30,'Tax Assumptions'!$F$9:$F$15,'Tax Assumptions'!$H$9:$H$15)) -> 0 | I30: =IF(C30="Working",MIN(MAX(B30-E30,0),'Tax Assumptions'!$B$11)*'Tax Assumptions'!$B$10,0) -> 0 | J30: =IF(C30="Working",MAX(B30-E30,0)*'Tax Assumptions'!$B$12,0) -> 0 | K30: =IF(C30="Working",MAX(MAX(B30-E30,0)-'Tax Assumptions'!$B$14,0)*'Tax Assumptions'!$B$13,0) -> 0 | L30: =IF(C30="Working",MIN(B30*'Tax Assumptions'!$B$15,'Tax Assumptions'!$B$16),0) -> 0 | M30: =IF(C30="Working",MIN(B30*'Tax Assumptions'!$B$17,'Tax Assumptions'!$B$18),0) -> 0 | N30: =IF(C30="Working",MAX(B30-D30-'Tax Assumptions'!$B$9,0),0) -> 0 | O30: =IF(N30=0,0,LOOKUP(N30,'Tax Assumptions'!$K$9:$K$17,'Tax Assumptions'!$N$9:$N$17)+(N30-LOOKUP(N30,'Tax Assumptions'!$K$9:$K$17,'Tax Assumptions'!$K$9:$K$17))*LOOKUP(N30,'Tax Assumptions'!$K$9:$K$17,'Tax Assumptions'!$M$9:$M$17)) -> 0 | P30: =IF(N30=0,0,LOOKUP(N30,'Tax Assumptions'!$P$9:$P$12,'Tax Assumptions'!$S$9:$S$12)+(N30-LOOKUP(N30,'Tax Assumptions'!$P$9:$P$12,'Tax Assumptions'!$P$9:$P$12))*LOOKUP(N30,'Tax Assumptions'!$P$9:$P$12,'Tax Assumptions'!$R$9:$R$12)) -> 0 | Q30: =H30+I30+J30+K30+L30+M30+O30+P30 -> 0 | R30: =IF(C30="Working",B30-D30-E30-F30-Q30,0) -> 0 | S30: =IF(C30="Working",IF(BL30="","",BL30*(1+'Model Inputs'!$B$35)^(AN30-1)),"") | T30: =IF(C30="Working",IF(BM30="","",BM30*(1+'Model Inputs'!$B$36)^(AN30-1)),"") | U30: =IF(C30="Working",R30-S30-T30,0) -> 0 | V30: =IF(C30="Working",MIN(MAX(U30,0),'Tax Assumptions'!$B$20),0) -> 0 | W30: =IF(C30="Working",U30-V30,0) -> 0 | X30: =IF(C30="Working",W30+V30+D30+E30,0) -> 0 | Y30: =IF(C30="Retired",$B$13,0) -> 200000 | Z30: =AA30+AB30+AC30+AD30 -> 200000 | AA30: =IF(C30="Retired",MIN(Y30,((AE29)*(1+$B$15)+IF(C30="Working",W30,0))),0) -> 200000 | AB30: =IF(C30="Retired",MIN(MAX(Y30-AA30,0),((AF29)*(1+$B$15)+IF(C30="Working",D30,0))),0) -> 0 | AC30: =IF(C30="Retired",MIN(MAX(Y30-AA30-AB30,0),((AG29)*(1+$B$15)+IF(C30="Working",V30,0))),0) -> 0 | AD30: =IF(C30="Retired",MIN(MAX(Y30-AA30-AB30-AC30,0),((AH29)*(1+$B$15)+IF(C30="Working",E30,0))),0) -> 0 | AE30: =MAX(((AE29)*(1+$B$15)+IF(C30="Working",W30,0))-AA30,0) -> 6339101.4 | AF30: =MAX(((AF29)*(1+$B$15)+IF(C30="Working",D30,0))-AB30,0) -> 362843.56 | AG30: =MAX(((AG29)*(1+$B$15)+IF(C30="Working",V30,0))-AC30,0) -> 111074.56 | AH30: =MAX(((AH29)*(1+$B$15)+IF(C30="Working",E30,0))-AD30,0) -> 0 | AI30: =AE30+AF30+AG30+AH30 -> 6813019.5 | AJ30: =IF(C30="Working",AJ29+X30,MAX(AJ29-MIN(Y30,AJ29),0)) -> 4917592.2 | AK30: =IF(C30="Working",AK29*(1+$B$16)+X30,MAX(AK29*(1+$B$16)-MIN(Y30,AK29*(1+$B$16)),0)) -> 7605207.2 | AL30: =IF(C30="Working",IF(B30=0,0,W30/B30),0) -> 0 | AM30: =IF(C30="Working",IF(B30=0,0,X30/B30),0) -> 0 | AN30: =A30 -> 12 | AO30: ='Model Inputs'!$B$22+AN30-1 -> 2037 | AP30: =IF(AND(AQ30="",AR30="",AX30="",BA30="",BC30=""),"",IF(AN30=1,(13-'Model Inputs'!$B$23)/12,1)) | AQ30: =IF(OR(AN30<='Model Inputs'!$B$24,AR30<>"",AX30<>"",BA30<>"",BC30<>""),'Model Inputs'!$B$25*(1+'Model Inputs'!$B$31)^(AN30-1),"") | AS30: =IF(AP30="","",IF(AR30="",AQ30,AR30)) | AT30: =IF(AS30="","",AP30*AS30) | AU30: =IF(AP30="","",IF(AN30=1,(13-'Model Inputs'!$B$23)/12*'Model Inputs'!$B$27,IF(AN30=2,'Model Inputs'!$B$27,IF(AN30<=MAX(3,'Model Inputs'!$B$30+1),'Model Inputs'!$B$27*(1+'Model Inputs'!$B$28)^(AN30-3),'Model Inputs'!$B$27*(1+'Model Inputs'!$B$28)^(MAX(3,'Model Inputs'!$B$30+1)-3)*(1+'Model Inputs'!$B$29)^(AN30-MAX(3,'Model Inputs'!$B$30+1)))))) | AV30: =IF(AU30="","",IF(AN30<=2,0,'Model Inputs'!$B$32*SIN(2*PI()*(AN30-3+'Model Inputs'!$B$34)/MAX(1,'Model Inputs'!$B$33)))) | AY30: =IF(AP30="","",IF(AX30<>"",AX30,AU30*(1+IF(AW30="",AV30,AW30)))) | AZ30: =IF(AN30=1,'Model Inputs'!$B$26,"") | BB30: =IF(AND(AS30="",BJ30="",AZ30="",BA30="",BC30="",BD30=""),"",IF(BD30<>"",BD30,IF(BC30<>"",BC30,AT30+IF(BJ30="",0,BJ30)+IF(AZ30="",0,AZ30)+IF(BA30="",0,BA30)))) | BD30: =IF(AND(BF30="",BG30="",BE29="",BE28=""),"",IF(BF30<>"",BF30,IF(AT30="",0,AT30))+0.75*IF(BE29<>"",BE29,IF(AY29="",0,AY29))+0.25*IF(BE28<>"",BE28,IF(AY28="",0,AY28))+IF(BG30<>"",BG30,IF(AZ30="",0,AZ30)+IF(BA30="",0,BA30))) | BJ30: =IF(AP30="","",0.75*IF(AY29="",0,AY29)+0.25*IF(AY28="",0,AY28)) | BK30: =IF(AP30="","",IF(AY30="",0,AY30)+0.25*IF(AY29="",0,AY29)) | BL30: =IF(C30="Working",LOOKUP(2,1/($BL$19:BL29<>""),$BL$19:BL29),"") | BM30: =IF(C30="Working",LOOKUP(2,1/($BM$19:BM29<>""),$BM$19:BM29),"")
A31: 13 | B31: =IF(BB31="","",BB31) | C31: =IF(B31="","Retired","Working") -> Retired | D31: =IF(OR(C31="Retired",B31=""),0,MIN(B31,'Tax Assumptions'!$B$19)) -> 0 | G31: =IF(C31="Working",MAX(B31-D31-E31-'Tax Assumptions'!$B$8,0),0) -> 0 | H31: =IF(G31=0,0,LOOKUP(G31,'Tax Assumptions'!$F$9:$F$15,'Tax Assumptions'!$I$9:$I$15)+(G31-LOOKUP(G31,'Tax Assumptions'!$F$9:$F$15,'Tax Assumptions'!$F$9:$F$15))*LOOKUP(G31,'Tax Assumptions'!$F$9:$F$15,'Tax Assumptions'!$H$9:$H$15)) -> 0 | I31: =IF(C31="Working",MIN(MAX(B31-E31,0),'Tax Assumptions'!$B$11)*'Tax Assumptions'!$B$10,0) -> 0 | J31: =IF(C31="Working",MAX(B31-E31,0)*'Tax Assumptions'!$B$12,0) -> 0 | K31: =IF(C31="Working",MAX(MAX(B31-E31,0)-'Tax Assumptions'!$B$14,0)*'Tax Assumptions'!$B$13,0) -> 0 | L31: =IF(C31="Working",MIN(B31*'Tax Assumptions'!$B$15,'Tax Assumptions'!$B$16),0) -> 0 | M31: =IF(C31="Working",MIN(B31*'Tax Assumptions'!$B$17,'Tax Assumptions'!$B$18),0) -> 0 | N31: =IF(C31="Working",MAX(B31-D31-'Tax Assumptions'!$B$9,0),0) -> 0 | O31: =IF(N31=0,0,LOOKUP(N31,'Tax Assumptions'!$K$9:$K$17,'Tax Assumptions'!$N$9:$N$17)+(N31-LOOKUP(N31,'Tax Assumptions'!$K$9:$K$17,'Tax Assumptions'!$K$9:$K$17))*LOOKUP(N31,'Tax Assumptions'!$K$9:$K$17,'Tax Assumptions'!$M$9:$M$17)) -> 0 | P31: =IF(N31=0,0,LOOKUP(N31,'Tax Assumptions'!$P$9:$P$12,'Tax Assumptions'!$S$9:$S$12)+(N31-LOOKUP(N31,'Tax Assumptions'!$P$9:$P$12,'Tax Assumptions'!$P$9:$P$12))*LOOKUP(N31,'Tax Assumptions'!$P$9:$P$12,'Tax Assumptions'!$R$9:$R$12)) -> 0 | Q31: =H31+I31+J31+K31+L31+M31+O31+P31 -> 0 | R31: =IF(C31="Working",B31-D31-E31-F31-Q31,0) -> 0 | S31: =IF(C31="Working",IF(BL31="","",BL31*(1+'Model Inputs'!$B$35)^(AN31-1)),"") | T31: =IF(C31="Working",IF(BM31="","",BM31*(1+'Model Inputs'!$B$36)^(AN31-1)),"") | U31: =IF(C31="Working",R31-S31-T31,0) -> 0 | V31: =IF(C31="Working",MIN(MAX(U31,0),'Tax Assumptions'!$B$20),0) -> 0 | W31: =IF(C31="Working",U31-V31,0) -> 0 | X31: =IF(C31="Working",W31+V31+D31+E31,0) -> 0 | Y31: =IF(C31="Retired",$B$13,0) -> 200000 | Z31: =AA31+AB31+AC31+AD31 -> 200000 | AA31: =IF(C31="Retired",MIN(Y31,((AE30)*(1+$B$15)+IF(C31="Working",W31,0))),0) -> 200000 | AB31: =IF(C31="Retired",MIN(MAX(Y31-AA31,0),((AF30)*(1+$B$15)+IF(C31="Working",D31,0))),0) -> 0 | AC31: =IF(C31="Retired",MIN(MAX(Y31-AA31-AB31,0),((AG30)*(1+$B$15)+IF(C31="Working",V31,0))),0) -> 0 | AD31: =IF(C31="Retired",MIN(MAX(Y31-AA31-AB31-AC31,0),((AH30)*(1+$B$15)+IF(C31="Working",E31,0))),0) -> 0 | AE31: =MAX(((AE30)*(1+$B$15)+IF(C31="Working",W31,0))-AA31,0) -> 6519447.5 | AF31: =MAX(((AF30)*(1+$B$15)+IF(C31="Working",D31,0))-AB31,0) -> 384614.17 | AG31: =MAX(((AG30)*(1+$B$15)+IF(C31="Working",V31,0))-AC31,0) -> 117739.03 | AH31: =MAX(((AH30)*(1+$B$15)+IF(C31="Working",E31,0))-AD31,0) -> 0 | AI31: =AE31+AF31+AG31+AH31 -> 7021800.7 | AJ31: =IF(C31="Working",AJ30+X31,MAX(AJ30-MIN(Y31,AJ30),0)) -> 4717592.2 | AK31: =IF(C31="Working",AK30*(1+$B$16)+X31,MAX(AK30*(1+$B$16)-MIN(Y31,AK30*(1+$B$16)),0)) -> 8013623.8 | AL31: =IF(C31="Working",IF(B31=0,0,W31/B31),0) -> 0 | AM31: =IF(C31="Working",IF(B31=0,0,X31/B31),0) -> 0 | AN31: =A31 -> 13 | AO31: ='Model Inputs'!$B$22+AN31-1 -> 2038 | AP31: =IF(AND(AQ31="",AR31="",AX31="",BA31="",BC31=""),"",IF(AN31=1,(13-'Model Inputs'!$B$23)/12,1)) | AQ31: =IF(OR(AN31<='Model Inputs'!$B$24,AR31<>"",AX31<>"",BA31<>"",BC31<>""),'Model Inputs'!$B$25*(1+'Model Inputs'!$B$31)^(AN31-1),"") | AS31: =IF(AP31="","",IF(AR31="",AQ31,AR31)) | AT31: =IF(AS31="","",AP31*AS31) | AU31: =IF(AP31="","",IF(AN31=1,AP31*'Model Inputs'!$B$27,IF(AN31<=MAX(2,'Model Inputs'!$B$30),'Model Inputs'!$B$27*(1+'Model Inputs'!$B$28)^(AN31-2),'Model Inputs'!$B$27*(1+'Model Inputs'!$B$28)^(MAX(2,'Model Inputs'!$B$30)-2)*(1+'Model Inputs'!$B$29)^(AN31-MAX(2,'Model Inputs'!$B$30))))) | AV31: =IF(AU31="","",IF(AN31<=2,0,'Model Inputs'!$B$32*SIN(2*PI()*(AN31-2+'Model Inputs'!$B$34)/MAX(1,'Model Inputs'!$B$33)))) | AY31: =IF(AP31="","",IF(BC31<>"",MAX(BC31-AT31-IF(AZ31="",0,AZ31)-IF(BA31="",0,BA31),0),IF(AX31<>"",AX31,AU31*(1+IF(AW31="",AV31,AW31))))) | AZ31: =IF(AN31=1,'Model Inputs'!$B$26,"") | BB31: =IF(AND(AS31="",AY31="",AZ31="",BA31="",BC31=""),"",IF(BC31<>"",BC31,AT31+IF(AY31="",0,AY31)+IF(AZ31="",0,AZ31)+IF(BA31="",0,BA31))) | BL31: =IF(C31="Working",LOOKUP(2,1/($BL$19:BL30<>""),$BL$19:BL30),"") | BM31: =IF(C31="Working",LOOKUP(2,1/($BM$19:BM30<>""),$BM$19:BM30),"")
A32: 14 | B32: =IF(BB32="","",BB32) | C32: =IF(B32="","Retired","Working") -> Retired | D32: =IF(OR(C32="Retired",B32=""),0,MIN(B32,'Tax Assumptions'!$B$19)) -> 0 | G32: =IF(C32="Working",MAX(B32-D32-E32-'Tax Assumptions'!$B$8,0),0) -> 0 | H32: =IF(G32=0,0,LOOKUP(G32,'Tax Assumptions'!$F$9:$F$15,'Tax Assumptions'!$I$9:$I$15)+(G32-LOOKUP(G32,'Tax Assumptions'!$F$9:$F$15,'Tax Assumptions'!$F$9:$F$15))*LOOKUP(G32,'Tax Assumptions'!$F$9:$F$15,'Tax Assumptions'!$H$9:$H$15)) -> 0 | I32: =IF(C32="Working",MIN(MAX(B32-E32,0),'Tax Assumptions'!$B$11)*'Tax Assumptions'!$B$10,0) -> 0 | J32: =IF(C32="Working",MAX(B32-E32,0)*'Tax Assumptions'!$B$12,0) -> 0 | K32: =IF(C32="Working",MAX(MAX(B32-E32,0)-'Tax Assumptions'!$B$14,0)*'Tax Assumptions'!$B$13,0) -> 0 | L32: =IF(C32="Working",MIN(B32*'Tax Assumptions'!$B$15,'Tax Assumptions'!$B$16),0) -> 0 | M32: =IF(C32="Working",MIN(B32*'Tax Assumptions'!$B$17,'Tax Assumptions'!$B$18),0) -> 0 | N32: =IF(C32="Working",MAX(B32-D32-'Tax Assumptions'!$B$9,0),0) -> 0 | O32: =IF(N32=0,0,LOOKUP(N32,'Tax Assumptions'!$K$9:$K$17,'Tax Assumptions'!$N$9:$N$17)+(N32-LOOKUP(N32,'Tax Assumptions'!$K$9:$K$17,'Tax Assumptions'!$K$9:$K$17))*LOOKUP(N32,'Tax Assumptions'!$K$9:$K$17,'Tax Assumptions'!$M$9:$M$17)) -> 0 | P32: =IF(N32=0,0,LOOKUP(N32,'Tax Assumptions'!$P$9:$P$12,'Tax Assumptions'!$S$9:$S$12)+(N32-LOOKUP(N32,'Tax Assumptions'!$P$9:$P$12,'Tax Assumptions'!$P$9:$P$12))*LOOKUP(N32,'Tax Assumptions'!$P$9:$P$12,'Tax Assumptions'!$R$9:$R$12)) -> 0 | Q32: =H32+I32+J32+K32+L32+M32+O32+P32 -> 0 | R32: =IF(C32="Working",B32-D32-E32-F32-Q32,0) -> 0 | S32: =IF(C32="Working",IF(BL32="","",BL32*(1+'Model Inputs'!$B$35)^(AN32-1)),"") | T32: =IF(C32="Working",IF(BM32="","",BM32*(1+'Model Inputs'!$B$36)^(AN32-1)),"") | U32: =IF(C32="Working",R32-S32-T32,0) -> 0 | V32: =IF(C32="Working",MIN(MAX(U32,0),'Tax Assumptions'!$B$20),0) -> 0 | W32: =IF(C32="Working",U32-V32,0) -> 0 | X32: =IF(C32="Working",W32+V32+D32+E32,0) -> 0 | Y32: =IF(C32="Retired",$B$13,0) -> 200000 | Z32: =AA32+AB32+AC32+AD32 -> 200000 | AA32: =IF(C32="Retired",MIN(Y32,((AE31)*(1+$B$15)+IF(C32="Working",W32,0))),0) -> 200000 | AB32: =IF(C32="Retired",MIN(MAX(Y32-AA32,0),((AF31)*(1+$B$15)+IF(C32="Working",D32,0))),0) -> 0 | AC32: =IF(C32="Retired",MIN(MAX(Y32-AA32-AB32,0),((AG31)*(1+$B$15)+IF(C32="Working",V32,0))),0) -> 0 | AD32: =IF(C32="Retired",MIN(MAX(Y32-AA32-AB32-AC32,0),((AH31)*(1+$B$15)+IF(C32="Working",E32,0))),0) -> 0 | AE32: =MAX(((AE31)*(1+$B$15)+IF(C32="Working",W32,0))-AA32,0) -> 6710614.3 | AF32: =MAX(((AF31)*(1+$B$15)+IF(C32="Working",D32,0))-AB32,0) -> 407691.02 | AG32: =MAX(((AG31)*(1+$B$15)+IF(C32="Working",V32,0))-AC32,0) -> 124803.37 | AH32: =MAX(((AH31)*(1+$B$15)+IF(C32="Working",E32,0))-AD32,0) -> 0 | AI32: =AE32+AF32+AG32+AH32 -> 7243108.7 | AJ32: =IF(C32="Working",AJ31+X32,MAX(AJ31-MIN(Y32,AJ31),0)) -> 4517592.2 | AK32: =IF(C32="Working",AK31*(1+$B$16)+X32,MAX(AK31*(1+$B$16)-MIN(Y32,AK31*(1+$B$16)),0)) -> 8454713.7 | AL32: =IF(C32="Working",IF(B32=0,0,W32/B32),0) -> 0 | AM32: =IF(C32="Working",IF(B32=0,0,X32/B32),0) -> 0 | AN32: =A32 -> 14 | AO32: ='Model Inputs'!$B$22+AN32-1 -> 2039 | AP32: =IF(AND(AQ32="",AR32="",AX32="",BA32="",BC32=""),"",IF(AN32=1,(13-'Model Inputs'!$B$23)/12,1)) | AQ32: =IF(OR(AN32<='Model Inputs'!$B$24,AR32<>"",AX32<>"",BA32<>"",BC32<>""),'Model Inputs'!$B$25*(1+'Model Inputs'!$B$31)^(AN32-1),"") | AS32: =IF(AP32="","",IF(AR32="",AQ32,AR32)) | AT32: =IF(AS32="","",AP32*AS32) | AU32: =IF(AP32="","",IF(AN32=1,AP32*'Model Inputs'!$B$27,IF(AN32<=MAX(2,'Model Inputs'!$B$30),'Model Inputs'!$B$27*(1+'Model Inputs'!$B$28)^(AN32-2),'Model Inputs'!$B$27*(1+'Model Inputs'!$B$28)^(MAX(2,'Model Inputs'!$B$30)-2)*(1+'Model Inputs'!$B$29)^(AN32-MAX(2,'Model Inputs'!$B$30))))) | AV32: =IF(AU32="","",IF(AN32<=2,0,'Model Inputs'!$B$32*SIN(2*PI()*(AN32-2+'Model Inputs'!$B$34)/MAX(1,'Model Inputs'!$B$33)))) | AY32: =IF(AP32="","",IF(BC32<>"",MAX(BC32-AT32-IF(AZ32="",0,AZ32)-IF(BA32="",0,BA32),0),IF(AX32<>"",AX32,AU32*(1+IF(AW32="",AV32,AW32))))) | AZ32: =IF(AN32=1,'Model Inputs'!$B$26,"") | BB32: =IF(AND(AS32="",AY32="",AZ32="",BA32="",BC32=""),"",IF(BC32<>"",BC32,AT32+IF(AY32="",0,AY32)+IF(AZ32="",0,AZ32)+IF(BA32="",0,BA32))) | BL32: =IF(C32="Working",LOOKUP(2,1/($BL$19:BL31<>""),$BL$19:BL31),"") | BM32: =IF(C32="Working",LOOKUP(2,1/($BM$19:BM31<>""),$BM$19:BM31),"")
A33: 15 | B33: =IF(BB33="","",BB33) | C33: =IF(B33="","Retired","Working") -> Retired | D33: =IF(OR(C33="Retired",B33=""),0,MIN(B33,'Tax Assumptions'!$B$19)) -> 0 | G33: =IF(C33="Working",MAX(B33-D33-E33-'Tax Assumptions'!$B$8,0),0) -> 0 | H33: =IF(G33=0,0,LOOKUP(G33,'Tax Assumptions'!$F$9:$F$15,'Tax Assumptions'!$I$9:$I$15)+(G33-LOOKUP(G33,'Tax Assumptions'!$F$9:$F$15,'Tax Assumptions'!$F$9:$F$15))*LOOKUP(G33,'Tax Assumptions'!$F$9:$F$15,'Tax Assumptions'!$H$9:$H$15)) -> 0 | I33: =IF(C33="Working",MIN(MAX(B33-E33,0),'Tax Assumptions'!$B$11)*'Tax Assumptions'!$B$10,0) -> 0 | J33: =IF(C33="Working",MAX(B33-E33,0)*'Tax Assumptions'!$B$12,0) -> 0 | K33: =IF(C33="Working",MAX(MAX(B33-E33,0)-'Tax Assumptions'!$B$14,0)*'Tax Assumptions'!$B$13,0) -> 0 | L33: =IF(C33="Working",MIN(B33*'Tax Assumptions'!$B$15,'Tax Assumptions'!$B$16),0) -> 0 | M33: =IF(C33="Working",MIN(B33*'Tax Assumptions'!$B$17,'Tax Assumptions'!$B$18),0) -> 0 | N33: =IF(C33="Working",MAX(B33-D33-'Tax Assumptions'!$B$9,0),0) -> 0 | O33: =IF(N33=0,0,LOOKUP(N33,'Tax Assumptions'!$K$9:$K$17,'Tax Assumptions'!$N$9:$N$17)+(N33-LOOKUP(N33,'Tax Assumptions'!$K$9:$K$17,'Tax Assumptions'!$K$9:$K$17))*LOOKUP(N33,'Tax Assumptions'!$K$9:$K$17,'Tax Assumptions'!$M$9:$M$17)) -> 0 | P33: =IF(N33=0,0,LOOKUP(N33,'Tax Assumptions'!$P$9:$P$12,'Tax Assumptions'!$S$9:$S$12)+(N33-LOOKUP(N33,'Tax Assumptions'!$P$9:$P$12,'Tax Assumptions'!$P$9:$P$12))*LOOKUP(N33,'Tax Assumptions'!$P$9:$P$12,'Tax Assumptions'!$R$9:$R$12)) -> 0 | Q33: =H33+I33+J33+K33+L33+M33+O33+P33 -> 0 | R33: =IF(C33="Working",B33-D33-E33-F33-Q33,0) -> 0 | S33: =IF(C33="Working",IF(BL33="","",BL33*(1+'Model Inputs'!$B$35)^(AN33-1)),"") | T33: =IF(C33="Working",IF(BM33="","",BM33*(1+'Model Inputs'!$B$36)^(AN33-1)),"") | U33: =IF(C33="Working",R33-S33-T33,0) -> 0 | V33: =IF(C33="Working",MIN(MAX(U33,0),'Tax Assumptions'!$B$20),0) -> 0 | W33: =IF(C33="Working",U33-V33,0) -> 0 | X33: =IF(C33="Working",W33+V33+D33+E33,0) -> 0 | Y33: =IF(C33="Retired",$B$13,0) -> 200000 | Z33: =AA33+AB33+AC33+AD33 -> 200000 | AA33: =IF(C33="Retired",MIN(Y33,((AE32)*(1+$B$15)+IF(C33="Working",W33,0))),0) -> 200000 | AB33: =IF(C33="Retired",MIN(MAX(Y33-AA33,0),((AF32)*(1+$B$15)+IF(C33="Working",D33,0))),0) -> 0 | AC33: =IF(C33="Retired",MIN(MAX(Y33-AA33-AB33,0),((AG32)*(1+$B$15)+IF(C33="Working",V33,0))),0) -> 0 | AD33: =IF(C33="Retired",MIN(MAX(Y33-AA33-AB33-AC33,0),((AH32)*(1+$B$15)+IF(C33="Working",E33,0))),0) -> 0 | AE33: =MAX(((AE32)*(1+$B$15)+IF(C33="Working",W33,0))-AA33,0) -> 6913251.2 | AF33: =MAX(((AF32)*(1+$B$15)+IF(C33="Working",D33,0))-AB33,0) -> 432152.48 | AG33: =MAX(((AG32)*(1+$B$15)+IF(C33="Working",V33,0))-AC33,0) -> 132291.58 | AH33: =MAX(((AH32)*(1+$B$15)+IF(C33="Working",E33,0))-AD33,0) -> 0 | AI33: =AE33+AF33+AG33+AH33 -> 7477695.2 | AJ33: =IF(C33="Working",AJ32+X33,MAX(AJ32-MIN(Y33,AJ32),0)) -> 4317592.2 | AK33: =IF(C33="Working",AK32*(1+$B$16)+X33,MAX(AK32*(1+$B$16)-MIN(Y33,AK32*(1+$B$16)),0)) -> 8931090.7 | AL33: =IF(C33="Working",IF(B33=0,0,W33/B33),0) -> 0 | AM33: =IF(C33="Working",IF(B33=0,0,X33/B33),0) -> 0 | AN33: =A33 -> 15 | AO33: ='Model Inputs'!$B$22+AN33-1 -> 2040 | AP33: =IF(AND(AQ33="",AR33="",AX33="",BA33="",BC33=""),"",IF(AN33=1,(13-'Model Inputs'!$B$23)/12,1)) | AQ33: =IF(OR(AN33<='Model Inputs'!$B$24,AR33<>"",AX33<>"",BA33<>"",BC33<>""),'Model Inputs'!$B$25*(1+'Model Inputs'!$B$31)^(AN33-1),"") | AS33: =IF(AP33="","",IF(AR33="",AQ33,AR33)) | AT33: =IF(AS33="","",AP33*AS33) | AU33: =IF(AP33="","",IF(AN33=1,AP33*'Model Inputs'!$B$27,IF(AN33<=MAX(2,'Model Inputs'!$B$30),'Model Inputs'!$B$27*(1+'Model Inputs'!$B$28)^(AN33-2),'Model Inputs'!$B$27*(1+'Model Inputs'!$B$28)^(MAX(2,'Model Inputs'!$B$30)-2)*(1+'Model Inputs'!$B$29)^(AN33-MAX(2,'Model Inputs'!$B$30))))) | AV33: =IF(AU33="","",IF(AN33<=2,0,'Model Inputs'!$B$32*SIN(2*PI()*(AN33-2+'Model Inputs'!$B$34)/MAX(1,'Model Inputs'!$B$33)))) | AY33: =IF(AP33="","",IF(BC33<>"",MAX(BC33-AT33-IF(AZ33="",0,AZ33)-IF(BA33="",0,BA33),0),IF(AX33<>"",AX33,AU33*(1+IF(AW33="",AV33,AW33))))) | AZ33: =IF(AN33=1,'Model Inputs'!$B$26,"") | BB33: =IF(AND(AS33="",AY33="",AZ33="",BA33="",BC33=""),"",IF(BC33<>"",BC33,AT33+IF(AY33="",0,AY33)+IF(AZ33="",0,AZ33)+IF(BA33="",0,BA33))) | BL33: =IF(C33="Working",LOOKUP(2,1/($BL$19:BL32<>""),$BL$19:BL32),"") | BM33: =IF(C33="Working",LOOKUP(2,1/($BM$19:BM32<>""),$BM$19:BM32),"")
A34: 16 | B34: =IF(BB34="","",BB34) | C34: =IF(B34="","Retired","Working") -> Retired | D34: =IF(OR(C34="Retired",B34=""),0,MIN(B34,'Tax Assumptions'!$B$19)) -> 0 | G34: 0 | H34: =IF(G34=0,0,LOOKUP(G34,'Tax Assumptions'!$F$9:$F$15,'Tax Assumptions'!$I$9:$I$15)+(G34-LOOKUP(G34,'Tax Assumptions'!$F$9:$F$15,'Tax Assumptions'!$F$9:$F$15))*LOOKUP(G34,'Tax Assumptions'!$F$9:$F$15,'Tax Assumptions'!$H$9:$H$15)) -> 0 | I34: =IF(C34="Working",MIN(MAX(B34-E34,0),'Tax Assumptions'!$B$11)*'Tax Assumptions'!$B$10,0) -> 0 | J34: =IF(C34="Working",MAX(B34-E34,0)*'Tax Assumptions'!$B$12,0) -> 0 | K34: =IF(C34="Working",MAX(MAX(B34-E34,0)-'Tax Assumptions'!$B$14,0)*'Tax Assumptions'!$B$13,0) -> 0 | L34: =IF(C34="Working",MIN(B34*'Tax Assumptions'!$B$15,'Tax Assumptions'!$B$16),0) -> 0 | M34: =IF(C34="Working",MIN(B34*'Tax Assumptions'!$B$17,'Tax Assumptions'!$B$18),0) -> 0 | N34: =IF(C34="Working",MAX(B34-D34-'Tax Assumptions'!$B$9,0),0) -> 0 | O34: =IF(N34=0,0,LOOKUP(N34,'Tax Assumptions'!$K$9:$K$17,'Tax Assumptions'!$N$9:$N$17)+(N34-LOOKUP(N34,'Tax Assumptions'!$K$9:$K$17,'Tax Assumptions'!$K$9:$K$17))*LOOKUP(N34,'Tax Assumptions'!$K$9:$K$17,'Tax Assumptions'!$M$9:$M$17)) -> 0 | P34: =IF(N34=0,0,LOOKUP(N34,'Tax Assumptions'!$P$9:$P$12,'Tax Assumptions'!$S$9:$S$12)+(N34-LOOKUP(N34,'Tax Assumptions'!$P$9:$P$12,'Tax Assumptions'!$P$9:$P$12))*LOOKUP(N34,'Tax Assumptions'!$P$9:$P$12,'Tax Assumptions'!$R$9:$R$12)) -> 0 | Q34: =H34+I34+J34+K34+L34+M34+O34+P34 -> 0 | R34: =IF(C34="Working",B34-D34-E34-F34-Q34,0) -> 0 | S34: =IF(C34="Working",IF(BL34="","",BL34*(1+'Model Inputs'!$B$35)^(AN34-1)),"") | T34: =IF(C34="Working",IF(BM34="","",BM34*(1+'Model Inputs'!$B$36)^(AN34-1)),"") | U34: =IF(C34="Working",R34-S34-T34,0) -> 0 | V34: =IF(C34="Working",MIN(MAX(U34,0),'Tax Assumptions'!$B$20),0) -> 0 | W34: =IF(C34="Working",U34-V34,0) -> 0 | X34: =IF(C34="Working",W34+V34+D34+E34,0) -> 0 | Y34: =IF(C34="Retired",$B$13,0) -> 200000 | Z34: =AA34+AB34+AC34+AD34 -> 200000 | AA34: =IF(C34="Retired",MIN(Y34,((AE33)*(1+$B$15)+IF(C34="Working",W34,0))),0) -> 200000 | AB34: =IF(C34="Retired",MIN(MAX(Y34-AA34,0),((AF33)*(1+$B$15)+IF(C34="Working",D34,0))),0) -> 0 | AC34: =IF(C34="Retired",MIN(MAX(Y34-AA34-AB34,0),((AG33)*(1+$B$15)+IF(C34="Working",V34,0))),0) -> 0 | AD34: =IF(C34="Retired",MIN(MAX(Y34-AA34-AB34-AC34,0),((AH33)*(1+$B$15)+IF(C34="Working",E34,0))),0) -> 0 | AE34: =MAX(((AE33)*(1+$B$15)+IF(C34="Working",W34,0))-AA34,0) -> 7128046.3 | AF34: =MAX(((AF33)*(1+$B$15)+IF(C34="Working",D34,0))-AB34,0) -> 458081.63 | AG34: =MAX(((AG33)*(1+$B$15)+IF(C34="Working",V34,0))-AC34,0) -> 140229.07 | AH34: =MAX(((AH33)*(1+$B$15)+IF(C34="Working",E34,0))-AD34,0) -> 0 | AI34: =AE34+AF34+AG34+AH34 -> 7726357 | AJ34: =IF(C34="Working",AJ33+X34,MAX(AJ33-MIN(Y34,AJ33),0)) -> 4117592.2 | AK34: =IF(C34="Working",AK33*(1+$B$16)+X34,MAX(AK33*(1+$B$16)-MIN(Y34,AK33*(1+$B$16)),0)) -> 9445578 | AL34: =IF(C34="Working",IF(B34=0,0,W34/B34),0) -> 0 | AM34: =IF(C34="Working",IF(B34=0,0,X34/B34),0) -> 0 | AN34: =A34 -> 16 | AO34: ='Model Inputs'!$B$22+AN34-1 -> 2041 | AP34: =IF(AND(AQ34="",AR34="",AX34="",BA34="",BC34=""),"",IF(AN34=1,(13-'Model Inputs'!$B$23)/12,1)) | AQ34: =IF(OR(AN34<='Model Inputs'!$B$24,AR34<>"",AX34<>"",BA34<>"",BC34<>""),'Model Inputs'!$B$25*(1+'Model Inputs'!$B$31)^(AN34-1),"") | AS34: =IF(AP34="","",IF(AR34="",AQ34,AR34)) | AT34: =IF(AS34="","",AP34*AS34) | AU34: =IF(AP34="","",IF(AN34=1,AP34*'Model Inputs'!$B$27,IF(AN34<=MAX(2,'Model Inputs'!$B$30),'Model Inputs'!$B$27*(1+'Model Inputs'!$B$28)^(AN34-2),'Model Inputs'!$B$27*(1+'Model Inputs'!$B$28)^(MAX(2,'Model Inputs'!$B$30)-2)*(1+'Model Inputs'!$B$29)^(AN34-MAX(2,'Model Inputs'!$B$30))))) | AV34: =IF(AU34="","",IF(AN34<=2,0,'Model Inputs'!$B$32*SIN(2*PI()*(AN34-2+'Model Inputs'!$B$34)/MAX(1,'Model Inputs'!$B$33)))) | AY34: =IF(AP34="","",IF(BC34<>"",MAX(BC34-AT34-IF(AZ34="",0,AZ34)-IF(BA34="",0,BA34),0),IF(AX34<>"",AX34,AU34*(1+IF(AW34="",AV34,AW34))))) | AZ34: =IF(AN34=1,'Model Inputs'!$B$26,"") | BB34: =IF(AND(AS34="",AY34="",AZ34="",BA34="",BC34=""),"",IF(BC34<>"",BC34,AT34+IF(AY34="",0,AY34)+IF(AZ34="",0,AZ34)+IF(BA34="",0,BA34))) | BL34: =IF(C34="Working",LOOKUP(2,1/($BL$19:BL33<>""),$BL$19:BL33),"") | BM34: =IF(C34="Working",LOOKUP(2,1/($BM$19:BM33<>""),$BM$19:BM33),"")
A35: 17 | B35: =IF(BB35="","",BB35) | C35: =IF(B35="","Retired","Working") -> Retired | D35: =IF(OR(C35="Retired",B35=""),0,MIN(B35,'Tax Assumptions'!$B$19)) -> 0 | G35: =IF(C35="Working",MAX(B35-D35-E35-'Tax Assumptions'!$B$8,0),0) -> 0 | H35: =IF(G35=0,0,LOOKUP(G35,'Tax Assumptions'!$F$9:$F$15,'Tax Assumptions'!$I$9:$I$15)+(G35-LOOKUP(G35,'Tax Assumptions'!$F$9:$F$15,'Tax Assumptions'!$F$9:$F$15))*LOOKUP(G35,'Tax Assumptions'!$F$9:$F$15,'Tax Assumptions'!$H$9:$H$15)) -> 0 | I35: =IF(C35="Working",MIN(MAX(B35-E35,0),'Tax Assumptions'!$B$11)*'Tax Assumptions'!$B$10,0) -> 0 | J35: =IF(C35="Working",MAX(B35-E35,0)*'Tax Assumptions'!$B$12,0) -> 0 | K35: =IF(C35="Working",MAX(MAX(B35-E35,0)-'Tax Assumptions'!$B$14,0)*'Tax Assumptions'!$B$13,0) -> 0 | L35: =IF(C35="Working",MIN(B35*'Tax Assumptions'!$B$15,'Tax Assumptions'!$B$16),0) -> 0 | M35: =IF(C35="Working",MIN(B35*'Tax Assumptions'!$B$17,'Tax Assumptions'!$B$18),0) -> 0 | N35: =IF(C35="Working",MAX(B35-D35-'Tax Assumptions'!$B$9,0),0) -> 0 | O35: =IF(N35=0,0,LOOKUP(N35,'Tax Assumptions'!$K$9:$K$17,'Tax Assumptions'!$N$9:$N$17)+(N35-LOOKUP(N35,'Tax Assumptions'!$K$9:$K$17,'Tax Assumptions'!$K$9:$K$17))*LOOKUP(N35,'Tax Assumptions'!$K$9:$K$17,'Tax Assumptions'!$M$9:$M$17)) -> 0 | P35: =IF(N35=0,0,LOOKUP(N35,'Tax Assumptions'!$P$9:$P$12,'Tax Assumptions'!$S$9:$S$12)+(N35-LOOKUP(N35,'Tax Assumptions'!$P$9:$P$12,'Tax Assumptions'!$P$9:$P$12))*LOOKUP(N35,'Tax Assumptions'!$P$9:$P$12,'Tax Assumptions'!$R$9:$R$12)) -> 0 | Q35: =H35+I35+J35+K35+L35+M35+O35+P35 -> 0 | R35: =IF(C35="Working",B35-D35-E35-F35-Q35,0) -> 0 | S35: =IF(C35="Working",IF(BL35="","",BL35*(1+'Model Inputs'!$B$35)^(AN35-1)),"") | T35: =IF(C35="Working",IF(BM35="","",BM35*(1+'Model Inputs'!$B$36)^(AN35-1)),"") | U35: =IF(C35="Working",R35-S35-T35,0) -> 0 | V35: =IF(C35="Working",MIN(MAX(U35,0),'Tax Assumptions'!$B$20),0) -> 0 | W35: =IF(C35="Working",U35-V35,0) -> 0 | X35: =IF(C35="Working",W35+V35+D35+E35,0) -> 0 | Y35: =IF(C35="Retired",$B$13,0) -> 200000 | Z35: =AA35+AB35+AC35+AD35 -> 200000 | AA35: =IF(C35="Retired",MIN(Y35,((AE34)*(1+$B$15)+IF(C35="Working",W35,0))),0) -> 200000 | AB35: =IF(C35="Retired",MIN(MAX(Y35-AA35,0),((AF34)*(1+$B$15)+IF(C35="Working",D35,0))),0) -> 0 | AC35: =IF(C35="Retired",MIN(MAX(Y35-AA35-AB35,0),((AG34)*(1+$B$15)+IF(C35="Working",V35,0))),0) -> 0 | AD35: =IF(C35="Retired",MIN(MAX(Y35-AA35-AB35-AC35,0),((AH34)*(1+$B$15)+IF(C35="Working",E35,0))),0) -> 0 | AE35: =MAX(((AE34)*(1+$B$15)+IF(C35="Working",W35,0))-AA35,0) -> 7355729 | AF35: =MAX(((AF34)*(1+$B$15)+IF(C35="Working",D35,0))-AB35,0) -> 485566.53 | AG35: =MAX(((AG34)*(1+$B$15)+IF(C35="Working",V35,0))-AC35,0) -> 148642.82 | AH35: =MAX(((AH34)*(1+$B$15)+IF(C35="Working",E35,0))-AD35,0) -> 0 | AI35: =AE35+AF35+AG35+AH35 -> 7989938.4 | AJ35: =IF(C35="Working",AJ34+X35,MAX(AJ34-MIN(Y35,AJ34),0)) -> 3917592.2 | AK35: =IF(C35="Working",AK34*(1+$B$16)+X35,MAX(AK34*(1+$B$16)-MIN(Y35,AK34*(1+$B$16)),0)) -> 10001224 | AL35: =IF(C35="Working",IF(B35=0,0,W35/B35),0) -> 0 | AM35: =IF(C35="Working",IF(B35=0,0,X35/B35),0) -> 0 | AN35: =A35 -> 17 | AO35: ='Model Inputs'!$B$22+AN35-1 -> 2042 | AP35: =IF(AND(AQ35="",AR35="",AX35="",BA35="",BC35=""),"",IF(AN35=1,(13-'Model Inputs'!$B$23)/12,1)) | AQ35: =IF(OR(AN35<='Model Inputs'!$B$24,AR35<>"",AX35<>"",BA35<>"",BC35<>""),'Model Inputs'!$B$25*(1+'Model Inputs'!$B$31)^(AN35-1),"") | AS35: =IF(AP35="","",IF(AR35="",AQ35,AR35)) | AT35: =IF(AS35="","",AP35*AS35) | AU35: =IF(AP35="","",IF(AN35=1,AP35*'Model Inputs'!$B$27,IF(AN35<=MAX(2,'Model Inputs'!$B$30),'Model Inputs'!$B$27*(1+'Model Inputs'!$B$28)^(AN35-2),'Model Inputs'!$B$27*(1+'Model Inputs'!$B$28)^(MAX(2,'Model Inputs'!$B$30)-2)*(1+'Model Inputs'!$B$29)^(AN35-MAX(2,'Model Inputs'!$B$30))))) | AV35: =IF(AU35="","",IF(AN35<=2,0,'Model Inputs'!$B$32*SIN(2*PI()*(AN35-2+'Model Inputs'!$B$34)/MAX(1,'Model Inputs'!$B$33)))) | AY35: =IF(AP35="","",IF(BC35<>"",MAX(BC35-AT35-IF(AZ35="",0,AZ35)-IF(BA35="",0,BA35),0),IF(AX35<>"",AX35,AU35*(1+IF(AW35="",AV35,AW35))))) | AZ35: =IF(AN35=1,'Model Inputs'!$B$26,"") | BB35: =IF(AND(AS35="",AY35="",AZ35="",BA35="",BC35=""),"",IF(BC35<>"",BC35,AT35+IF(AY35="",0,AY35)+IF(AZ35="",0,AZ35)+IF(BA35="",0,BA35))) | BL35: =IF(C35="Working",LOOKUP(2,1/($BL$19:BL34<>""),$BL$19:BL34),"") | BM35: =IF(C35="Working",LOOKUP(2,1/($BM$19:BM34<>""),$BM$19:BM34),"")
A36: 18 | B36: =IF(BB36="","",BB36) | C36: =IF(B36="","Retired","Working") -> Retired | D36: =IF(OR(C36="Retired",B36=""),0,MIN(B36,'Tax Assumptions'!$B$19)) -> 0 | G36: =IF(C36="Working",MAX(B36-D36-E36-'Tax Assumptions'!$B$8,0),0) -> 0 | H36: =IF(G36=0,0,LOOKUP(G36,'Tax Assumptions'!$F$9:$F$15,'Tax Assumptions'!$I$9:$I$15)+(G36-LOOKUP(G36,'Tax Assumptions'!$F$9:$F$15,'Tax Assumptions'!$F$9:$F$15))*LOOKUP(G36,'Tax Assumptions'!$F$9:$F$15,'Tax Assumptions'!$H$9:$H$15)) -> 0 | I36: =IF(C36="Working",MIN(MAX(B36-E36,0),'Tax Assumptions'!$B$11)*'Tax Assumptions'!$B$10,0) -> 0 | J36: =IF(C36="Working",MAX(B36-E36,0)*'Tax Assumptions'!$B$12,0) -> 0 | K36: =IF(C36="Working",MAX(MAX(B36-E36,0)-'Tax Assumptions'!$B$14,0)*'Tax Assumptions'!$B$13,0) -> 0 | L36: =IF(C36="Working",MIN(B36*'Tax Assumptions'!$B$15,'Tax Assumptions'!$B$16),0) -> 0 | M36: =IF(C36="Working",MIN(B36*'Tax Assumptions'!$B$17,'Tax Assumptions'!$B$18),0) -> 0 | N36: =IF(C36="Working",MAX(B36-D36-'Tax Assumptions'!$B$9,0),0) -> 0 | O36: =IF(N36=0,0,LOOKUP(N36,'Tax Assumptions'!$K$9:$K$17,'Tax Assumptions'!$N$9:$N$17)+(N36-LOOKUP(N36,'Tax Assumptions'!$K$9:$K$17,'Tax Assumptions'!$K$9:$K$17))*LOOKUP(N36,'Tax Assumptions'!$K$9:$K$17,'Tax Assumptions'!$M$9:$M$17)) -> 0 | P36: =IF(N36=0,0,LOOKUP(N36,'Tax Assumptions'!$P$9:$P$12,'Tax Assumptions'!$S$9:$S$12)+(N36-LOOKUP(N36,'Tax Assumptions'!$P$9:$P$12,'Tax Assumptions'!$P$9:$P$12))*LOOKUP(N36,'Tax Assumptions'!$P$9:$P$12,'Tax Assumptions'!$R$9:$R$12)) -> 0 | Q36: =H36+I36+J36+K36+L36+M36+O36+P36 -> 0 | R36: =IF(C36="Working",B36-D36-E36-F36-Q36,0) -> 0 | S36: =IF(C36="Working",IF(BL36="","",BL36*(1+'Model Inputs'!$B$35)^(AN36-1)),"") | T36: =IF(C36="Working",IF(BM36="","",BM36*(1+'Model Inputs'!$B$36)^(AN36-1)),"") | U36: =IF(C36="Working",R36-S36-T36,0) -> 0 | V36: =IF(C36="Working",MIN(MAX(U36,0),'Tax Assumptions'!$B$20),0) -> 0 | W36: =IF(C36="Working",U36-V36,0) -> 0 | X36: =IF(C36="Working",W36+V36+D36+E36,0) -> 0 | Y36: =IF(C36="Retired",$B$13,0) -> 200000 | Z36: =AA36+AB36+AC36+AD36 -> 200000 | AA36: =IF(C36="Retired",MIN(Y36,((AE35)*(1+$B$15)+IF(C36="Working",W36,0))),0) -> 200000 | AB36: =IF(C36="Retired",MIN(MAX(Y36-AA36,0),((AF35)*(1+$B$15)+IF(C36="Working",D36,0))),0) -> 0 | AC36: =IF(C36="Retired",MIN(MAX(Y36-AA36-AB36,0),((AG35)*(1+$B$15)+IF(C36="Working",V36,0))),0) -> 0 | AD36: =IF(C36="Retired",MIN(MAX(Y36-AA36-AB36-AC36,0),((AH35)*(1+$B$15)+IF(C36="Working",E36,0))),0) -> 0 | AE36: =MAX(((AE35)*(1+$B$15)+IF(C36="Working",W36,0))-AA36,0) -> 7597072.8 | AF36: =MAX(((AF35)*(1+$B$15)+IF(C36="Working",D36,0))-AB36,0) -> 514700.52 | AG36: =MAX(((AG35)*(1+$B$15)+IF(C36="Working",V36,0))-AC36,0) -> 157561.38 | AH36: =MAX(((AH35)*(1+$B$15)+IF(C36="Working",E36,0))-AD36,0) -> 0 | AI36: =AE36+AF36+AG36+AH36 -> 8269334.7 | AJ36: =IF(C36="Working",AJ35+X36,MAX(AJ35-MIN(Y36,AJ35),0)) -> 3717592.2 | AK36: =IF(C36="Working",AK35*(1+$B$16)+X36,MAX(AK35*(1+$B$16)-MIN(Y36,AK35*(1+$B$16)),0)) -> 10601322 | AL36: =IF(C36="Working",IF(B36=0,0,W36/B36),0) -> 0 | AM36: =IF(C36="Working",IF(B36=0,0,X36/B36),0) -> 0 | AN36: =A36 -> 18 | AO36: ='Model Inputs'!$B$22+AN36-1 -> 2043 | AP36: =IF(AND(AQ36="",AR36="",AX36="",BA36="",BC36=""),"",IF(AN36=1,(13-'Model Inputs'!$B$23)/12,1)) | AQ36: =IF(OR(AN36<='Model Inputs'!$B$24,AR36<>"",AX36<>"",BA36<>"",BC36<>""),'Model Inputs'!$B$25*(1+'Model Inputs'!$B$31)^(AN36-1),"") | AS36: =IF(AP36="","",IF(AR36="",AQ36,AR36)) | AT36: =IF(AS36="","",AP36*AS36) | AU36: =IF(AP36="","",IF(AN36=1,AP36*'Model Inputs'!$B$27,IF(AN36<=MAX(2,'Model Inputs'!$B$30),'Model Inputs'!$B$27*(1+'Model Inputs'!$B$28)^(AN36-2),'Model Inputs'!$B$27*(1+'Model Inputs'!$B$28)^(MAX(2,'Model Inputs'!$B$30)-2)*(1+'Model Inputs'!$B$29)^(AN36-MAX(2,'Model Inputs'!$B$30))))) | AV36: =IF(AU36="","",IF(AN36<=2,0,'Model Inputs'!$B$32*SIN(2*PI()*(AN36-2+'Model Inputs'!$B$34)/MAX(1,'Model Inputs'!$B$33)))) | AY36: =IF(AP36="","",IF(BC36<>"",MAX(BC36-AT36-IF(AZ36="",0,AZ36)-IF(BA36="",0,BA36),0),IF(AX36<>"",AX36,AU36*(1+IF(AW36="",AV36,AW36))))) | AZ36: =IF(AN36=1,'Model Inputs'!$B$26,"") | BB36: =IF(AND(AS36="",AY36="",AZ36="",BA36="",BC36=""),"",IF(BC36<>"",BC36,AT36+IF(AY36="",0,AY36)+IF(AZ36="",0,AZ36)+IF(BA36="",0,BA36))) | BL36: =IF(C36="Working",LOOKUP(2,1/($BL$19:BL35<>""),$BL$19:BL35),"") | BM36: =IF(C36="Working",LOOKUP(2,1/($BM$19:BM35<>""),$BM$19:BM35),"")
A37: 19 | B37: =IF(BB37="","",BB37) | C37: =IF(B37="","Retired","Working") -> Retired | D37: =IF(OR(C37="Retired",B37=""),0,MIN(B37,'Tax Assumptions'!$B$19)) -> 0 | G37: =IF(C37="Working",MAX(B37-D37-E37-'Tax Assumptions'!$B$8,0),0) -> 0 | H37: =IF(G37=0,0,LOOKUP(G37,'Tax Assumptions'!$F$9:$F$15,'Tax Assumptions'!$I$9:$I$15)+(G37-LOOKUP(G37,'Tax Assumptions'!$F$9:$F$15,'Tax Assumptions'!$F$9:$F$15))*LOOKUP(G37,'Tax Assumptions'!$F$9:$F$15,'Tax Assumptions'!$H$9:$H$15)) -> 0 | I37: =IF(C37="Working",MIN(MAX(B37-E37,0),'Tax Assumptions'!$B$11)*'Tax Assumptions'!$B$10,0) -> 0 | J37: =IF(C37="Working",MAX(B37-E37,0)*'Tax Assumptions'!$B$12,0) -> 0 | K37: =IF(C37="Working",MAX(MAX(B37-E37,0)-'Tax Assumptions'!$B$14,0)*'Tax Assumptions'!$B$13,0) -> 0 | L37: =IF(C37="Working",MIN(B37*'Tax Assumptions'!$B$15,'Tax Assumptions'!$B$16),0) -> 0 | M37: =IF(C37="Working",MIN(B37*'Tax Assumptions'!$B$17,'Tax Assumptions'!$B$18),0) -> 0 | N37: =IF(C37="Working",MAX(B37-D37-'Tax Assumptions'!$B$9,0),0) -> 0 | O37: =IF(N37=0,0,LOOKUP(N37,'Tax Assumptions'!$K$9:$K$17,'Tax Assumptions'!$N$9:$N$17)+(N37-LOOKUP(N37,'Tax Assumptions'!$K$9:$K$17,'Tax Assumptions'!$K$9:$K$17))*LOOKUP(N37,'Tax Assumptions'!$K$9:$K$17,'Tax Assumptions'!$M$9:$M$17)) -> 0 | P37: =IF(N37=0,0,LOOKUP(N37,'Tax Assumptions'!$P$9:$P$12,'Tax Assumptions'!$S$9:$S$12)+(N37-LOOKUP(N37,'Tax Assumptions'!$P$9:$P$12,'Tax Assumptions'!$P$9:$P$12))*LOOKUP(N37,'Tax Assumptions'!$P$9:$P$12,'Tax Assumptions'!$R$9:$R$12)) -> 0 | Q37: =H37+I37+J37+K37+L37+M37+O37+P37 -> 0 | R37: =IF(C37="Working",B37-D37-E37-F37-Q37,0) -> 0 | S37: =IF(C37="Working",IF(BL37="","",BL37*(1+'Model Inputs'!$B$35)^(AN37-1)),"") | T37: =IF(C37="Working",IF(BM37="","",BM37*(1+'Model Inputs'!$B$36)^(AN37-1)),"") | U37: =IF(C37="Working",R37-S37-T37,0) -> 0 | V37: =IF(C37="Working",MIN(MAX(U37,0),'Tax Assumptions'!$B$20),0) -> 0 | W37: =IF(C37="Working",U37-V37,0) -> 0 | X37: =IF(C37="Working",W37+V37+D37+E37,0) -> 0 | Y37: =IF(C37="Retired",$B$13,0) -> 200000 | Z37: =AA37+AB37+AC37+AD37 -> 200000 | AA37: =IF(C37="Retired",MIN(Y37,((AE36)*(1+$B$15)+IF(C37="Working",W37,0))),0) -> 200000 | AB37: =IF(C37="Retired",MIN(MAX(Y37-AA37,0),((AF36)*(1+$B$15)+IF(C37="Working",D37,0))),0) -> 0 | AC37: =IF(C37="Retired",MIN(MAX(Y37-AA37-AB37,0),((AG36)*(1+$B$15)+IF(C37="Working",V37,0))),0) -> 0 | AD37: =IF(C37="Retired",MIN(MAX(Y37-AA37-AB37-AC37,0),((AH36)*(1+$B$15)+IF(C37="Working",E37,0))),0) -> 0 | AE37: =MAX(((AE36)*(1+$B$15)+IF(C37="Working",W37,0))-AA37,0) -> 7852897.1 | AF37: =MAX(((AF36)*(1+$B$15)+IF(C37="Working",D37,0))-AB37,0) -> 545582.56 | AG37: =MAX(((AG36)*(1+$B$15)+IF(C37="Working",V37,0))-AC37,0) -> 167015.07 | AH37: =MAX(((AH36)*(1+$B$15)+IF(C37="Working",E37,0))-AD37,0) -> 0 | AI37: =AE37+AF37+AG37+AH37 -> 8565494.8 | AJ37: =IF(C37="Working",AJ36+X37,MAX(AJ36-MIN(Y37,AJ36),0)) -> 3517592.2 | AK37: =IF(C37="Working",AK36*(1+$B$16)+X37,MAX(AK36*(1+$B$16)-MIN(Y37,AK36*(1+$B$16)),0)) -> 11249428 | AL37: =IF(C37="Working",IF(B37=0,0,W37/B37),0) -> 0 | AM37: =IF(C37="Working",IF(B37=0,0,X37/B37),0) -> 0 | AN37: =A37 -> 19 | AO37: ='Model Inputs'!$B$22+AN37-1 -> 2044 | AP37: =IF(AND(AQ37="",AR37="",AX37="",BA37="",BC37=""),"",IF(AN37=1,(13-'Model Inputs'!$B$23)/12,1)) | AQ37: =IF(OR(AN37<='Model Inputs'!$B$24,AR37<>"",AX37<>"",BA37<>"",BC37<>""),'Model Inputs'!$B$25*(1+'Model Inputs'!$B$31)^(AN37-1),"") | AS37: =IF(AP37="","",IF(AR37="",AQ37,AR37)) | AT37: =IF(AS37="","",AP37*AS37) | AU37: =IF(AP37="","",IF(AN37=1,AP37*'Model Inputs'!$B$27,IF(AN37<=MAX(2,'Model Inputs'!$B$30),'Model Inputs'!$B$27*(1+'Model Inputs'!$B$28)^(AN37-2),'Model Inputs'!$B$27*(1+'Model Inputs'!$B$28)^(MAX(2,'Model Inputs'!$B$30)-2)*(1+'Model Inputs'!$B$29)^(AN37-MAX(2,'Model Inputs'!$B$30))))) | AV37: =IF(AU37="","",IF(AN37<=2,0,'Model Inputs'!$B$32*SIN(2*PI()*(AN37-2+'Model Inputs'!$B$34)/MAX(1,'Model Inputs'!$B$33)))) | AY37: =IF(AP37="","",IF(BC37<>"",MAX(BC37-AT37-IF(AZ37="",0,AZ37)-IF(BA37="",0,BA37),0),IF(AX37<>"",AX37,AU37*(1+IF(AW37="",AV37,AW37))))) | AZ37: =IF(AN37=1,'Model Inputs'!$B$26,"") | BB37: =IF(AND(AS37="",AY37="",AZ37="",BA37="",BC37=""),"",IF(BC37<>"",BC37,AT37+IF(AY37="",0,AY37)+IF(AZ37="",0,AZ37)+IF(BA37="",0,BA37))) | BL37: =IF(C37="Working",LOOKUP(2,1/($BL$19:BL36<>""),$BL$19:BL36),"") | BM37: =IF(C37="Working",LOOKUP(2,1/($BM$19:BM36<>""),$BM$19:BM36),"")
A38: 20 | B38: =IF(BB38="","",BB38) | C38: =IF(B38="","Retired","Working") -> Retired | D38: =IF(OR(C38="Retired",B38=""),0,MIN(B38,'Tax Assumptions'!$B$19)) -> 0 | G38: =IF(C38="Working",MAX(B38-D38-E38-'Tax Assumptions'!$B$8,0),0) -> 0 | H38: =IF(G38=0,0,LOOKUP(G38,'Tax Assumptions'!$F$9:$F$15,'Tax Assumptions'!$I$9:$I$15)+(G38-LOOKUP(G38,'Tax Assumptions'!$F$9:$F$15,'Tax Assumptions'!$F$9:$F$15))*LOOKUP(G38,'Tax Assumptions'!$F$9:$F$15,'Tax Assumptions'!$H$9:$H$15)) -> 0 | I38: =IF(C38="Working",MIN(MAX(B38-E38,0),'Tax Assumptions'!$B$11)*'Tax Assumptions'!$B$10,0) -> 0 | J38: =IF(C38="Working",MAX(B38-E38,0)*'Tax Assumptions'!$B$12,0) -> 0 | K38: =IF(C38="Working",MAX(MAX(B38-E38,0)-'Tax Assumptions'!$B$14,0)*'Tax Assumptions'!$B$13,0) -> 0 | L38: =IF(C38="Working",MIN(B38*'Tax Assumptions'!$B$15,'Tax Assumptions'!$B$16),0) -> 0 | M38: =IF(C38="Working",MIN(B38*'Tax Assumptions'!$B$17,'Tax Assumptions'!$B$18),0) -> 0 | N38: =IF(C38="Working",MAX(B38-D38-'Tax Assumptions'!$B$9,0),0) -> 0 | O38: =IF(N38=0,0,LOOKUP(N38,'Tax Assumptions'!$K$9:$K$17,'Tax Assumptions'!$N$9:$N$17)+(N38-LOOKUP(N38,'Tax Assumptions'!$K$9:$K$17,'Tax Assumptions'!$K$9:$K$17))*LOOKUP(N38,'Tax Assumptions'!$K$9:$K$17,'Tax Assumptions'!$M$9:$M$17)) -> 0 | P38: =IF(N38=0,0,LOOKUP(N38,'Tax Assumptions'!$P$9:$P$12,'Tax Assumptions'!$S$9:$S$12)+(N38-LOOKUP(N38,'Tax Assumptions'!$P$9:$P$12,'Tax Assumptions'!$P$9:$P$12))*LOOKUP(N38,'Tax Assumptions'!$P$9:$P$12,'Tax Assumptions'!$R$9:$R$12)) -> 0 | Q38: =H38+I38+J38+K38+L38+M38+O38+P38 -> 0 | R38: =IF(C38="Working",B38-D38-E38-F38-Q38,0) -> 0 | S38: =IF(C38="Working",IF(BL38="","",BL38*(1+'Model Inputs'!$B$35)^(AN38-1)),"") | T38: =IF(C38="Working",IF(BM38="","",BM38*(1+'Model Inputs'!$B$36)^(AN38-1)),"") | U38: =IF(C38="Working",R38-S38-T38,0) -> 0 | V38: =IF(C38="Working",MIN(MAX(U38,0),'Tax Assumptions'!$B$20),0) -> 0 | W38: =IF(C38="Working",U38-V38,0) -> 0 | X38: =IF(C38="Working",W38+V38+D38+E38,0) -> 0 | Y38: =IF(C38="Retired",$B$13,0) -> 200000 | Z38: =AA38+AB38+AC38+AD38 -> 200000 | AA38: =IF(C38="Retired",MIN(Y38,((AE37)*(1+$B$15)+IF(C38="Working",W38,0))),0) -> 200000 | AB38: =IF(C38="Retired",MIN(MAX(Y38-AA38,0),((AF37)*(1+$B$15)+IF(C38="Working",D38,0))),0) -> 0 | AC38: =IF(C38="Retired",MIN(MAX(Y38-AA38-AB38,0),((AG37)*(1+$B$15)+IF(C38="Working",V38,0))),0) -> 0 | AD38: =IF(C38="Retired",MIN(MAX(Y38-AA38-AB38-AC38,0),((AH37)*(1+$B$15)+IF(C38="Working",E38,0))),0) -> 0 | AE38: =MAX(((AE37)*(1+$B$15)+IF(C38="Working",W38,0))-AA38,0) -> 8124071 | AF38: =MAX(((AF37)*(1+$B$15)+IF(C38="Working",D38,0))-AB38,0) -> 578317.51 | AG38: =MAX(((AG37)*(1+$B$15)+IF(C38="Working",V38,0))-AC38,0) -> 177035.97 | AH38: =MAX(((AH37)*(1+$B$15)+IF(C38="Working",E38,0))-AD38,0) -> 0 | AI38: =AE38+AF38+AG38+AH38 -> 8879424.4 | AJ38: =IF(C38="Working",AJ37+X38,MAX(AJ37-MIN(Y38,AJ37),0)) -> 3317592.2 | AK38: =IF(C38="Working",AK37*(1+$B$16)+X38,MAX(AK37*(1+$B$16)-MIN(Y38,AK37*(1+$B$16)),0)) -> 11949382 | AL38: =IF(C38="Working",IF(B38=0,0,W38/B38),0) -> 0 | AM38: =IF(C38="Working",IF(B38=0,0,X38/B38),0) -> 0 | AN38: =A38 -> 20 | AO38: ='Model Inputs'!$B$22+AN38-1 -> 2045 | AP38: =IF(AND(AQ38="",AR38="",AX38="",BA38="",BC38=""),"",IF(AN38=1,(13-'Model Inputs'!$B$23)/12,1)) | AQ38: =IF(OR(AN38<='Model Inputs'!$B$24,AR38<>"",AX38<>"",BA38<>"",BC38<>""),'Model Inputs'!$B$25*(1+'Model Inputs'!$B$31)^(AN38-1),"") | AS38: =IF(AP38="","",IF(AR38="",AQ38,AR38)) | AT38: =IF(AS38="","",AP38*AS38) | AU38: =IF(AP38="","",IF(AN38=1,AP38*'Model Inputs'!$B$27,IF(AN38<=MAX(2,'Model Inputs'!$B$30),'Model Inputs'!$B$27*(1+'Model Inputs'!$B$28)^(AN38-2),'Model Inputs'!$B$27*(1+'Model Inputs'!$B$28)^(MAX(2,'Model Inputs'!$B$30)-2)*(1+'Model Inputs'!$B$29)^(AN38-MAX(2,'Model Inputs'!$B$30))))) | AV38: =IF(AU38="","",IF(AN38<=2,0,'Model Inputs'!$B$32*SIN(2*PI()*(AN38-2+'Model Inputs'!$B$34)/MAX(1,'Model Inputs'!$B$33)))) | AY38: =IF(AP38="","",IF(BC38<>"",MAX(BC38-AT38-IF(AZ38="",0,AZ38)-IF(BA38="",0,BA38),0),IF(AX38<>"",AX38,AU38*(1+IF(AW38="",AV38,AW38))))) | AZ38: =IF(AN38=1,'Model Inputs'!$B$26,"") | BB38: =IF(AND(AS38="",AY38="",AZ38="",BA38="",BC38=""),"",IF(BC38<>"",BC38,AT38+IF(AY38="",0,AY38)+IF(AZ38="",0,AZ38)+IF(BA38="",0,BA38))) | BL38: =IF(C38="Working",LOOKUP(2,1/($BL$19:BL37<>""),$BL$19:BL37),"") | BM38: =IF(C38="Working",LOOKUP(2,1/($BM$19:BM37<>""),$BM$19:BM37),"")
A39: 21 | B39: =IF(BB39="","",BB39) | C39: =IF(B39="","Retired","Working") -> Retired | D39: =IF(OR(C39="Retired",B39=""),0,MIN(B39,'Tax Assumptions'!$B$19)) -> 0 | G39: =IF(C39="Working",MAX(B39-D39-E39-'Tax Assumptions'!$B$8,0),0) -> 0 | H39: =IF(G39=0,0,LOOKUP(G39,'Tax Assumptions'!$F$9:$F$15,'Tax Assumptions'!$I$9:$I$15)+(G39-LOOKUP(G39,'Tax Assumptions'!$F$9:$F$15,'Tax Assumptions'!$F$9:$F$15))*LOOKUP(G39,'Tax Assumptions'!$F$9:$F$15,'Tax Assumptions'!$H$9:$H$15)) -> 0 | I39: =IF(C39="Working",MIN(MAX(B39-E39,0),'Tax Assumptions'!$B$11)*'Tax Assumptions'!$B$10,0) -> 0 | J39: =IF(C39="Working",MAX(B39-E39,0)*'Tax Assumptions'!$B$12,0) -> 0 | K39: =IF(C39="Working",MAX(MAX(B39-E39,0)-'Tax Assumptions'!$B$14,0)*'Tax Assumptions'!$B$13,0) -> 0 | L39: =IF(C39="Working",MIN(B39*'Tax Assumptions'!$B$15,'Tax Assumptions'!$B$16),0) -> 0 | M39: =IF(C39="Working",MIN(B39*'Tax Assumptions'!$B$17,'Tax Assumptions'!$B$18),0) -> 0 | N39: =IF(C39="Working",MAX(B39-D39-'Tax Assumptions'!$B$9,0),0) -> 0 | O39: =IF(N39=0,0,LOOKUP(N39,'Tax Assumptions'!$K$9:$K$17,'Tax Assumptions'!$N$9:$N$17)+(N39-LOOKUP(N39,'Tax Assumptions'!$K$9:$K$17,'Tax Assumptions'!$K$9:$K$17))*LOOKUP(N39,'Tax Assumptions'!$K$9:$K$17,'Tax Assumptions'!$M$9:$M$17)) -> 0 | P39: =IF(N39=0,0,LOOKUP(N39,'Tax Assumptions'!$P$9:$P$12,'Tax Assumptions'!$S$9:$S$12)+(N39-LOOKUP(N39,'Tax Assumptions'!$P$9:$P$12,'Tax Assumptions'!$P$9:$P$12))*LOOKUP(N39,'Tax Assumptions'!$P$9:$P$12,'Tax Assumptions'!$R$9:$R$12)) -> 0 | Q39: =H39+I39+J39+K39+L39+M39+O39+P39 -> 0 | R39: =IF(C39="Working",B39-D39-E39-F39-Q39,0) -> 0 | S39: =IF(C39="Working",IF(BL39="","",BL39*(1+'Model Inputs'!$B$35)^(AN39-1)),"") | T39: =IF(C39="Working",IF(BM39="","",BM39*(1+'Model Inputs'!$B$36)^(AN39-1)),"") | U39: =IF(C39="Working",R39-S39-T39,0) -> 0 | V39: =IF(C39="Working",MIN(MAX(U39,0),'Tax Assumptions'!$B$20),0) -> 0 | W39: =IF(C39="Working",U39-V39,0) -> 0 | X39: =IF(C39="Working",W39+V39+D39+E39,0) -> 0 | Y39: =IF(C39="Retired",$B$13,0) -> 200000 | Z39: =AA39+AB39+AC39+AD39 -> 200000 | AA39: =IF(C39="Retired",MIN(Y39,((AE38)*(1+$B$15)+IF(C39="Working",W39,0))),0) -> 200000 | AB39: =IF(C39="Retired",MIN(MAX(Y39-AA39,0),((AF38)*(1+$B$15)+IF(C39="Working",D39,0))),0) -> 0 | AC39: =IF(C39="Retired",MIN(MAX(Y39-AA39-AB39,0),((AG38)*(1+$B$15)+IF(C39="Working",V39,0))),0) -> 0 | AD39: =IF(C39="Retired",MIN(MAX(Y39-AA39-AB39-AC39,0),((AH38)*(1+$B$15)+IF(C39="Working",E39,0))),0) -> 0 | AE39: =MAX(((AE38)*(1+$B$15)+IF(C39="Working",W39,0))-AA39,0) -> 8411515.2 | AF39: =MAX(((AF38)*(1+$B$15)+IF(C39="Working",D39,0))-AB39,0) -> 613016.56 | AG39: =MAX(((AG38)*(1+$B$15)+IF(C39="Working",V39,0))-AC39,0) -> 187658.13 | AH39: =MAX(((AH38)*(1+$B$15)+IF(C39="Working",E39,0))-AD39,0) -> 0 | AI39: =AE39+AF39+AG39+AH39 -> 9212189.9 | AJ39: =IF(C39="Working",AJ38+X39,MAX(AJ38-MIN(Y39,AJ38),0)) -> 3117592.2 | AK39: =IF(C39="Working",AK38*(1+$B$16)+X39,MAX(AK38*(1+$B$16)-MIN(Y39,AK38*(1+$B$16)),0)) -> 12705333 | AL39: =IF(C39="Working",IF(B39=0,0,W39/B39),0) -> 0 | AM39: =IF(C39="Working",IF(B39=0,0,X39/B39),0) -> 0 | AN39: =A39 -> 21 | AO39: ='Model Inputs'!$B$22+AN39-1 -> 2046 | AP39: =IF(AND(AQ39="",AR39="",AX39="",BA39="",BC39=""),"",IF(AN39=1,(13-'Model Inputs'!$B$23)/12,1)) | AQ39: =IF(OR(AN39<='Model Inputs'!$B$24,AR39<>"",AX39<>"",BA39<>"",BC39<>""),'Model Inputs'!$B$25*(1+'Model Inputs'!$B$31)^(AN39-1),"") | AS39: =IF(AP39="","",IF(AR39="",AQ39,AR39)) | AT39: =IF(AS39="","",AP39*AS39) | AU39: =IF(AP39="","",IF(AN39=1,AP39*'Model Inputs'!$B$27,IF(AN39<=MAX(2,'Model Inputs'!$B$30),'Model Inputs'!$B$27*(1+'Model Inputs'!$B$28)^(AN39-2),'Model Inputs'!$B$27*(1+'Model Inputs'!$B$28)^(MAX(2,'Model Inputs'!$B$30)-2)*(1+'Model Inputs'!$B$29)^(AN39-MAX(2,'Model Inputs'!$B$30))))) | AV39: =IF(AU39="","",IF(AN39<=2,0,'Model Inputs'!$B$32*SIN(2*PI()*(AN39-2+'Model Inputs'!$B$34)/MAX(1,'Model Inputs'!$B$33)))) | AY39: =IF(AP39="","",IF(BC39<>"",MAX(BC39-AT39-IF(AZ39="",0,AZ39)-IF(BA39="",0,BA39),0),IF(AX39<>"",AX39,AU39*(1+IF(AW39="",AV39,AW39))))) | AZ39: =IF(AN39=1,'Model Inputs'!$B$26,"") | BB39: =IF(AND(AS39="",AY39="",AZ39="",BA39="",BC39=""),"",IF(BC39<>"",BC39,AT39+IF(AY39="",0,AY39)+IF(AZ39="",0,AZ39)+IF(BA39="",0,BA39))) | BL39: =IF(C39="Working",LOOKUP(2,1/($BL$19:BL38<>""),$BL$19:BL38),"") | BM39: =IF(C39="Working",LOOKUP(2,1/($BM$19:BM38<>""),$BM$19:BM38),"")
A40: 22 | B40: =IF(BB40="","",BB40) | C40: =IF(B40="","Retired","Working") -> Retired | D40: =IF(OR(C40="Retired",B40=""),0,MIN(B40,'Tax Assumptions'!$B$19)) -> 0 | G40: =IF(C40="Working",MAX(B40-D40-E40-'Tax Assumptions'!$B$8,0),0) -> 0 | H40: =IF(G40=0,0,LOOKUP(G40,'Tax Assumptions'!$F$9:$F$15,'Tax Assumptions'!$I$9:$I$15)+(G40-LOOKUP(G40,'Tax Assumptions'!$F$9:$F$15,'Tax Assumptions'!$F$9:$F$15))*LOOKUP(G40,'Tax Assumptions'!$F$9:$F$15,'Tax Assumptions'!$H$9:$H$15)) -> 0 | I40: =IF(C40="Working",MIN(MAX(B40-E40,0),'Tax Assumptions'!$B$11)*'Tax Assumptions'!$B$10,0) -> 0 | J40: =IF(C40="Working",MAX(B40-E40,0)*'Tax Assumptions'!$B$12,0) -> 0 | K40: =IF(C40="Working",MAX(MAX(B40-E40,0)-'Tax Assumptions'!$B$14,0)*'Tax Assumptions'!$B$13,0) -> 0 | L40: =IF(C40="Working",MIN(B40*'Tax Assumptions'!$B$15,'Tax Assumptions'!$B$16),0) -> 0 | M40: =IF(C40="Working",MIN(B40*'Tax Assumptions'!$B$17,'Tax Assumptions'!$B$18),0) -> 0 | N40: =IF(C40="Working",MAX(B40-D40-'Tax Assumptions'!$B$9,0),0) -> 0 | O40: =IF(N40=0,0,LOOKUP(N40,'Tax Assumptions'!$K$9:$K$17,'Tax Assumptions'!$N$9:$N$17)+(N40-LOOKUP(N40,'Tax Assumptions'!$K$9:$K$17,'Tax Assumptions'!$K$9:$K$17))*LOOKUP(N40,'Tax Assumptions'!$K$9:$K$17,'Tax Assumptions'!$M$9:$M$17)) -> 0 | P40: =IF(N40=0,0,LOOKUP(N40,'Tax Assumptions'!$P$9:$P$12,'Tax Assumptions'!$S$9:$S$12)+(N40-LOOKUP(N40,'Tax Assumptions'!$P$9:$P$12,'Tax Assumptions'!$P$9:$P$12))*LOOKUP(N40,'Tax Assumptions'!$P$9:$P$12,'Tax Assumptions'!$R$9:$R$12)) -> 0 | Q40: =H40+I40+J40+K40+L40+M40+O40+P40 -> 0 | R40: =IF(C40="Working",B40-D40-E40-F40-Q40,0) -> 0 | S40: =IF(C40="Working",IF(BL40="","",BL40*(1+'Model Inputs'!$B$35)^(AN40-1)),"") | T40: =IF(C40="Working",IF(BM40="","",BM40*(1+'Model Inputs'!$B$36)^(AN40-1)),"") | U40: =IF(C40="Working",R40-S40-T40,0) -> 0 | V40: =IF(C40="Working",MIN(MAX(U40,0),'Tax Assumptions'!$B$20),0) -> 0 | W40: =IF(C40="Working",U40-V40,0) -> 0 | X40: =IF(C40="Working",W40+V40+D40+E40,0) -> 0 | Y40: =IF(C40="Retired",$B$13,0) -> 200000 | Z40: =AA40+AB40+AC40+AD40 -> 200000 | AA40: =IF(C40="Retired",MIN(Y40,((AE39)*(1+$B$15)+IF(C40="Working",W40,0))),0) -> 200000 | AB40: =IF(C40="Retired",MIN(MAX(Y40-AA40,0),((AF39)*(1+$B$15)+IF(C40="Working",D40,0))),0) -> 0 | AC40: =IF(C40="Retired",MIN(MAX(Y40-AA40-AB40,0),((AG39)*(1+$B$15)+IF(C40="Working",V40,0))),0) -> 0 | AD40: =IF(C40="Retired",MIN(MAX(Y40-AA40-AB40-AC40,0),((AH39)*(1+$B$15)+IF(C40="Working",E40,0))),0) -> 0 | AE40: =MAX(((AE39)*(1+$B$15)+IF(C40="Working",W40,0))-AA40,0) -> 8716206.1 | AF40: =MAX(((AF39)*(1+$B$15)+IF(C40="Working",D40,0))-AB40,0) -> 649797.55 | AG40: =MAX(((AG39)*(1+$B$15)+IF(C40="Working",V40,0))-AC40,0) -> 198917.62 | AH40: =MAX(((AH39)*(1+$B$15)+IF(C40="Working",E40,0))-AD40,0) -> 0 | AI40: =AE40+AF40+AG40+AH40 -> 9564921.3 | AJ40: =IF(C40="Working",AJ39+X40,MAX(AJ39-MIN(Y40,AJ39),0)) -> 2917592.2 | AK40: =IF(C40="Working",AK39*(1+$B$16)+X40,MAX(AK39*(1+$B$16)-MIN(Y40,AK39*(1+$B$16)),0)) -> 13521759 | AL40: =IF(C40="Working",IF(B40=0,0,W40/B40),0) -> 0 | AM40: =IF(C40="Working",IF(B40=0,0,X40/B40),0) -> 0 | AN40: =A40 -> 22 | AO40: ='Model Inputs'!$B$22+AN40-1 -> 2047 | AP40: =IF(AND(AQ40="",AR40="",AX40="",BA40="",BC40=""),"",IF(AN40=1,(13-'Model Inputs'!$B$23)/12,1)) | AQ40: =IF(OR(AN40<='Model Inputs'!$B$24,AR40<>"",AX40<>"",BA40<>"",BC40<>""),'Model Inputs'!$B$25*(1+'Model Inputs'!$B$31)^(AN40-1),"") | AS40: =IF(AP40="","",IF(AR40="",AQ40,AR40)) | AT40: =IF(AS40="","",AP40*AS40) | AU40: =IF(AP40="","",IF(AN40=1,AP40*'Model Inputs'!$B$27,IF(AN40<=MAX(2,'Model Inputs'!$B$30),'Model Inputs'!$B$27*(1+'Model Inputs'!$B$28)^(AN40-2),'Model Inputs'!$B$27*(1+'Model Inputs'!$B$28)^(MAX(2,'Model Inputs'!$B$30)-2)*(1+'Model Inputs'!$B$29)^(AN40-MAX(2,'Model Inputs'!$B$30))))) | AV40: =IF(AU40="","",IF(AN40<=2,0,'Model Inputs'!$B$32*SIN(2*PI()*(AN40-2+'Model Inputs'!$B$34)/MAX(1,'Model Inputs'!$B$33)))) | AY40: =IF(AP40="","",IF(BC40<>"",MAX(BC40-AT40-IF(AZ40="",0,AZ40)-IF(BA40="",0,BA40),0),IF(AX40<>"",AX40,AU40*(1+IF(AW40="",AV40,AW40))))) | AZ40: =IF(AN40=1,'Model Inputs'!$B$26,"") | BB40: =IF(AND(AS40="",AY40="",AZ40="",BA40="",BC40=""),"",IF(BC40<>"",BC40,AT40+IF(AY40="",0,AY40)+IF(AZ40="",0,AZ40)+IF(BA40="",0,BA40))) | BL40: =IF(C40="Working",LOOKUP(2,1/($BL$19:BL39<>""),$BL$19:BL39),"") | BM40: =IF(C40="Working",LOOKUP(2,1/($BM$19:BM39<>""),$BM$19:BM39),"")
A41: 23 | B41: =IF(BB41="","",BB41) | C41: =IF(B41="","Retired","Working") -> Retired | D41: =IF(OR(C41="Retired",B41=""),0,MIN(B41,'Tax Assumptions'!$B$19)) -> 0 | G41: =IF(C41="Working",MAX(B41-D41-E41-'Tax Assumptions'!$B$8,0),0) -> 0 | H41: =IF(G41=0,0,LOOKUP(G41,'Tax Assumptions'!$F$9:$F$15,'Tax Assumptions'!$I$9:$I$15)+(G41-LOOKUP(G41,'Tax Assumptions'!$F$9:$F$15,'Tax Assumptions'!$F$9:$F$15))*LOOKUP(G41,'Tax Assumptions'!$F$9:$F$15,'Tax Assumptions'!$H$9:$H$15)) -> 0 | I41: =IF(C41="Working",MIN(MAX(B41-E41,0),'Tax Assumptions'!$B$11)*'Tax Assumptions'!$B$10,0) -> 0 | J41: =IF(C41="Working",MAX(B41-E41,0)*'Tax Assumptions'!$B$12,0) -> 0 | K41: =IF(C41="Working",MAX(MAX(B41-E41,0)-'Tax Assumptions'!$B$14,0)*'Tax Assumptions'!$B$13,0) -> 0 | L41: =IF(C41="Working",MIN(B41*'Tax Assumptions'!$B$15,'Tax Assumptions'!$B$16),0) -> 0 | M41: =IF(C41="Working",MIN(B41*'Tax Assumptions'!$B$17,'Tax Assumptions'!$B$18),0) -> 0 | N41: =IF(C41="Working",MAX(B41-D41-'Tax Assumptions'!$B$9,0),0) -> 0 | O41: =IF(N41=0,0,LOOKUP(N41,'Tax Assumptions'!$K$9:$K$17,'Tax Assumptions'!$N$9:$N$17)+(N41-LOOKUP(N41,'Tax Assumptions'!$K$9:$K$17,'Tax Assumptions'!$K$9:$K$17))*LOOKUP(N41,'Tax Assumptions'!$K$9:$K$17,'Tax Assumptions'!$M$9:$M$17)) -> 0 | P41: =IF(N41=0,0,LOOKUP(N41,'Tax Assumptions'!$P$9:$P$12,'Tax Assumptions'!$S$9:$S$12)+(N41-LOOKUP(N41,'Tax Assumptions'!$P$9:$P$12,'Tax Assumptions'!$P$9:$P$12))*LOOKUP(N41,'Tax Assumptions'!$P$9:$P$12,'Tax Assumptions'!$R$9:$R$12)) -> 0 | Q41: =H41+I41+J41+K41+L41+M41+O41+P41 -> 0 | R41: =IF(C41="Working",B41-D41-E41-F41-Q41,0) -> 0 | S41: =IF(C41="Working",IF(BL41="","",BL41*(1+'Model Inputs'!$B$35)^(AN41-1)),"") | T41: =IF(C41="Working",IF(BM41="","",BM41*(1+'Model Inputs'!$B$36)^(AN41-1)),"") | U41: =IF(C41="Working",R41-S41-T41,0) -> 0 | V41: =IF(C41="Working",MIN(MAX(U41,0),'Tax Assumptions'!$B$20),0) -> 0 | W41: =IF(C41="Working",U41-V41,0) -> 0 | X41: =IF(C41="Working",W41+V41+D41+E41,0) -> 0 | Y41: =IF(C41="Retired",$B$13,0) -> 200000 | Z41: =AA41+AB41+AC41+AD41 -> 200000 | AA41: =IF(C41="Retired",MIN(Y41,((AE40)*(1+$B$15)+IF(C41="Working",W41,0))),0) -> 200000 | AB41: =IF(C41="Retired",MIN(MAX(Y41-AA41,0),((AF40)*(1+$B$15)+IF(C41="Working",D41,0))),0) -> 0 | AC41: =IF(C41="Retired",MIN(MAX(Y41-AA41-AB41,0),((AG40)*(1+$B$15)+IF(C41="Working",V41,0))),0) -> 0 | AD41: =IF(C41="Retired",MIN(MAX(Y41-AA41-AB41-AC41,0),((AH40)*(1+$B$15)+IF(C41="Working",E41,0))),0) -> 0 | AE41: =MAX(((AE40)*(1+$B$15)+IF(C41="Working",W41,0))-AA41,0) -> 9039178.5 | AF41: =MAX(((AF40)*(1+$B$15)+IF(C41="Working",D41,0))-AB41,0) -> 688785.41 | AG41: =MAX(((AG40)*(1+$B$15)+IF(C41="Working",V41,0))-AC41,0) -> 210852.68 | AH41: =MAX(((AH40)*(1+$B$15)+IF(C41="Working",E41,0))-AD41,0) -> 0 | AI41: =AE41+AF41+AG41+AH41 -> 9938816.6 | AJ41: =IF(C41="Working",AJ40+X41,MAX(AJ40-MIN(Y41,AJ40),0)) -> 2717592.2 | AK41: =IF(C41="Working",AK40*(1+$B$16)+X41,MAX(AK40*(1+$B$16)-MIN(Y41,AK40*(1+$B$16)),0)) -> 14403500 | AL41: =IF(C41="Working",IF(B41=0,0,W41/B41),0) -> 0 | AM41: =IF(C41="Working",IF(B41=0,0,X41/B41),0) -> 0 | AN41: =A41 -> 23 | AO41: ='Model Inputs'!$B$22+AN41-1 -> 2048 | AP41: =IF(AND(AQ41="",AR41="",AX41="",BA41="",BC41=""),"",IF(AN41=1,(13-'Model Inputs'!$B$23)/12,1)) | AQ41: =IF(OR(AN41<='Model Inputs'!$B$24,AR41<>"",AX41<>"",BA41<>"",BC41<>""),'Model Inputs'!$B$25*(1+'Model Inputs'!$B$31)^(AN41-1),"") | AS41: =IF(AP41="","",IF(AR41="",AQ41,AR41)) | AT41: =IF(AS41="","",AP41*AS41) | AU41: =IF(AP41="","",IF(AN41=1,AP41*'Model Inputs'!$B$27,IF(AN41<=MAX(2,'Model Inputs'!$B$30),'Model Inputs'!$B$27*(1+'Model Inputs'!$B$28)^(AN41-2),'Model Inputs'!$B$27*(1+'Model Inputs'!$B$28)^(MAX(2,'Model Inputs'!$B$30)-2)*(1+'Model Inputs'!$B$29)^(AN41-MAX(2,'Model Inputs'!$B$30))))) | AV41: =IF(AU41="","",IF(AN41<=2,0,'Model Inputs'!$B$32*SIN(2*PI()*(AN41-2+'Model Inputs'!$B$34)/MAX(1,'Model Inputs'!$B$33)))) | AY41: =IF(AP41="","",IF(BC41<>"",MAX(BC41-AT41-IF(AZ41="",0,AZ41)-IF(BA41="",0,BA41),0),IF(AX41<>"",AX41,AU41*(1+IF(AW41="",AV41,AW41))))) | AZ41: =IF(AN41=1,'Model Inputs'!$B$26,"") | BB41: =IF(AND(AS41="",AY41="",AZ41="",BA41="",BC41=""),"",IF(BC41<>"",BC41,AT41+IF(AY41="",0,AY41)+IF(AZ41="",0,AZ41)+IF(BA41="",0,BA41))) | BL41: =IF(C41="Working",LOOKUP(2,1/($BL$19:BL40<>""),$BL$19:BL40),"") | BM41: =IF(C41="Working",LOOKUP(2,1/($BM$19:BM40<>""),$BM$19:BM40),"")
A42: 24 | B42: =IF(BB42="","",BB42) | C42: =IF(B42="","Retired","Working") -> Retired | D42: =IF(OR(C42="Retired",B42=""),0,MIN(B42,'Tax Assumptions'!$B$19)) -> 0 | G42: =IF(C42="Working",MAX(B42-D42-E42-'Tax Assumptions'!$B$8,0),0) -> 0 | H42: =IF(G42=0,0,LOOKUP(G42,'Tax Assumptions'!$F$9:$F$15,'Tax Assumptions'!$I$9:$I$15)+(G42-LOOKUP(G42,'Tax Assumptions'!$F$9:$F$15,'Tax Assumptions'!$F$9:$F$15))*LOOKUP(G42,'Tax Assumptions'!$F$9:$F$15,'Tax Assumptions'!$H$9:$H$15)) -> 0 | I42: =IF(C42="Working",MIN(MAX(B42-E42,0),'Tax Assumptions'!$B$11)*'Tax Assumptions'!$B$10,0) -> 0 | J42: =IF(C42="Working",MAX(B42-E42,0)*'Tax Assumptions'!$B$12,0) -> 0 | K42: =IF(C42="Working",MAX(MAX(B42-E42,0)-'Tax Assumptions'!$B$14,0)*'Tax Assumptions'!$B$13,0) -> 0 | L42: =IF(C42="Working",MIN(B42*'Tax Assumptions'!$B$15,'Tax Assumptions'!$B$16),0) -> 0 | M42: =IF(C42="Working",MIN(B42*'Tax Assumptions'!$B$17,'Tax Assumptions'!$B$18),0) -> 0 | N42: =IF(C42="Working",MAX(B42-D42-'Tax Assumptions'!$B$9,0),0) -> 0 | O42: =IF(N42=0,0,LOOKUP(N42,'Tax Assumptions'!$K$9:$K$17,'Tax Assumptions'!$N$9:$N$17)+(N42-LOOKUP(N42,'Tax Assumptions'!$K$9:$K$17,'Tax Assumptions'!$K$9:$K$17))*LOOKUP(N42,'Tax Assumptions'!$K$9:$K$17,'Tax Assumptions'!$M$9:$M$17)) -> 0 | P42: =IF(N42=0,0,LOOKUP(N42,'Tax Assumptions'!$P$9:$P$12,'Tax Assumptions'!$S$9:$S$12)+(N42-LOOKUP(N42,'Tax Assumptions'!$P$9:$P$12,'Tax Assumptions'!$P$9:$P$12))*LOOKUP(N42,'Tax Assumptions'!$P$9:$P$12,'Tax Assumptions'!$R$9:$R$12)) -> 0 | Q42: =H42+I42+J42+K42+L42+M42+O42+P42 -> 0 | R42: =IF(C42="Working",B42-D42-E42-F42-Q42,0) -> 0 | S42: =IF(C42="Working",IF(BL42="","",BL42*(1+'Model Inputs'!$B$35)^(AN42-1)),"") | T42: =IF(C42="Working",IF(BM42="","",BM42*(1+'Model Inputs'!$B$36)^(AN42-1)),"") | U42: =IF(C42="Working",R42-S42-T42,0) -> 0 | V42: =IF(C42="Working",MIN(MAX(U42,0),'Tax Assumptions'!$B$20),0) -> 0 | W42: =IF(C42="Working",U42-V42,0) -> 0 | X42: =IF(C42="Working",W42+V42+D42+E42,0) -> 0 | Y42: =IF(C42="Retired",$B$13,0) -> 200000 | Z42: =AA42+AB42+AC42+AD42 -> 200000 | AA42: =IF(C42="Retired",MIN(Y42,((AE41)*(1+$B$15)+IF(C42="Working",W42,0))),0) -> 200000 | AB42: =IF(C42="Retired",MIN(MAX(Y42-AA42,0),((AF41)*(1+$B$15)+IF(C42="Working",D42,0))),0) -> 0 | AC42: =IF(C42="Retired",MIN(MAX(Y42-AA42-AB42,0),((AG41)*(1+$B$15)+IF(C42="Working",V42,0))),0) -> 0 | AD42: =IF(C42="Retired",MIN(MAX(Y42-AA42-AB42-AC42,0),((AH41)*(1+$B$15)+IF(C42="Working",E42,0))),0) -> 0 | AE42: =MAX(((AE41)*(1+$B$15)+IF(C42="Working",W42,0))-AA42,0) -> 9381529.2 | AF42: =MAX(((AF41)*(1+$B$15)+IF(C42="Working",D42,0))-AB42,0) -> 730112.53 | AG42: =MAX(((AG41)*(1+$B$15)+IF(C42="Working",V42,0))-AC42,0) -> 223503.84 | AH42: =MAX(((AH41)*(1+$B$15)+IF(C42="Working",E42,0))-AD42,0) -> 0 | AI42: =AE42+AF42+AG42+AH42 -> 10335146 | AJ42: =IF(C42="Working",AJ41+X42,MAX(AJ41-MIN(Y42,AJ41),0)) -> 2517592.2 | AK42: =IF(C42="Working",AK41*(1+$B$16)+X42,MAX(AK41*(1+$B$16)-MIN(Y42,AK41*(1+$B$16)),0)) -> 15355780 | AL42: =IF(C42="Working",IF(B42=0,0,W42/B42),0) -> 0 | AM42: =IF(C42="Working",IF(B42=0,0,X42/B42),0) -> 0 | AN42: =A42 -> 24 | AO42: ='Model Inputs'!$B$22+AN42-1 -> 2049 | AP42: =IF(AND(AQ42="",AR42="",AX42="",BA42="",BC42=""),"",IF(AN42=1,(13-'Model Inputs'!$B$23)/12,1)) | AQ42: =IF(OR(AN42<='Model Inputs'!$B$24,AR42<>"",AX42<>"",BA42<>"",BC42<>""),'Model Inputs'!$B$25*(1+'Model Inputs'!$B$31)^(AN42-1),"") | AS42: =IF(AP42="","",IF(AR42="",AQ42,AR42)) | AT42: =IF(AS42="","",AP42*AS42) | AU42: =IF(AP42="","",IF(AN42=1,AP42*'Model Inputs'!$B$27,IF(AN42<=MAX(2,'Model Inputs'!$B$30),'Model Inputs'!$B$27*(1+'Model Inputs'!$B$28)^(AN42-2),'Model Inputs'!$B$27*(1+'Model Inputs'!$B$28)^(MAX(2,'Model Inputs'!$B$30)-2)*(1+'Model Inputs'!$B$29)^(AN42-MAX(2,'Model Inputs'!$B$30))))) | AV42: =IF(AU42="","",IF(AN42<=2,0,'Model Inputs'!$B$32*SIN(2*PI()*(AN42-2+'Model Inputs'!$B$34)/MAX(1,'Model Inputs'!$B$33)))) | AY42: =IF(AP42="","",IF(BC42<>"",MAX(BC42-AT42-IF(AZ42="",0,AZ42)-IF(BA42="",0,BA42),0),IF(AX42<>"",AX42,AU42*(1+IF(AW42="",AV42,AW42))))) | AZ42: =IF(AN42=1,'Model Inputs'!$B$26,"") | BB42: =IF(AND(AS42="",AY42="",AZ42="",BA42="",BC42=""),"",IF(BC42<>"",BC42,AT42+IF(AY42="",0,AY42)+IF(AZ42="",0,AZ42)+IF(BA42="",0,BA42))) | BL42: =IF(C42="Working",LOOKUP(2,1/($BL$19:BL41<>""),$BL$19:BL41),"") | BM42: =IF(C42="Working",LOOKUP(2,1/($BM$19:BM41<>""),$BM$19:BM41),"")
A43: 25 | B43: =IF(BB43="","",BB43) | C43: =IF(B43="","Retired","Working") -> Retired | D43: =IF(OR(C43="Retired",B43=""),0,MIN(B43,'Tax Assumptions'!$B$19)) -> 0 | G43: =IF(C43="Working",MAX(B43-D43-E43-'Tax Assumptions'!$B$8,0),0) -> 0 | H43: =IF(G43=0,0,LOOKUP(G43,'Tax Assumptions'!$F$9:$F$15,'Tax Assumptions'!$I$9:$I$15)+(G43-LOOKUP(G43,'Tax Assumptions'!$F$9:$F$15,'Tax Assumptions'!$F$9:$F$15))*LOOKUP(G43,'Tax Assumptions'!$F$9:$F$15,'Tax Assumptions'!$H$9:$H$15)) -> 0 | I43: =IF(C43="Working",MIN(MAX(B43-E43,0),'Tax Assumptions'!$B$11)*'Tax Assumptions'!$B$10,0) -> 0 | J43: =IF(C43="Working",MAX(B43-E43,0)*'Tax Assumptions'!$B$12,0) -> 0 | K43: =IF(C43="Working",MAX(MAX(B43-E43,0)-'Tax Assumptions'!$B$14,0)*'Tax Assumptions'!$B$13,0) -> 0 | L43: =IF(C43="Working",MIN(B43*'Tax Assumptions'!$B$15,'Tax Assumptions'!$B$16),0) -> 0 | M43: =IF(C43="Working",MIN(B43*'Tax Assumptions'!$B$17,'Tax Assumptions'!$B$18),0) -> 0 | N43: =IF(C43="Working",MAX(B43-D43-'Tax Assumptions'!$B$9,0),0) -> 0 | O43: =IF(N43=0,0,LOOKUP(N43,'Tax Assumptions'!$K$9:$K$17,'Tax Assumptions'!$N$9:$N$17)+(N43-LOOKUP(N43,'Tax Assumptions'!$K$9:$K$17,'Tax Assumptions'!$K$9:$K$17))*LOOKUP(N43,'Tax Assumptions'!$K$9:$K$17,'Tax Assumptions'!$M$9:$M$17)) -> 0 | P43: =IF(N43=0,0,LOOKUP(N43,'Tax Assumptions'!$P$9:$P$12,'Tax Assumptions'!$S$9:$S$12)+(N43-LOOKUP(N43,'Tax Assumptions'!$P$9:$P$12,'Tax Assumptions'!$P$9:$P$12))*LOOKUP(N43,'Tax Assumptions'!$P$9:$P$12,'Tax Assumptions'!$R$9:$R$12)) -> 0 | Q43: =H43+I43+J43+K43+L43+M43+O43+P43 -> 0 | R43: =IF(C43="Working",B43-D43-E43-F43-Q43,0) -> 0 | S43: =IF(C43="Working",IF(BL43="","",BL43*(1+'Model Inputs'!$B$35)^(AN43-1)),"") | T43: =IF(C43="Working",IF(BM43="","",BM43*(1+'Model Inputs'!$B$36)^(AN43-1)),"") | U43: =IF(C43="Working",R43-S43-T43,0) -> 0 | V43: =IF(C43="Working",MIN(MAX(U43,0),'Tax Assumptions'!$B$20),0) -> 0 | W43: =IF(C43="Working",U43-V43,0) -> 0 | X43: =IF(C43="Working",W43+V43+D43+E43,0) -> 0 | Y43: =IF(C43="Retired",$B$13,0) -> 200000 | Z43: =AA43+AB43+AC43+AD43 -> 200000 | AA43: =IF(C43="Retired",MIN(Y43,((AE42)*(1+$B$15)+IF(C43="Working",W43,0))),0) -> 200000 | AB43: =IF(C43="Retired",MIN(MAX(Y43-AA43,0),((AF42)*(1+$B$15)+IF(C43="Working",D43,0))),0) -> 0 | AC43: =IF(C43="Retired",MIN(MAX(Y43-AA43-AB43,0),((AG42)*(1+$B$15)+IF(C43="Working",V43,0))),0) -> 0 | AD43: =IF(C43="Retired",MIN(MAX(Y43-AA43-AB43-AC43,0),((AH42)*(1+$B$15)+IF(C43="Working",E43,0))),0) -> 0 | AE43: =MAX(((AE42)*(1+$B$15)+IF(C43="Working",W43,0))-AA43,0) -> 9744421 | AF43: =MAX(((AF42)*(1+$B$15)+IF(C43="Working",D43,0))-AB43,0) -> 773919.28 | AG43: =MAX(((AG42)*(1+$B$15)+IF(C43="Working",V43,0))-AC43,0) -> 236914.07 | AH43: =MAX(((AH42)*(1+$B$15)+IF(C43="Working",E43,0))-AD43,0) -> 0 | AI43: =AE43+AF43+AG43+AH43 -> 10755254 | AJ43: =IF(C43="Working",AJ42+X43,MAX(AJ42-MIN(Y43,AJ42),0)) -> 2317592.2 | AK43: =IF(C43="Working",AK42*(1+$B$16)+X43,MAX(AK42*(1+$B$16)-MIN(Y43,AK42*(1+$B$16)),0)) -> 16384243 | AL43: =IF(C43="Working",IF(B43=0,0,W43/B43),0) -> 0 | AM43: =IF(C43="Working",IF(B43=0,0,X43/B43),0) -> 0 | AN43: =A43 -> 25 | AO43: ='Model Inputs'!$B$22+AN43-1 -> 2050 | AP43: =IF(AND(AQ43="",AR43="",AX43="",BA43="",BC43=""),"",IF(AN43=1,(13-'Model Inputs'!$B$23)/12,1)) | AQ43: =IF(OR(AN43<='Model Inputs'!$B$24,AR43<>"",AX43<>"",BA43<>"",BC43<>""),'Model Inputs'!$B$25*(1+'Model Inputs'!$B$31)^(AN43-1),"") | AS43: =IF(AP43="","",IF(AR43="",AQ43,AR43)) | AT43: =IF(AS43="","",AP43*AS43) | AU43: =IF(AP43="","",IF(AN43=1,AP43*'Model Inputs'!$B$27,IF(AN43<=MAX(2,'Model Inputs'!$B$30),'Model Inputs'!$B$27*(1+'Model Inputs'!$B$28)^(AN43-2),'Model Inputs'!$B$27*(1+'Model Inputs'!$B$28)^(MAX(2,'Model Inputs'!$B$30)-2)*(1+'Model Inputs'!$B$29)^(AN43-MAX(2,'Model Inputs'!$B$30))))) | AV43: =IF(AU43="","",IF(AN43<=2,0,'Model Inputs'!$B$32*SIN(2*PI()*(AN43-2+'Model Inputs'!$B$34)/MAX(1,'Model Inputs'!$B$33)))) | AY43: =IF(AP43="","",IF(BC43<>"",MAX(BC43-AT43-IF(AZ43="",0,AZ43)-IF(BA43="",0,BA43),0),IF(AX43<>"",AX43,AU43*(1+IF(AW43="",AV43,AW43))))) | AZ43: =IF(AN43=1,'Model Inputs'!$B$26,"") | BB43: =IF(AND(AS43="",AY43="",AZ43="",BA43="",BC43=""),"",IF(BC43<>"",BC43,AT43+IF(AY43="",0,AY43)+IF(AZ43="",0,AZ43)+IF(BA43="",0,BA43))) | BL43: =IF(C43="Working",LOOKUP(2,1/($BL$19:BL42<>""),$BL$19:BL42),"") | BM43: =IF(C43="Working",LOOKUP(2,1/($BM$19:BM42<>""),$BM$19:BM42),"")
A44: 26 | B44: =IF(BB44="","",BB44) | C44: =IF(B44="","Retired","Working") -> Retired | D44: =IF(OR(C44="Retired",B44=""),0,MIN(B44,'Tax Assumptions'!$B$19)) -> 0 | G44: =IF(C44="Working",MAX(B44-D44-E44-'Tax Assumptions'!$B$8,0),0) -> 0 | H44: =IF(G44=0,0,LOOKUP(G44,'Tax Assumptions'!$F$9:$F$15,'Tax Assumptions'!$I$9:$I$15)+(G44-LOOKUP(G44,'Tax Assumptions'!$F$9:$F$15,'Tax Assumptions'!$F$9:$F$15))*LOOKUP(G44,'Tax Assumptions'!$F$9:$F$15,'Tax Assumptions'!$H$9:$H$15)) -> 0 | I44: =IF(C44="Working",MIN(MAX(B44-E44,0),'Tax Assumptions'!$B$11)*'Tax Assumptions'!$B$10,0) -> 0 | J44: =IF(C44="Working",MAX(B44-E44,0)*'Tax Assumptions'!$B$12,0) -> 0 | K44: =IF(C44="Working",MAX(MAX(B44-E44,0)-'Tax Assumptions'!$B$14,0)*'Tax Assumptions'!$B$13,0) -> 0 | L44: =IF(C44="Working",MIN(B44*'Tax Assumptions'!$B$15,'Tax Assumptions'!$B$16),0) -> 0 | M44: =IF(C44="Working",MIN(B44*'Tax Assumptions'!$B$17,'Tax Assumptions'!$B$18),0) -> 0 | N44: =IF(C44="Working",MAX(B44-D44-'Tax Assumptions'!$B$9,0),0) -> 0 | O44: =IF(N44=0,0,LOOKUP(N44,'Tax Assumptions'!$K$9:$K$17,'Tax Assumptions'!$N$9:$N$17)+(N44-LOOKUP(N44,'Tax Assumptions'!$K$9:$K$17,'Tax Assumptions'!$K$9:$K$17))*LOOKUP(N44,'Tax Assumptions'!$K$9:$K$17,'Tax Assumptions'!$M$9:$M$17)) -> 0 | P44: =IF(N44=0,0,LOOKUP(N44,'Tax Assumptions'!$P$9:$P$12,'Tax Assumptions'!$S$9:$S$12)+(N44-LOOKUP(N44,'Tax Assumptions'!$P$9:$P$12,'Tax Assumptions'!$P$9:$P$12))*LOOKUP(N44,'Tax Assumptions'!$P$9:$P$12,'Tax Assumptions'!$R$9:$R$12)) -> 0 | Q44: =H44+I44+J44+K44+L44+M44+O44+P44 -> 0 | R44: =IF(C44="Working",B44-D44-E44-F44-Q44,0) -> 0 | S44: =IF(C44="Working",IF(BL44="","",BL44*(1+'Model Inputs'!$B$35)^(AN44-1)),"") | T44: =IF(C44="Working",IF(BM44="","",BM44*(1+'Model Inputs'!$B$36)^(AN44-1)),"") | U44: =IF(C44="Working",R44-S44-T44,0) -> 0 | V44: =IF(C44="Working",MIN(MAX(U44,0),'Tax Assumptions'!$B$20),0) -> 0 | W44: =IF(C44="Working",U44-V44,0) -> 0 | X44: =IF(C44="Working",W44+V44+D44+E44,0) -> 0 | Y44: =IF(C44="Retired",$B$13,0) -> 200000 | Z44: =AA44+AB44+AC44+AD44 -> 200000 | AA44: =IF(C44="Retired",MIN(Y44,((AE43)*(1+$B$15)+IF(C44="Working",W44,0))),0) -> 200000 | AB44: =IF(C44="Retired",MIN(MAX(Y44-AA44,0),((AF43)*(1+$B$15)+IF(C44="Working",D44,0))),0) -> 0 | AC44: =IF(C44="Retired",MIN(MAX(Y44-AA44-AB44,0),((AG43)*(1+$B$15)+IF(C44="Working",V44,0))),0) -> 0 | AD44: =IF(C44="Retired",MIN(MAX(Y44-AA44-AB44-AC44,0),((AH43)*(1+$B$15)+IF(C44="Working",E44,0))),0) -> 0 | AE44: =MAX(((AE43)*(1+$B$15)+IF(C44="Working",W44,0))-AA44,0) -> 10129086 | AF44: =MAX(((AF43)*(1+$B$15)+IF(C44="Working",D44,0))-AB44,0) -> 820354.44 | AG44: =MAX(((AG43)*(1+$B$15)+IF(C44="Working",V44,0))-AC44,0) -> 251128.91 | AH44: =MAX(((AH43)*(1+$B$15)+IF(C44="Working",E44,0))-AD44,0) -> 0 | AI44: =AE44+AF44+AG44+AH44 -> 11200570 | AJ44: =IF(C44="Working",AJ43+X44,MAX(AJ43-MIN(Y44,AJ43),0)) -> 2117592.2 | AK44: =IF(C44="Working",AK43*(1+$B$16)+X44,MAX(AK43*(1+$B$16)-MIN(Y44,AK43*(1+$B$16)),0)) -> 17494982 | AL44: =IF(C44="Working",IF(B44=0,0,W44/B44),0) -> 0 | AM44: =IF(C44="Working",IF(B44=0,0,X44/B44),0) -> 0 | AN44: =A44 -> 26 | AO44: ='Model Inputs'!$B$22+AN44-1 -> 2051 | AP44: =IF(AND(AQ44="",AR44="",AX44="",BA44="",BC44=""),"",IF(AN44=1,(13-'Model Inputs'!$B$23)/12,1)) | AQ44: =IF(OR(AN44<='Model Inputs'!$B$24,AR44<>"",AX44<>"",BA44<>"",BC44<>""),'Model Inputs'!$B$25*(1+'Model Inputs'!$B$31)^(AN44-1),"") | AS44: =IF(AP44="","",IF(AR44="",AQ44,AR44)) | AT44: =IF(AS44="","",AP44*AS44) | AU44: =IF(AP44="","",IF(AN44=1,AP44*'Model Inputs'!$B$27,IF(AN44<=MAX(2,'Model Inputs'!$B$30),'Model Inputs'!$B$27*(1+'Model Inputs'!$B$28)^(AN44-2),'Model Inputs'!$B$27*(1+'Model Inputs'!$B$28)^(MAX(2,'Model Inputs'!$B$30)-2)*(1+'Model Inputs'!$B$29)^(AN44-MAX(2,'Model Inputs'!$B$30))))) | AV44: =IF(AU44="","",IF(AN44<=2,0,'Model Inputs'!$B$32*SIN(2*PI()*(AN44-2+'Model Inputs'!$B$34)/MAX(1,'Model Inputs'!$B$33)))) | AY44: =IF(AP44="","",IF(BC44<>"",MAX(BC44-AT44-IF(AZ44="",0,AZ44)-IF(BA44="",0,BA44),0),IF(AX44<>"",AX44,AU44*(1+IF(AW44="",AV44,AW44))))) | AZ44: =IF(AN44=1,'Model Inputs'!$B$26,"") | BB44: =IF(AND(AS44="",AY44="",AZ44="",BA44="",BC44=""),"",IF(BC44<>"",BC44,AT44+IF(AY44="",0,AY44)+IF(AZ44="",0,AZ44)+IF(BA44="",0,BA44))) | BL44: =IF(C44="Working",LOOKUP(2,1/($BL$19:BL43<>""),$BL$19:BL43),"") | BM44: =IF(C44="Working",LOOKUP(2,1/($BM$19:BM43<>""),$BM$19:BM43),"")
A45: 27 | B45: =IF(BB45="","",BB45) | C45: =IF(B45="","Retired","Working") -> Retired | D45: =IF(OR(C45="Retired",B45=""),0,MIN(B45,'Tax Assumptions'!$B$19)) -> 0 | G45: =IF(C45="Working",MAX(B45-D45-E45-'Tax Assumptions'!$B$8,0),0) -> 0 | H45: =IF(G45=0,0,LOOKUP(G45,'Tax Assumptions'!$F$9:$F$15,'Tax Assumptions'!$I$9:$I$15)+(G45-LOOKUP(G45,'Tax Assumptions'!$F$9:$F$15,'Tax Assumptions'!$F$9:$F$15))*LOOKUP(G45,'Tax Assumptions'!$F$9:$F$15,'Tax Assumptions'!$H$9:$H$15)) -> 0 | I45: =IF(C45="Working",MIN(MAX(B45-E45,0),'Tax Assumptions'!$B$11)*'Tax Assumptions'!$B$10,0) -> 0 | J45: =IF(C45="Working",MAX(B45-E45,0)*'Tax Assumptions'!$B$12,0) -> 0 | K45: =IF(C45="Working",MAX(MAX(B45-E45,0)-'Tax Assumptions'!$B$14,0)*'Tax Assumptions'!$B$13,0) -> 0 | L45: =IF(C45="Working",MIN(B45*'Tax Assumptions'!$B$15,'Tax Assumptions'!$B$16),0) -> 0 | M45: =IF(C45="Working",MIN(B45*'Tax Assumptions'!$B$17,'Tax Assumptions'!$B$18),0) -> 0 | N45: =IF(C45="Working",MAX(B45-D45-'Tax Assumptions'!$B$9,0),0) -> 0 | O45: =IF(N45=0,0,LOOKUP(N45,'Tax Assumptions'!$K$9:$K$17,'Tax Assumptions'!$N$9:$N$17)+(N45-LOOKUP(N45,'Tax Assumptions'!$K$9:$K$17,'Tax Assumptions'!$K$9:$K$17))*LOOKUP(N45,'Tax Assumptions'!$K$9:$K$17,'Tax Assumptions'!$M$9:$M$17)) -> 0 | P45: =IF(N45=0,0,LOOKUP(N45,'Tax Assumptions'!$P$9:$P$12,'Tax Assumptions'!$S$9:$S$12)+(N45-LOOKUP(N45,'Tax Assumptions'!$P$9:$P$12,'Tax Assumptions'!$P$9:$P$12))*LOOKUP(N45,'Tax Assumptions'!$P$9:$P$12,'Tax Assumptions'!$R$9:$R$12)) -> 0 | Q45: =H45+I45+J45+K45+L45+M45+O45+P45 -> 0 | R45: =IF(C45="Working",B45-D45-E45-F45-Q45,0) -> 0 | S45: =IF(C45="Working",IF(BL45="","",BL45*(1+'Model Inputs'!$B$35)^(AN45-1)),"") | T45: =IF(C45="Working",IF(BM45="","",BM45*(1+'Model Inputs'!$B$36)^(AN45-1)),"") | U45: =IF(C45="Working",R45-S45-T45,0) -> 0 | V45: =IF(C45="Working",MIN(MAX(U45,0),'Tax Assumptions'!$B$20),0) -> 0 | W45: =IF(C45="Working",U45-V45,0) -> 0 | X45: =IF(C45="Working",W45+V45+D45+E45,0) -> 0 | Y45: =IF(C45="Retired",$B$13,0) -> 200000 | Z45: =AA45+AB45+AC45+AD45 -> 200000 | AA45: =IF(C45="Retired",MIN(Y45,((AE44)*(1+$B$15)+IF(C45="Working",W45,0))),0) -> 200000 | AB45: =IF(C45="Retired",MIN(MAX(Y45-AA45,0),((AF44)*(1+$B$15)+IF(C45="Working",D45,0))),0) -> 0 | AC45: =IF(C45="Retired",MIN(MAX(Y45-AA45-AB45,0),((AG44)*(1+$B$15)+IF(C45="Working",V45,0))),0) -> 0 | AD45: =IF(C45="Retired",MIN(MAX(Y45-AA45-AB45-AC45,0),((AH44)*(1+$B$15)+IF(C45="Working",E45,0))),0) -> 0 | AE45: =MAX(((AE44)*(1+$B$15)+IF(C45="Working",W45,0))-AA45,0) -> 10536831 | AF45: =MAX(((AF44)*(1+$B$15)+IF(C45="Working",D45,0))-AB45,0) -> 869575.7 | AG45: =MAX(((AG44)*(1+$B$15)+IF(C45="Working",V45,0))-AC45,0) -> 266196.64 | AH45: =MAX(((AH44)*(1+$B$15)+IF(C45="Working",E45,0))-AD45,0) -> 0 | AI45: =AE45+AF45+AG45+AH45 -> 11672604 | AJ45: =IF(C45="Working",AJ44+X45,MAX(AJ44-MIN(Y45,AJ44),0)) -> 1917592.2 | AK45: =IF(C45="Working",AK44*(1+$B$16)+X45,MAX(AK44*(1+$B$16)-MIN(Y45,AK44*(1+$B$16)),0)) -> 18694581 | AL45: =IF(C45="Working",IF(B45=0,0,W45/B45),0) -> 0 | AM45: =IF(C45="Working",IF(B45=0,0,X45/B45),0) -> 0 | AN45: =A45 -> 27 | AO45: ='Model Inputs'!$B$22+AN45-1 -> 2052 | AP45: =IF(AND(AQ45="",AR45="",AX45="",BA45="",BC45=""),"",IF(AN45=1,(13-'Model Inputs'!$B$23)/12,1)) | AQ45: =IF(OR(AN45<='Model Inputs'!$B$24,AR45<>"",AX45<>"",BA45<>"",BC45<>""),'Model Inputs'!$B$25*(1+'Model Inputs'!$B$31)^(AN45-1),"") | AS45: =IF(AP45="","",IF(AR45="",AQ45,AR45)) | AT45: =IF(AS45="","",AP45*AS45) | AU45: =IF(AP45="","",IF(AN45=1,AP45*'Model Inputs'!$B$27,IF(AN45<=MAX(2,'Model Inputs'!$B$30),'Model Inputs'!$B$27*(1+'Model Inputs'!$B$28)^(AN45-2),'Model Inputs'!$B$27*(1+'Model Inputs'!$B$28)^(MAX(2,'Model Inputs'!$B$30)-2)*(1+'Model Inputs'!$B$29)^(AN45-MAX(2,'Model Inputs'!$B$30))))) | AV45: =IF(AU45="","",IF(AN45<=2,0,'Model Inputs'!$B$32*SIN(2*PI()*(AN45-2+'Model Inputs'!$B$34)/MAX(1,'Model Inputs'!$B$33)))) | AY45: =IF(AP45="","",IF(BC45<>"",MAX(BC45-AT45-IF(AZ45="",0,AZ45)-IF(BA45="",0,BA45),0),IF(AX45<>"",AX45,AU45*(1+IF(AW45="",AV45,AW45))))) | AZ45: =IF(AN45=1,'Model Inputs'!$B$26,"") | BB45: =IF(AND(AS45="",AY45="",AZ45="",BA45="",BC45=""),"",IF(BC45<>"",BC45,AT45+IF(AY45="",0,AY45)+IF(AZ45="",0,AZ45)+IF(BA45="",0,BA45))) | BL45: =IF(C45="Working",LOOKUP(2,1/($BL$19:BL44<>""),$BL$19:BL44),"") | BM45: =IF(C45="Working",LOOKUP(2,1/($BM$19:BM44<>""),$BM$19:BM44),"")
A46: 28 | B46: =IF(BB46="","",BB46) | C46: =IF(B46="","Retired","Working") -> Retired | D46: =IF(OR(C46="Retired",B46=""),0,MIN(B46,'Tax Assumptions'!$B$19)) -> 0 | G46: =IF(C46="Working",MAX(B46-D46-E46-'Tax Assumptions'!$B$8,0),0) -> 0 | H46: =IF(G46=0,0,LOOKUP(G46,'Tax Assumptions'!$F$9:$F$15,'Tax Assumptions'!$I$9:$I$15)+(G46-LOOKUP(G46,'Tax Assumptions'!$F$9:$F$15,'Tax Assumptions'!$F$9:$F$15))*LOOKUP(G46,'Tax Assumptions'!$F$9:$F$15,'Tax Assumptions'!$H$9:$H$15)) -> 0 | I46: =IF(C46="Working",MIN(MAX(B46-E46,0),'Tax Assumptions'!$B$11)*'Tax Assumptions'!$B$10,0) -> 0 | J46: =IF(C46="Working",MAX(B46-E46,0)*'Tax Assumptions'!$B$12,0) -> 0 | K46: =IF(C46="Working",MAX(MAX(B46-E46,0)-'Tax Assumptions'!$B$14,0)*'Tax Assumptions'!$B$13,0) -> 0 | L46: =IF(C46="Working",MIN(B46*'Tax Assumptions'!$B$15,'Tax Assumptions'!$B$16),0) -> 0 | M46: =IF(C46="Working",MIN(B46*'Tax Assumptions'!$B$17,'Tax Assumptions'!$B$18),0) -> 0 | N46: =IF(C46="Working",MAX(B46-D46-'Tax Assumptions'!$B$9,0),0) -> 0 | O46: =IF(N46=0,0,LOOKUP(N46,'Tax Assumptions'!$K$9:$K$17,'Tax Assumptions'!$N$9:$N$17)+(N46-LOOKUP(N46,'Tax Assumptions'!$K$9:$K$17,'Tax Assumptions'!$K$9:$K$17))*LOOKUP(N46,'Tax Assumptions'!$K$9:$K$17,'Tax Assumptions'!$M$9:$M$17)) -> 0 | P46: =IF(N46=0,0,LOOKUP(N46,'Tax Assumptions'!$P$9:$P$12,'Tax Assumptions'!$S$9:$S$12)+(N46-LOOKUP(N46,'Tax Assumptions'!$P$9:$P$12,'Tax Assumptions'!$P$9:$P$12))*LOOKUP(N46,'Tax Assumptions'!$P$9:$P$12,'Tax Assumptions'!$R$9:$R$12)) -> 0 | Q46: =H46+I46+J46+K46+L46+M46+O46+P46 -> 0 | R46: =IF(C46="Working",B46-D46-E46-F46-Q46,0) -> 0 | S46: =IF(C46="Working",IF(BL46="","",BL46*(1+'Model Inputs'!$B$35)^(AN46-1)),"") | T46: =IF(C46="Working",IF(BM46="","",BM46*(1+'Model Inputs'!$B$36)^(AN46-1)),"") | U46: =IF(C46="Working",R46-S46-T46,0) -> 0 | V46: =IF(C46="Working",MIN(MAX(U46,0),'Tax Assumptions'!$B$20),0) -> 0 | W46: =IF(C46="Working",U46-V46,0) -> 0 | X46: =IF(C46="Working",W46+V46+D46+E46,0) -> 0 | Y46: =IF(C46="Retired",$B$13,0) -> 200000 | Z46: =AA46+AB46+AC46+AD46 -> 200000 | AA46: =IF(C46="Retired",MIN(Y46,((AE45)*(1+$B$15)+IF(C46="Working",W46,0))),0) -> 200000 | AB46: =IF(C46="Retired",MIN(MAX(Y46-AA46,0),((AF45)*(1+$B$15)+IF(C46="Working",D46,0))),0) -> 0 | AC46: =IF(C46="Retired",MIN(MAX(Y46-AA46-AB46,0),((AG45)*(1+$B$15)+IF(C46="Working",V46,0))),0) -> 0 | AD46: =IF(C46="Retired",MIN(MAX(Y46-AA46-AB46-AC46,0),((AH45)*(1+$B$15)+IF(C46="Working",E46,0))),0) -> 0 | AE46: =MAX(((AE45)*(1+$B$15)+IF(C46="Working",W46,0))-AA46,0) -> 10969041 | AF46: =MAX(((AF45)*(1+$B$15)+IF(C46="Working",D46,0))-AB46,0) -> 921750.25 | AG46: =MAX(((AG45)*(1+$B$15)+IF(C46="Working",V46,0))-AC46,0) -> 282168.44 | AH46: =MAX(((AH45)*(1+$B$15)+IF(C46="Working",E46,0))-AD46,0) -> 0 | AI46: =AE46+AF46+AG46+AH46 -> 12172960 | AJ46: =IF(C46="Working",AJ45+X46,MAX(AJ45-MIN(Y46,AJ45),0)) -> 1717592.2 | AK46: =IF(C46="Working",AK45*(1+$B$16)+X46,MAX(AK45*(1+$B$16)-MIN(Y46,AK45*(1+$B$16)),0)) -> 19990147 | AL46: =IF(C46="Working",IF(B46=0,0,W46/B46),0) -> 0 | AM46: =IF(C46="Working",IF(B46=0,0,X46/B46),0) -> 0 | AN46: =A46 -> 28 | AO46: ='Model Inputs'!$B$22+AN46-1 -> 2053 | AP46: =IF(AND(AQ46="",AR46="",AX46="",BA46="",BC46=""),"",IF(AN46=1,(13-'Model Inputs'!$B$23)/12,1)) | AQ46: =IF(OR(AN46<='Model Inputs'!$B$24,AR46<>"",AX46<>"",BA46<>"",BC46<>""),'Model Inputs'!$B$25*(1+'Model Inputs'!$B$31)^(AN46-1),"") | AS46: =IF(AP46="","",IF(AR46="",AQ46,AR46)) | AT46: =IF(AS46="","",AP46*AS46) | AU46: =IF(AP46="","",IF(AN46=1,AP46*'Model Inputs'!$B$27,IF(AN46<=MAX(2,'Model Inputs'!$B$30),'Model Inputs'!$B$27*(1+'Model Inputs'!$B$28)^(AN46-2),'Model Inputs'!$B$27*(1+'Model Inputs'!$B$28)^(MAX(2,'Model Inputs'!$B$30)-2)*(1+'Model Inputs'!$B$29)^(AN46-MAX(2,'Model Inputs'!$B$30))))) | AV46: =IF(AU46="","",IF(AN46<=2,0,'Model Inputs'!$B$32*SIN(2*PI()*(AN46-2+'Model Inputs'!$B$34)/MAX(1,'Model Inputs'!$B$33)))) | AY46: =IF(AP46="","",IF(BC46<>"",MAX(BC46-AT46-IF(AZ46="",0,AZ46)-IF(BA46="",0,BA46),0),IF(AX46<>"",AX46,AU46*(1+IF(AW46="",AV46,AW46))))) | AZ46: =IF(AN46=1,'Model Inputs'!$B$26,"") | BB46: =IF(AND(AS46="",AY46="",AZ46="",BA46="",BC46=""),"",IF(BC46<>"",BC46,AT46+IF(AY46="",0,AY46)+IF(AZ46="",0,AZ46)+IF(BA46="",0,BA46))) | BL46: =IF(C46="Working",LOOKUP(2,1/($BL$19:BL45<>""),$BL$19:BL45),"") | BM46: =IF(C46="Working",LOOKUP(2,1/($BM$19:BM45<>""),$BM$19:BM45),"")
... A58: 40 | B58: =IF(BB58="","",BB58) | C58: =IF(B58="","Retired","Working") -> Retired | D58: =IF(OR(C58="Retired",B58=""),0,MIN(B58,'Tax Assumptions'!$B$19)) -> 0 | G58: =IF(C58="Working",MAX(B58-D58-E58-'Tax Assumptions'!$B$8,0),0) -> 0 | H58: =IF(G58=0,0,LOOKUP(G58,'Tax Assumptions'!$F$9:$F$15,'Tax Assumptions'!$I$9:$I$15)+(G58-LOOKUP(G58,'Tax Assumptions'!$F$9:$F$15,'Tax Assumptions'!$F$9:$F$15))*LOOKUP(G58,'Tax Assumptions'!$F$9:$F$15,'Tax Assumptions'!$H$9:$H$15)) -> 0 | I58: =IF(C58="Working",MIN(MAX(B58-E58,0),'Tax Assumptions'!$B$11)*'Tax Assumptions'!$B$10,0) -> 0 | J58: =IF(C58="Working",MAX(B58-E58,0)*'Tax Assumptions'!$B$12,0) -> 0 | K58: =IF(C58="Working",MAX(MAX(B58-E58,0)-'Tax Assumptions'!$B$14,0)*'Tax Assumptions'!$B$13,0) -> 0 | L58: =IF(C58="Working",MIN(B58*'Tax Assumptions'!$B$15,'Tax Assumptions'!$B$16),0) -> 0 | M58: =IF(C58="Working",MIN(B58*'Tax Assumptions'!$B$17,'Tax Assumptions'!$B$18),0) -> 0 | N58: =IF(C58="Working",MAX(B58-D58-'Tax Assumptions'!$B$9,0),0) -> 0 | O58: =IF(N58=0,0,LOOKUP(N58,'Tax Assumptions'!$K$9:$K$17,'Tax Assumptions'!$N$9:$N$17)+(N58-LOOKUP(N58,'Tax Assumptions'!$K$9:$K$17,'Tax Assumptions'!$K$9:$K$17))*LOOKUP(N58,'Tax Assumptions'!$K$9:$K$17,'Tax Assumptions'!$M$9:$M$17)) -> 0 | P58: =IF(N58=0,0,LOOKUP(N58,'Tax Assumptions'!$P$9:$P$12,'Tax Assumptions'!$S$9:$S$12)+(N58-LOOKUP(N58,'Tax Assumptions'!$P$9:$P$12,'Tax Assumptions'!$P$9:$P$12))*LOOKUP(N58,'Tax Assumptions'!$P$9:$P$12,'Tax Assumptions'!$R$9:$R$12)) -> 0 | Q58: =H58+I58+J58+K58+L58+M58+O58+P58 -> 0 | R58: =IF(C58="Working",B58-D58-E58-F58-Q58,0) -> 0 | S58: =IF(C58="Working",IF(BL58="","",BL58*(1+'Model Inputs'!$B$35)^(AN58-1)),"") | T58: =IF(C58="Working",IF(BM58="","",BM58*(1+'Model Inputs'!$B$36)^(AN58-1)),"") | U58: =IF(C58="Working",R58-S58-T58,0) -> 0 | V58: =IF(C58="Working",MIN(MAX(U58,0),'Tax Assumptions'!$B$20),0) -> 0 | W58: =IF(C58="Working",U58-V58,0) -> 0 | X58: =IF(C58="Working",W58+V58+D58+E58,0) -> 0 | Y58: =IF(C58="Retired",$B$13,0) -> 200000 | Z58: =AA58+AB58+AC58+AD58 -> 200000 | AA58: =IF(C58="Retired",MIN(Y58,((AE57)*(1+$B$15)+IF(C58="Working",W58,0))),0) -> 200000 | AB58: =IF(C58="Retired",MIN(MAX(Y58-AA58,0),((AF57)*(1+$B$15)+IF(C58="Working",D58,0))),0) -> 0 | AC58: =IF(C58="Retired",MIN(MAX(Y58-AA58-AB58,0),((AG57)*(1+$B$15)+IF(C58="Working",V58,0))),0) -> 0 | AD58: =IF(C58="Retired",MIN(MAX(Y58-AA58-AB58-AC58,0),((AH57)*(1+$B$15)+IF(C58="Working",E58,0))),0) -> 0 | AE58: =MAX(((AE57)*(1+$B$15)+IF(C58="Working",W58,0))-AA58,0) -> 18697878 | AF58: =MAX(((AF57)*(1+$B$15)+IF(C58="Working",D58,0))-AB58,0) -> 1854742.6 | AG58: =MAX(((AG57)*(1+$B$15)+IF(C58="Working",V58,0))-AC58,0) -> 567778.35 | AH58: =MAX(((AH57)*(1+$B$15)+IF(C58="Working",E58,0))-AD58,0) -> 0 | AI58: =AE58+AF58+AG58+AH58 -> 21120399 | AJ58: =IF(C58="Working",AJ57+X58,MAX(AJ57-MIN(Y58,AJ57),0)) -> 0 | AK58: =IF(C58="Working",AK57*(1+$B$16)+X58,MAX(AK57*(1+$B$16)-MIN(Y58,AK57*(1+$B$16)),0)) -> 46543165 | AL58: =IF(C58="Working",IF(B58=0,0,W58/B58),0) -> 0 | AM58: =IF(C58="Working",IF(B58=0,0,X58/B58),0) -> 0 | AN58: =A58 -> 40 | AO58: ='Model Inputs'!$B$22+AN58-1 -> 2065 | AP58: =IF(AND(AQ58="",AR58="",AX58="",BA58="",BC58=""),"",IF(AN58=1,(13-'Model Inputs'!$B$23)/12,1)) | AQ58: =IF(OR(AN58<='Model Inputs'!$B$24,AR58<>"",AX58<>"",BA58<>"",BC58<>""),'Model Inputs'!$B$25*(1+'Model Inputs'!$B$31)^(AN58-1),"") | AS58: =IF(AP58="","",IF(AR58="",AQ58,AR58)) | AT58: =IF(AS58="","",AP58*AS58) | AU58: =IF(AP58="","",IF(AN58=1,AP58*'Model Inputs'!$B$27,IF(AN58<=MAX(2,'Model Inputs'!$B$30),'Model Inputs'!$B$27*(1+'Model Inputs'!$B$28)^(AN58-2),'Model Inputs'!$B$27*(1+'Model Inputs'!$B$28)^(MAX(2,'Model Inputs'!$B$30)-2)*(1+'Model Inputs'!$B$29)^(AN58-MAX(2,'Model Inputs'!$B$30))))) | AV58: =IF(AU58="","",IF(AN58<=2,0,'Model Inputs'!$B$32*SIN(2*PI()*(AN58-2+'Model Inputs'!$B$34)/MAX(1,'Model Inputs'!$B$33)))) | AY58: =IF(AP58="","",IF(BC58<>"",MAX(BC58-AT58-IF(AZ58="",0,AZ58)-IF(BA58="",0,BA58),0),IF(AX58<>"",AX58,AU58*(1+IF(AW58="",AV58,AW58))))) | AZ58: =IF(AN58=1,'Model Inputs'!$B$26,"") | BB58: =IF(AND(AS58="",AY58="",AZ58="",BA58="",BC58=""),"",IF(BC58<>"",BC58,AT58+IF(AY58="",0,AY58)+IF(AZ58="",0,AZ58)+IF(BA58="",0,BA58))) | BL58: =IF(C58="Working",LOOKUP(2,1/($BL$19:BL57<>""),$BL$19:BL57),"") | BM58: =IF(C58="Working",LOOKUP(2,1/($BM$19:BM57<>""),$BM$19:BM57),"")
A59: Totals / Ending | B59: =SUM(B19:B58) -> 12380228 | D59: =SUM(D19:D58) -> 245000 | E59: =SUM(E19:E58) -> 0 | F59: =SUM(F19:F58) -> 0 | H59: =SUM(H19:H58) -> 3998158.9 | I59: =SUM(I19:I58) -> 114390 | J59: =SUM(J19:J58) -> 179513.31 | K59: =SUM(K19:K58) -> 93422.052 | L59: =SUM(L19:L58) -> 4119.1 | M59: =SUM(M19:M58) -> 312 | O59: =SUM(O19:O58) -> 897322.08 | P59: =SUM(P19:P58) -> 466012.34 | Q59: =SUM(Q19:Q58) -> 5753249.7 | R59: =SUM(R19:R58) -> 6381978.3 | S59: =SUM(S19:S58) -> 906492.07 | T59: =SUM(T19:T58) -> 552893.97 | V59: =SUM(V19:V58) -> 75000 | W59: =SUM(W19:W58) -> 4847592.2 | X59: =SUM(X19:X58) -> 5167592.2 | Y59: =SUM(Y19:Y58) -> 6000000 | Z59: =SUM(Z19:Z58) -> 6000000 | AA59: =SUM(AA19:AA58) -> 6000000 | AB59: =SUM(AB19:AB58) -> 0 | AC59: =SUM(AC19:AC58) -> 0 | AD59: =SUM(AD19:AD58) -> 0 | AE59: =AE58 -> 18697878 | AF59: =AF58 -> 1854742.6 | AG59: =AG58 -> 567778.35 | AH59: =AH58 -> 0 | AI59: =AI58 -> 21120399 | AJ59: =AJ58 -> 0 | AK59: =AK58 -> 46543165 | AL59: =AVERAGEIF(AL19:AL58,">0",AL19:AL58) -> 0.36621862 | AM59: =AVERAGEIF(AM19:AM58,">0",AM19:AM58) -> 0.4017882

Sheet Scenario Lab
A1: Scenario Lab
A2: Downside, base, and upside cases all stay visible here. Edit the assumptions on Model Inputs; this sheet shows the linked scenario calculations in full, including a retirement-distance down-payment policy and a separate burn-control recommendation.
A4: Linked Assumptions (Edit Model Inputs) | F4: Scenario Summary | P4: Use Model Inputs for global scenario edits. This sheet reuses the visible base earnings path from Savings Projection, then layers on scenario multipliers, earlier-retirement caps, baseline non-housing retirement spend, and a full house-cost stack.
A5: Scenario | B5: ='Model Inputs'!$F$5 -> Downside | C5: ='Model Inputs'!$G$5 -> Base | D5: ='Model Inputs'!$H$5 -> Upside | F5: Metric | G5: =B5 -> Downside | H5: =C5 -> Base | I5: =D5 -> Upside
A6: Gross comp multiplier | B6: ='Model Inputs'!$F$6 -> 0.75 | C6: ='Model Inputs'!$G$6 -> 1 | D6: ='Model Inputs'!$H$6 -> 1.2 | F6: Gross comp multiplier | G6: =$B$6 -> 0.75 | H6: =$C$6 -> 1 | I6: =$D$6 -> 1.2
A7: Tax multiplier | B7: ='Model Inputs'!$F$7 -> 1.04 | C7: ='Model Inputs'!$G$7 -> 1 | D7: ='Model Inputs'!$H$7 -> 0.97 | F7: Return assumption | G7: =$B$10 -> 0.04 | H7: =$C$10 -> 0.06 | I7: =$D$10 -> 0.09
A8: Rent multiplier | B8: ='Model Inputs'!$F$8 -> 1 | C8: ='Model Inputs'!$G$8 -> 1 | D8: ='Model Inputs'!$H$8 -> 1.05 | F8: Baseline retirement spend | G8: =$B$12 -> 170000 | H8: =$C$12 -> 200000 | I8: =$D$12 -> 240000
A9: Living multiplier | B9: ='Model Inputs'!$F$9 -> 0.95 | C9: ='Model Inputs'!$G$9 -> 1 | D9: ='Model Inputs'!$H$9 -> 1.08 | F9: Home purchase year | G9: =$B$13 -> 10 | H9: =$C$13 -> 10 | I9: =$D$13 -> 10
A10: Return assumption | B10: ='Model Inputs'!$F$10 -> 0.04 | C10: ='Model Inputs'!$G$10 -> 0.06 | D10: ='Model Inputs'!$H$10 -> 0.09 | F10: Home purchase price | G10: =$B$14 -> 5000000 | H10: =$C$14 -> 5000000 | I10: =$D$14 -> 5000000
A11: Retire after YOE cap | B11: ='Model Inputs'!$F$11 -> 12 | C11: ='Model Inputs'!$G$11 -> 10 | D11: ='Model Inputs'!$H$11 -> 9 | F11: Cash required at purchase | G11: =INDEX(AB32:AB71,MAX(1,MIN($B$13,ROWS(Y32:Y71)))) -> 2025000 | H11: =INDEX(AB80:AB119,MAX(1,MIN($C$13,ROWS(Y80:Y119)))) -> 2375000 | I11: =INDEX(AB128:AB167,MAX(1,MIN($D$13,ROWS(Y128:Y167)))) -> 2125000
A12: Baseline retirement spend (non-housing) | B12: ='Model Inputs'!$F$12 -> 170000 | C12: ='Model Inputs'!$G$12 -> 200000 | D12: ='Model Inputs'!$H$12 -> 240000 | F12: Liquid wealth at retirement | G12: =INDEX(Y32:Y71,IF(COUNTIF(B32:B71,"Working")=0,1,COUNTIF(B32:B71,"Working"))) -> 1797689.5 | H12: =INDEX(Y80:Y119,IF(COUNTIF(B80:B119,"Working")=0,1,COUNTIF(B80:B119,"Working"))) -> 3736659.2 | I12: =INDEX(Y128:Y167,IF(COUNTIF(B128:B167,"Working")=0,1,COUNTIF(B128:B167,"Working"))) -> 6815408.6
A13: Home purchase year | B13: ='Model Inputs'!$F$13 -> 10 | C13: ='Model Inputs'!$G$13 -> 10 | D13: ='Model Inputs'!$H$13 -> 10 | F13: Liquid wealth before close | G13: =INDEX(Y32:Y71,MAX(1,MIN($B$13,ROWS(Y32:Y71))))+INDEX(AB32:AB71,MAX(1,MIN($B$13,ROWS(Y32:Y71)))) -> 3822689.5 | H13: =INDEX(Y80:Y119,MAX(1,MIN($C$13,ROWS(Y80:Y119))))+INDEX(AB80:AB119,MAX(1,MIN($C$13,ROWS(Y80:Y119)))) -> 6111659.2 | I13: =INDEX(Y128:Y167,MAX(1,MIN($D$13,ROWS(Y128:Y167))))+INDEX(AB128:AB167,MAX(1,MIN($D$13,ROWS(Y128:Y167)))) -> 6851250.9
A14: Home purchase price | B14: ='Model Inputs'!$F$14 -> 5000000 | C14: ='Model Inputs'!$G$14 -> 5000000 | D14: ='Model Inputs'!$H$14 -> 5000000 | F14: Liquid wealth after close | G14: =INDEX(Y32:Y71,MAX(1,MIN($B$13,ROWS(Y32:Y71)))) -> 1797689.5 | H14: =INDEX(Y80:Y119,MAX(1,MIN($C$13,ROWS(Y80:Y119)))) -> 3736659.2 | I14: =INDEX(Y128:Y167,MAX(1,MIN($D$13,ROWS(Y128:Y167)))) -> 4726250.9
A15: Effective down payment % | B15: =IF(B29<>"",B29,MAX(B26,MIN(B27,B26+MAX(0,MIN(1,1-MAX(B11-B13,0)/MAX(B28,1)))*(B27-B26)))) -> 0.38 | C15: =IF(C29<>"",C29,MAX(C26,MIN(C27,C26+MAX(0,MIN(1,1-MAX(C11-C13,0)/MAX(C28,1)))*(C27-C26)))) -> 0.45 | D15: =IF(D29<>"",D29,MAX(D26,MIN(D27,D26+MAX(0,MIN(1,1-MAX(D11-D13,0)/MAX(D28,1)))*(D27-D26)))) -> 0.4 | F15: Annual housing carry at retirement | G15: =INDEX(AC32:AC71,IF(COUNTIF(B32:B71,"Working")=0,1,COUNTIF(B32:B71,"Working"))) -> 345129.3 | H15: =INDEX(AC80:AC119,IF(COUNTIF(B80:B119,"Working")=0,1,COUNTIF(B80:B119,"Working"))) -> 318582.45 | I15: =INDEX(AC128:AC167,IF(COUNTIF(B128:B167,"Working")=0,1,COUNTIF(B128:B167,"Working"))) -> 0
A16: Mortgage rate | B16: ='Model Inputs'!$F$16 -> 0.065 | C16: ='Model Inputs'!$G$16 -> 0.065 | D16: ='Model Inputs'!$H$16 -> 0.065 | F16: Total retirement need | G16: =$B$12+INDEX(AC32:AC71,IF(COUNTIF(B32:B71,"Working")=0,1,COUNTIF(B32:B71,"Working"))) -> 515129.3 | H16: =$C$12+INDEX(AC80:AC119,IF(COUNTIF(B80:B119,"Working")=0,1,COUNTIF(B80:B119,"Working"))) -> 518582.45 | I16: =$D$12+INDEX(AC128:AC167,IF(COUNTIF(B128:B167,"Working")=0,1,COUNTIF(B128:B167,"Working"))) -> 240000
A17: Mortgage term (years) | B17: ='Model Inputs'!$F$17 -> 30 | C17: ='Model Inputs'!$G$17 -> 30 | D17: ='Model Inputs'!$H$17 -> 30 | F17: Housing share of total spend at retirement | G17: =IF(($B$12+INDEX(AC32:AC71,IF(COUNTIF(B32:B71,"Working")=0,1,COUNTIF(B32:B71,"Working"))))=0,0,(INDEX(AC32:AC71,IF(COUNTIF(B32:B71,"Working")=0,1,COUNTIF(B32:B71,"Working"))))/($B$12+INDEX(AC32:AC71,IF(COUNTIF(B32:B71,"Working")=0,1,COUNTIF(B32:B71,"Working"))))) -> 0.66998577 | H17: =IF(($C$12+INDEX(AC80:AC119,IF(COUNTIF(B80:B119,"Working")=0,1,COUNTIF(B80:B119,"Working"))))=0,0,(INDEX(AC80:AC119,IF(COUNTIF(B80:B119,"Working")=0,1,COUNTIF(B80:B119,"Working"))))/($C$12+INDEX(AC80:AC119,IF(COUNTIF(B80:B119,"Working")=0,1,COUNTIF(B80:B119,"Working"))))) -> 0.61433326 | I17: =IF(($D$12+INDEX(AC128:AC167,IF(COUNTIF(B128:B167,"Working")=0,1,COUNTIF(B128:B167,"Working"))))=0,0,(INDEX(AC128:AC167,IF(COUNTIF(B128:B167,"Working")=0,1,COUNTIF(B128:B167,"Working"))))/($D$12+INDEX(AC128:AC167,IF(COUNTIF(B128:B167,"Working")=0,1,COUNTIF(B128:B167,"Working"))))) -> 0
A18: Closing costs % | B18: ='Model Inputs'!$F$18 -> 0.025 | C18: ='Model Inputs'!$G$18 -> 0.025 | D18: ='Model Inputs'!$H$18 -> 0.025 | F18: All-in draw rate on liquid wealth at retirement | G18: =IF((INDEX(Y32:Y71,IF(COUNTIF(B32:B71,"Working")=0,1,COUNTIF(B32:B71,"Working"))))=0,0,($B$12+INDEX(AC32:AC71,IF(COUNTIF(B32:B71,"Working")=0,1,COUNTIF(B32:B71,"Working"))))/(INDEX(Y32:Y71,IF(COUNTIF(B32:B71,"Working")=0,1,COUNTIF(B32:B71,"Working"))))) -> 0.28655077 | H18: =IF((INDEX(Y80:Y119,IF(COUNTIF(B80:B119,"Working")=0,1,COUNTIF(B80:B119,"Working"))))=0,0,($C$12+INDEX(AC80:AC119,IF(COUNTIF(B80:B119,"Working")=0,1,COUNTIF(B80:B119,"Working"))))/(INDEX(Y80:Y119,IF(COUNTIF(B80:B119,"Working")=0,1,COUNTIF(B80:B119,"Working"))))) -> 0.13878238 | I18: =IF((INDEX(Y128:Y167,IF(COUNTIF(B128:B167,"Working")=0,1,COUNTIF(B128:B167,"Working"))))=0,0,($D$12+INDEX(AC128:AC167,IF(COUNTIF(B128:B167,"Working")=0,1,COUNTIF(B128:B167,"Working"))))/(INDEX(Y128:Y167,IF(COUNTIF(B128:B167,"Working")=0,1,COUNTIF(B128:B167,"Working"))))) -> 0.035214323
A19: Property tax rate | B19: ='Model Inputs'!$F$19 -> 0.01 | C19: ='Model Inputs'!$G$19 -> 0.01 | D19: ='Model Inputs'!$H$19 -> 0.01 | F19: Max non-housing spend @ target draw | G19: =MAX('Model Inputs'!$B$16*INDEX(Y32:Y71,IF(COUNTIF(B32:B71,"Working")=0,1,COUNTIF(B32:B71,"Working")))-INDEX(AC32:AC71,IF(COUNTIF(B32:B71,"Working")=0,1,COUNTIF(B32:B71,"Working"))),0) -> 0 | H19: =MAX('Model Inputs'!$B$16*INDEX(Y80:Y119,IF(COUNTIF(B80:B119,"Working")=0,1,COUNTIF(B80:B119,"Working")))-INDEX(AC80:AC119,IF(COUNTIF(B80:B119,"Working")=0,1,COUNTIF(B80:B119,"Working"))),0) -> 0 | I19: =MAX('Model Inputs'!$B$16*INDEX(Y128:Y167,IF(COUNTIF(B128:B167,"Working")=0,1,COUNTIF(B128:B167,"Working")))-INDEX(AC128:AC167,IF(COUNTIF(B128:B167,"Working")=0,1,COUNTIF(B128:B167,"Working"))),0) -> 238539.3
A20: Home insurance rate | B20: ='Model Inputs'!$F$20 -> 0.002 | C20: ='Model Inputs'!$G$20 -> 0.002 | D20: ='Model Inputs'!$H$20 -> 0.002 | F20: Max house price @ liquidity floor at purchase | G20: =IF(($B$15+$B$18)<=0,0,MAX(INDEX(Y32:Y71,MAX(1,MIN($B$13,ROWS(Y32:Y71))))+INDEX(AB32:AB71,MAX(1,MIN($B$13,ROWS(Y32:Y71))))-'Model Inputs'!$B$18-$B$24,0)/($B$15+$B$18)) -> 6969603.7 | H20: =IF(($C$15+$C$18)<=0,0,MAX(INDEX(Y80:Y119,MAX(1,MIN($C$13,ROWS(Y80:Y119))))+INDEX(AB80:AB119,MAX(1,MIN($C$13,ROWS(Y80:Y119))))-'Model Inputs'!$B$18-$C$24,0)/($C$15+$C$18)) -> 10761388 | I20: =IF(($D$15+$D$18)<=0,0,MAX(INDEX(Y128:Y167,MAX(1,MIN($D$13,ROWS(Y128:Y167))))+INDEX(AB128:AB167,MAX(1,MIN($D$13,ROWS(Y128:Y167))))-'Model Inputs'!$B$18-$D$24,0)/($D$15+$D$18)) -> 13767649
A21: Home maintenance rate | B21: ='Model Inputs'!$F$21 -> 0.01 | C21: ='Model Inputs'!$G$21 -> 0.01 | D21: ='Model Inputs'!$H$21 -> 0.01 | F21: Max house price @ housing budget | G21: =IF((IF($B$17<=0,0,IF($B$16=0,(1-$B$15)/$B$17,-PMT($B$16/12,$B$17*12,(1-$B$15))*12))+$B$19+$B$20+$B$21)<=0,0,MAX((IF(OR('Model Inputs'!$B$17<=0,'Model Inputs'!$B$17>=1),0,$B$12*'Model Inputs'!$B$17/(1-'Model Inputs'!$B$17)))-($B$22+$B$23),0)/(IF($B$17<=0,0,IF($B$16=0,(1-$B$15)/$B$17,-PMT($B$16/12,$B$17*12,(1-$B$15))*12))+$B$19+$B$20+$B$21)) -> 1326147.3 | H21: =IF((IF($C$17<=0,0,IF($C$16=0,(1-$C$15)/$C$17,-PMT($C$16/12,$C$17*12,(1-$C$15))*12))+$C$19+$C$20+$C$21)<=0,0,MAX((IF(OR('Model Inputs'!$B$17<=0,'Model Inputs'!$B$17>=1),0,$C$12*'Model Inputs'!$B$17/(1-'Model Inputs'!$B$17)))-($C$22+$C$23),0)/(IF($C$17<=0,0,IF($C$16=0,(1-$C$15)/$C$17,-PMT($C$16/12,$C$17*12,(1-$C$15))*12))+$C$19+$C$20+$C$21)) -> 1690179.6 | I21: =IF((IF($D$17<=0,0,IF($D$16=0,(1-$D$15)/$D$17,-PMT($D$16/12,$D$17*12,(1-$D$15))*12))+$D$19+$D$20+$D$21)<=0,0,MAX((IF(OR('Model Inputs'!$B$17<=0,'Model Inputs'!$B$17>=1),0,$D$12*'Model Inputs'!$B$17/(1-'Model Inputs'!$B$17)))-($D$22+$D$23),0)/(IF($D$17<=0,0,IF($D$16=0,(1-$D$15)/$D$17,-PMT($D$16/12,$D$17*12,(1-$D$15))*12))+$D$19+$D$20+$D$21)) -> 1914277.6
A22: Annual HOA / common charges | B22: ='Model Inputs'!$F$22 -> 0 | C22: ='Model Inputs'!$G$22 -> 0 | D22: ='Model Inputs'!$H$22 -> 0 | F22: Planning max house by purchase + retirement rules | G22: =IF(AND(IF(($B$15+$B$18)<=0,0,MAX(INDEX(Y32:Y71,MAX(1,MIN($B$13,ROWS(Y32:Y71))))+INDEX(AB32:AB71,MAX(1,MIN($B$13,ROWS(Y32:Y71))))-'Model Inputs'!$B$18-$B$24,0)/($B$15+$B$18))>0,IF((IF($B$17<=0,0,IF($B$16=0,(1-$B$15)/$B$17,-PMT($B$16/12,$B$17*12,(1-$B$15))*12))+$B$19+$B$20+$B$21)<=0,0,MAX((IF(OR('Model Inputs'!$B$17<=0,'Model Inputs'!$B$17>=1),0,$B$12*'Model Inputs'!$B$17/(1-'Model Inputs'!$B$17)))-($B$22+$B$23),0)/(IF($B$17<=0,0,IF($B$16=0,(1-$B$15)/$B$17,-PMT($B$16/12,$B$17*12,(1-$B$15))*12))+$B$19+$B$20+$B$21))>0),MIN(IF(($B$15+$B$18)<=0,0,MAX(INDEX(Y32:Y71,MAX(1,MIN($B$13,ROWS(Y32:Y71))))+INDEX(AB32:AB71,MAX(1,MIN($B$13,ROWS(Y32:Y71))))-'Model Inputs'!$B$18-$B$24,0)/($B$15+$B$18)),IF((IF($B$17<=0,0,IF($B$16=0,(1-$B$15)/$B$17,-PMT($B$16/12,$B$17*12,(1-$B$15))*12))+$B$19+$B$20+$B$21)<=0,0,MAX((IF(OR('Model Inputs'!$B$17<=0,'Model Inputs'!$B$17>=1),0,$B$12*'Model Inputs'!$B$17/(1-'Model Inputs'!$B$17)))-($B$22+$B$23),0)/(IF($B$17<=0,0,IF($B$16=0,(1-$B$15)/$B$17,-PMT($B$16/12,$B$17*12,(1-$B$15))*12))+$B$19+$B$20+$B$21))),MAX(IF(($B$15+$B$18)<=0,0,MAX(INDEX(Y32:Y71,MAX(1,MIN($B$13,ROWS(Y32:Y71))))+INDEX(AB32:AB71,MAX(1,MIN($B$13,ROWS(Y32:Y71))))-'Model Inputs'!$B$18-$B$24,0)/($B$15+$B$18)),IF((IF($B$17<=0,0,IF($B$16=0,(1-$B$15)/$B$17,-PMT($B$16/12,$B$17*12,(1-$B$15))*12))+$B$19+$B$20+$B$21)<=0,0,MAX((IF(OR('Model Inputs'!$B$17<=0,'Model Inputs'!$B$17>=1),0,$B$12*'Model Inputs'!$B$17/(1-'Model Inputs'!$B$17)))-($B$22+$B$23),0)/(IF($B$17<=0,0,IF($B$16=0,(1-$B$15)/$B$17,-PMT($B$16/12,$B$17*12,(1-$B$15))*12))+$B$19+$B$20+$B$21)))) -> 1326147.3 | H22: =IF(AND(IF(($C$15+$C$18)<=0,0,MAX(INDEX(Y80:Y119,MAX(1,MIN($C$13,ROWS(Y80:Y119))))+INDEX(AB80:AB119,MAX(1,MIN($C$13,ROWS(Y80:Y119))))-'Model Inputs'!$B$18-$C$24,0)/($C$15+$C$18))>0,IF((IF($C$17<=0,0,IF($C$16=0,(1-$C$15)/$C$17,-PMT($C$16/12,$C$17*12,(1-$C$15))*12))+$C$19+$C$20+$C$21)<=0,0,MAX((IF(OR('Model Inputs'!$B$17<=0,'Model Inputs'!$B$17>=1),0,$C$12*'Model Inputs'!$B$17/(1-'Model Inputs'!$B$17)))-($C$22+$C$23),0)/(IF($C$17<=0,0,IF($C$16=0,(1-$C$15)/$C$17,-PMT($C$16/12,$C$17*12,(1-$C$15))*12))+$C$19+$C$20+$C$21))>0),MIN(IF(($C$15+$C$18)<=0,0,MAX(INDEX(Y80:Y119,MAX(1,MIN($C$13,ROWS(Y80:Y119))))+INDEX(AB80:AB119,MAX(1,MIN($C$13,ROWS(Y80:Y119))))-'Model Inputs'!$B$18-$C$24,0)/($C$15+$C$18)),IF((IF($C$17<=0,0,IF($C$16=0,(1-$C$15)/$C$17,-PMT($C$16/12,$C$17*12,(1-$C$15))*12))+$C$19+$C$20+$C$21)<=0,0,MAX((IF(OR('Model Inputs'!$B$17<=0,'Model Inputs'!$B$17>=1),0,$C$12*'Model Inputs'!$B$17/(1-'Model Inputs'!$B$17)))-($C$22+$C$23),0)/(IF($C$17<=0,0,IF($C$16=0,(1-$C$15)/$C$17,-PMT($C$16/12,$C$17*12,(1-$C$15))*12))+$C$19+$C$20+$C$21))),MAX(IF(($C$15+$C$18)<=0,0,MAX(INDEX(Y80:Y119,MAX(1,MIN($C$13,ROWS(Y80:Y119))))+INDEX(AB80:AB119,MAX(1,MIN($C$13,ROWS(Y80:Y119))))-'Model Inputs'!$B$18-$C$24,0)/($C$15+$C$18)),IF((IF($C$17<=0,0,IF($C$16=0,(1-$C$15)/$C$17,-PMT($C$16/12,$C$17*12,(1-$C$15))*12))+$C$19+$C$20+$C$21)<=0,0,MAX((IF(OR('Model Inputs'!$B$17<=0,'Model Inputs'!$B$17>=1),0,$C$12*'Model Inputs'!$B$17/(1-'Model Inputs'!$B$17)))-($C$22+$C$23),0)/(IF($C$17<=0,0,IF($C$16=0,(1-$C$15)/$C$17,-PMT($C$16/12,$C$17*12,(1-$C$15))*12))+$C$19+$C$20+$C$21)))) -> 1690179.6 | I22: =IF(AND(IF(($D$15+$D$18)<=0,0,MAX(INDEX(Y128:Y167,MAX(1,MIN($D$13,ROWS(Y128:Y167))))+INDEX(AB128:AB167,MAX(1,MIN($D$13,ROWS(Y128:Y167))))-'Model Inputs'!$B$18-$D$24,0)/($D$15+$D$18))>0,IF((IF($D$17<=0,0,IF($D$16=0,(1-$D$15)/$D$17,-PMT($D$16/12,$D$17*12,(1-$D$15))*12))+$D$19+$D$20+$D$21)<=0,0,MAX((IF(OR('Model Inputs'!$B$17<=0,'Model Inputs'!$B$17>=1),0,$D$12*'Model Inputs'!$B$17/(1-'Model Inputs'!$B$17)))-($D$22+$D$23),0)/(IF($D$17<=0,0,IF($D$16=0,(1-$D$15)/$D$17,-PMT($D$16/12,$D$17*12,(1-$D$15))*12))+$D$19+$D$20+$D$21))>0),MIN(IF(($D$15+$D$18)<=0,0,MAX(INDEX(Y128:Y167,MAX(1,MIN($D$13,ROWS(Y128:Y167))))+INDEX(AB128:AB167,MAX(1,MIN($D$13,ROWS(Y128:Y167))))-'Model Inputs'!$B$18-$D$24,0)/($D$15+$D$18)),IF((IF($D$17<=0,0,IF($D$16=0,(1-$D$15)/$D$17,-PMT($D$16/12,$D$17*12,(1-$D$15))*12))+$D$19+$D$20+$D$21)<=0,0,MAX((IF(OR('Model Inputs'!$B$17<=0,'Model Inputs'!$B$17>=1),0,$D$12*'Model Inputs'!$B$17/(1-'Model Inputs'!$B$17)))-($D$22+$D$23),0)/(IF($D$17<=0,0,IF($D$16=0,(1-$D$15)/$D$17,-PMT($D$16/12,$D$17*12,(1-$D$15))*12))+$D$19+$D$20+$D$21))),MAX(IF(($D$15+$D$18)<=0,0,MAX(INDEX(Y128:Y167,MAX(1,MIN($D$13,ROWS(Y128:Y167))))+INDEX(AB128:AB167,MAX(1,MIN($D$13,ROWS(Y128:Y167))))-'Model Inputs'!$B$18-$D$24,0)/($D$15+$D$18)),IF((IF($D$17<=0,0,IF($D$16=0,(1-$D$15)/$D$17,-PMT($D$16/12,$D$17*12,(1-$D$15))*12))+$D$19+$D$20+$D$21)<=0,0,MAX((IF(OR('Model Inputs'!$B$17<=0,'Model Inputs'!$B$17>=1),0,$D$12*'Model Inputs'!$B$17/(1-'Model Inputs'!$B$17)))-($D$22+$D$23),0)/(IF($D$17<=0,0,IF($D$16=0,(1-$D$15)/$D$17,-PMT($D$16/12,$D$17*12,(1-$D$15))*12))+$D$19+$D$20+$D$21)))) -> 1914277.6
A23: Annual home services / utilities | B23: ='Model Inputs'!$F$23 -> 0 | C23: ='Model Inputs'!$G$23 -> 0 | D23: ='Model Inputs'!$H$23 -> 0 | F23: Retired years funded | G23: =COUNTIFS(B32:B71,"Retired",Z32:Z71,0) -> 3 | H23: =COUNTIFS(B80:B119,"Retired",Z80:Z119,0) -> 9 | I23: =COUNTIFS(B128:B167,"Retired",Z128:Z167,0) -> 15
A24: One-time move / furnish reserve | B24: ='Model Inputs'!$F$24 -> 0 | C24: ='Model Inputs'!$G$24 -> 0 | D24: ='Model Inputs'!$H$24 -> 0 | F24: First shortfall year | G24: =IF(COUNTIF(Z32:Z71,">0")=0,0,INDEX(A32:A71,MATCH(1,INDEX((Z32:Z71>0)*1,0),0))) -> 14 | H24: =IF(COUNTIF(Z80:Z119,">0")=0,0,INDEX(A80:A119,MATCH(1,INDEX((Z80:Z119>0)*1,0),0))) -> 20 | I24: =IF(COUNTIF(Z128:Z167,">0")=0,0,INDEX(A128:A167,MATCH(1,INDEX((Z128:Z167>0)*1,0),0))) -> 25
A25: Home appreciation | B25: ='Model Inputs'!$F$25 -> 0.03 | C25: ='Model Inputs'!$G$25 -> 0.03 | D25: ='Model Inputs'!$H$25 -> 0.03 | F25: Ending liquid wealth | G25: =Y71 -> 0 | H25: =Y119 -> 0 | I25: =Y167 -> 0
A26: Minimum down payment % | B26: ='Model Inputs'!$F$15 -> 0.2 | C26: ='Model Inputs'!$G$15 -> 0.2 | D26: ='Model Inputs'!$H$15 -> 0.2 | F26: Ending home equity | G26: =AF71 -> 12136312 | H26: =AF119 -> 12136312 | I26: =AF167 -> 12136312
A27: Down payment % if buying at / after retirement | B27: ='Model Inputs'!$F$26 -> 0.5 | C27: ='Model Inputs'!$G$26 -> 0.45 | D27: ='Model Inputs'!$H$26 -> 0.4 | F27: Ending net worth | G27: =AG71 -> 12136312 | H27: =AG119 -> 12136312 | I27: =AG167 -> 12136312
A28: Working years until minimum down payment | B28: ='Model Inputs'!$F$27 -> 5 | C28: ='Model Inputs'!$G$27 -> 5 | D28: ='Model Inputs'!$H$27 -> 4 | F28: Working years after purchase | G28: =MAX(B11-B13,0) -> 2 | H28: =MAX(C11-C13,0) -> 0 | I28: =MAX(D11-D13,0) -> 0
A29: Manual down payment override % | B29: =IF('Model Inputs'!$F$28="","",'Model Inputs'!$F$28) | C29: =IF('Model Inputs'!$G$28="","",'Model Inputs'!$G$28) | D29: =IF('Model Inputs'!$H$28="","",'Model Inputs'!$H$28) | F29: Burn-control down payment % | G29: =IF(OR(B14<=0,IF(OR(B14<=0,B17<=0),0,IF(B16=0,1/B17,-PMT(B16/12,B17*12,1)*12))<=0),0,MAX(0,MIN(1,1-MAX(IF(OR('Model Inputs'!$B$17<=0,'Model Inputs'!$B$17>=1),0,B12*'Model Inputs'!$B$17/(1-'Model Inputs'!$B$17))-(B14*(B19+B20+B21)+B22+B23),0)/((IF(OR(B14<=0,B17<=0),0,IF(B16=0,1/B17,-PMT(B16/12,B17*12,1)*12)))*B14)))) -> 1 | H29: =IF(OR(C14<=0,IF(OR(C14<=0,C17<=0),0,IF(C16=0,1/C17,-PMT(C16/12,C17*12,1)*12))<=0),0,MAX(0,MIN(1,1-MAX(IF(OR('Model Inputs'!$B$17<=0,'Model Inputs'!$B$17>=1),0,C12*'Model Inputs'!$B$17/(1-'Model Inputs'!$B$17))-(C14*(C19+C20+C21)+C22+C23),0)/((IF(OR(C14<=0,C17<=0),0,IF(C16=0,1/C17,-PMT(C16/12,C17*12,1)*12)))*C14)))) -> 1 | I29: =IF(OR(D14<=0,IF(OR(D14<=0,D17<=0),0,IF(D16=0,1/D17,-PMT(D16/12,D17*12,1)*12))<=0),0,MAX(0,MIN(1,1-MAX(IF(OR('Model Inputs'!$B$17<=0,'Model Inputs'!$B$17>=1),0,D12*'Model Inputs'!$B$17/(1-'Model Inputs'!$B$17))-(D14*(D19+D20+D21)+D22+D23),0)/((IF(OR(D14<=0,D17<=0),0,IF(D16=0,1/D17,-PMT(D16/12,D17*12,1)*12)))*D14)))) -> 0.9492914
A30: =B$5&" Scenario" -> Downside Scenario
A31: Year | B31: Phase | C31: Base Gross | D31: Scenario Gross | E31: 401(k) | F31: HSA | G31: After-Tax Payroll | H31: Adj. Total Tax | I31: Post-Tax Cash | J31: Rent | K31: Living | L31: Roth | M31: Taxable Savings / (Draw) | N31: Net Portfolio Flow | O31: Planned Retirement Need | P31: Actual Withdrawal | Q31: Taxable Draw | R31: 401(k) Draw | S31: Roth Draw | T31: HSA Draw | U31: Taxable Balance | V31: 401(k) Balance | W31: Roth Balance | X31: HSA Balance | Y31: Liquid Wealth | Z31: Funding Gap | AA31: Total Savings Rate | AB31: Home Purchase Cash | AC31: Annual Housing Carry | AD31: House Value | AE31: Mortgage Balance | AF31: Home Equity | AG31: Net Worth Incl. Home
A32: 1 | B32: =IF(AND(C32>0,A32<=$B$11),"Working","Retired") -> Working | C32: =N('Savings Projection'!$B$19) -> 550000 | D32: =IF(B32="Working",C32*$B$6,0) -> 412500 | E32: =IF(OR(B32="Retired",D32=0),0,MIN(D32,'Tax Assumptions'!$B$19)) -> 24500 | F32: =IF(B32="Working",N('Savings Projection'!$E$19),0) -> 0 | G32: =IF(B32="Working",N('Savings Projection'!$F$19),0) -> 0 | H32: =IF(D32=0,0,((LOOKUP(MAX(D32-E32-F32-'Tax Assumptions'!$B$8,0),'Tax Assumptions'!$F$9:$F$15,'Tax Assumptions'!$I$9:$I$15)+(MAX(D32-E32-F32-'Tax Assumptions'!$B$8,0)-LOOKUP(MAX(D32-E32-F32-'Tax Assumptions'!$B$8,0),'Tax Assumptions'!$F$9:$F$15,'Tax Assumptions'!$F$9:$F$15))*LOOKUP(MAX(D32-E32-F32-'Tax Assumptions'!$B$8,0),'Tax Assumptions'!$F$9:$F$15,'Tax Assumptions'!$H$9:$H$15))+(MIN(MAX(D32-F32,0),'Tax Assumptions'!$B$11)*'Tax Assumptions'!$B$10)+(MAX(D32-F32,0)*'Tax Assumptions'!$B$12)+(MAX(MAX(D32-F32,0)-'Tax Assumptions'!$B$14,0)*'Tax Assumptions'!$B$13)+(MIN(D32*'Tax Assumptions'!$B$15,'Tax Assumptions'!$B$16))+(MIN(D32*'Tax Assumptions'!$B$17,'Tax Assumptions'!$B$18))+(LOOKUP(MAX(D32-E32-'Tax Assumptions'!$B$9,0),'Tax Assumptions'!$K$9:$K$17,'Tax Assumptions'!$N$9:$N$17)+(MAX(D32-E32-'Tax Assumptions'!$B$9,0)-LOOKUP(MAX(D32-E32-'Tax Assumptions'!$B$9,0),'Tax Assumptions'!$K$9:$K$17,'Tax Assumptions'!$K$9:$K$17))*LOOKUP(MAX(D32-E32-'Tax Assumptions'!$B$9,0),'Tax Assumptions'!$K$9:$K$17,'Tax Assumptions'!$M$9:$M$17))+(LOOKUP(MAX(D32-E32-'Tax Assumptions'!$B$9,0),'Tax Assumptions'!$P$9:$P$12,'Tax Assumptions'!$S$9:$S$12)+(MAX(D32-E32-'Tax Assumptions'!$B$9,0)-LOOKUP(MAX(D32-E32-'Tax Assumptions'!$B$9,0),'Tax Assumptions'!$P$9:$P$12,'Tax Assumptions'!$P$9:$P$12))*LOOKUP(MAX(D32-E32-'Tax Assumptions'!$B$9,0),'Tax Assumptions'!$P$9:$P$12,'Tax Assumptions'!$R$9:$R$12)))*$B$7) -> 162999.23 | I32: =IF(B32="Working",D32-E32-F32-G32-H32,0) -> 225000.77 | J32: =IF(B32="Working",N('Savings Projection'!$S$19)*$B$8,0) -> 78000 | K32: =IF(B32="Working",N('Savings Projection'!$T$19)*$B$9,0) -> 38000 | L32: =IF(B32="Working",MIN(MAX(I32-J32-K32-AB32-AC32,0),'Tax Assumptions'!$B$20),0) -> 7500 | M32: =IF(B32="Working",I32-J32-K32-L32-AB32-AC32,0) -> 101500.77 | N32: =IF(B32="Working",M32+L32+E32+F32,-P32) -> 133500.77 | O32: =IF(B32="Retired",$B$12+AB32+AC32,0) -> 0 | P32: =Q32+R32+S32+T32 -> 0 | Q32: =IF(B32="Retired",MIN((('Savings Projection'!$B$7)*(1+$B$10)+IF(B32="Working",M32,0)),O32),0) -> 0 | R32: =IF(B32="Retired",MIN(MAX(O32-Q32,0),(('Savings Projection'!$B$8)*(1+$B$10)+IF(B32="Working",E32,0))),0) -> 0 | S32: =IF(B32="Retired",MIN(MAX(O32-Q32-R32,0),(('Savings Projection'!$B$9)*(1+$B$10)+IF(B32="Working",L32,0))),0) -> 0 | T32: =IF(B32="Retired",MIN(MAX(O32-Q32-R32-S32,0),(('Savings Projection'!$B$10)*(1+$B$10)+IF(B32="Working",F32,0))),0) -> 0 | U32: =MAX((('Savings Projection'!$B$7)*(1+$B$10)+IF(B32="Working",M32,0))-Q32,0) -> 257500.77 | V32: =MAX((('Savings Projection'!$B$8)*(1+$B$10)+IF(B32="Working",E32,0))-R32,0) -> 24500 | W32: =MAX((('Savings Projection'!$B$9)*(1+$B$10)+IF(B32="Working",L32,0))-S32,0) -> 7500 | X32: =MAX((('Savings Projection'!$B$10)*(1+$B$10)+IF(B32="Working",F32,0))-T32,0) -> 0 | Y32: =U32+V32+W32+X32 -> 289500.77 | Z32: =IF(B32="Retired",MAX(O32-P32,0),0) -> 0 | AA32: =IF(B32="Working",IF(D32=0,0,N32/D32),0) -> 0.32363823 | AB32: =IF(AND($B$14>0,A32=$B$13),$B$14*($B$15+$B$18),0)+IF(AND($B$14>0,A32=$B$13),$B$24,0) -> 0 | AC32: =IF(OR($B$14<=0,A32<$B$13),0,IF(AND($B$14>0,$B$17>0,A32>=$B$13,A32<($B$13+$B$17)),IF($B$17<=0,0,IF($B$16=0,MAX($B$14*(1-$B$15),0)/$B$17,-PMT($B$16/12,$B$17*12,MAX($B$14*(1-$B$15),0))*12)),0)+AD32*($B$19+$B$20+$B$21)+$B$22+$B$23) -> 0 | AD32: =IF(AND($B$14>0,A32>=$B$13),$B$14*(1+$B$25)^(A32-$B$13),0) -> 0 | AE32: =IF(OR($B$14<=0,$B$17<=0,A32<$B$13,MIN(MAX((A32-$B$13+1)*12,0),$B$17*12)>=$B$17*12),0,IF($B$16=0,MAX(MAX($B$14*(1-$B$15),0)-(IF($B$17<=0,0,IF($B$16=0,MAX($B$14*(1-$B$15),0)/$B$17,-PMT($B$16/12,$B$17*12,MAX($B$14*(1-$B$15),0))*12))/12)*MIN(MAX((A32-$B$13+1)*12,0),$B$17*12),0),MAX(MAX($B$14*(1-$B$15),0)*(1+$B$16/12)^MIN(MAX((A32-$B$13+1)*12,0),$B$17*12)-(IF($B$17<=0,0,IF($B$16=0,MAX($B$14*(1-$B$15),0)/$B$17,-PMT($B$16/12,$B$17*12,MAX($B$14*(1-$B$15),0))*12))/12)*(((1+$B$16/12)^MIN(MAX((A32-$B$13+1)*12,0),$B$17*12)-1)/($B$16/12)),0))) -> 0 | AF32: =MAX(AD32-AE32,0) -> 0 | AG32: =Y32+AF32 -> 289500.77
A33: 2 | B33: =IF(AND(C33>0,A33<=$B$11),"Working","Retired") -> Working | C33: =N('Savings Projection'!$B$20) -> 412500 | D33: =IF(B33="Working",C33*$B$6,0) -> 309375 | E33: =IF(OR(B33="Retired",D33=0),0,MIN(D33,'Tax Assumptions'!$B$19)) -> 24500 | F33: =IF(B33="Working",N('Savings Projection'!$E$20),0) -> 0 | G33: =IF(B33="Working",N('Savings Projection'!$F$20),0) -> 0 | H33: =IF(D33=0,0,((LOOKUP(MAX(D33-E33-F33-'Tax Assumptions'!$B$8,0),'Tax Assumptions'!$F$9:$F$15,'Tax Assumptions'!$I$9:$I$15)+(MAX(D33-E33-F33-'Tax Assumptions'!$B$8,0)-LOOKUP(MAX(D33-E33-F33-'Tax Assumptions'!$B$8,0),'Tax Assumptions'!$F$9:$F$15,'Tax Assumptions'!$F$9:$F$15))*LOOKUP(MAX(D33-E33-F33-'Tax Assumptions'!$B$8,0),'Tax Assumptions'!$F$9:$F$15,'Tax Assumptions'!$H$9:$H$15))+(MIN(MAX(D33-F33,0),'Tax Assumptions'!$B$11)*'Tax Assumptions'!$B$10)+(MAX(D33-F33,0)*'Tax Assumptions'!$B$12)+(MAX(MAX(D33-F33,0)-'Tax Assumptions'!$B$14,0)*'Tax Assumptions'!$B$13)+(MIN(D33*'Tax Assumptions'!$B$15,'Tax Assumptions'!$B$16))+(MIN(D33*'Tax Assumptions'!$B$17,'Tax Assumptions'!$B$18))+(LOOKUP(MAX(D33-E33-'Tax Assumptions'!$B$9,0),'Tax Assumptions'!$K$9:$K$17,'Tax Assumptions'!$N$9:$N$17)+(MAX(D33-E33-'Tax Assumptions'!$B$9,0)-LOOKUP(MAX(D33-E33-'Tax Assumptions'!$B$9,0),'Tax Assumptions'!$K$9:$K$17,'Tax Assumptions'!$K$9:$K$17))*LOOKUP(MAX(D33-E33-'Tax Assumptions'!$B$9,0),'Tax Assumptions'!$K$9:$K$17,'Tax Assumptions'!$M$9:$M$17))+(LOOKUP(MAX(D33-E33-'Tax Assumptions'!$B$9,0),'Tax Assumptions'!$P$9:$P$12,'Tax Assumptions'!$S$9:$S$12)+(MAX(D33-E33-'Tax Assumptions'!$B$9,0)-LOOKUP(MAX(D33-E33-'Tax Assumptions'!$B$9,0),'Tax Assumptions'!$P$9:$P$12,'Tax Assumptions'!$P$9:$P$12))*LOOKUP(MAX(D33-E33-'Tax Assumptions'!$B$9,0),'Tax Assumptions'!$P$9:$P$12,'Tax Assumptions'!$R$9:$R$12)))*$B$7) -> 111437.72 | I33: =IF(B33="Working",D33-E33-F33-G33-H33,0) -> 173437.28 | J33: =IF(B33="Working",N('Savings Projection'!$S$20)*$B$8,0) -> 80340 | K33: =IF(B33="Working",N('Savings Projection'!$T$20)*$B$9,0) -> 39140 | L33: =IF(B33="Working",MIN(MAX(I33-J33-K33-AB33-AC33,0),'Tax Assumptions'!$B$20),0) -> 7500 | M33: =IF(B33="Working",I33-J33-K33-L33-AB33-AC33,0) -> 46457.279 | N33: =IF(B33="Working",M33+L33+E33+F33,-P33) -> 78457.279 | O33: =IF(B33="Retired",$B$12+AB33+AC33,0) -> 0 | P33: =Q33+R33+S33+T33 -> 0 | Q33: =IF(B33="Retired",MIN(((U32)*(1+$B$10)+IF(B33="Working",M33,0)),O33),0) -> 0 | R33: =IF(B33="Retired",MIN(MAX(O33-Q33,0),((V32)*(1+$B$10)+IF(B33="Working",E33,0))),0) -> 0 | S33: =IF(B33="Retired",MIN(MAX(O33-Q33-R33,0),((W32)*(1+$B$10)+IF(B33="Working",L33,0))),0) -> 0 | T33: =IF(B33="Retired",MIN(MAX(O33-Q33-R33-S33,0),((X32)*(1+$B$10)+IF(B33="Working",F33,0))),0) -> 0 | U33: =MAX(((U32)*(1+$B$10)+IF(B33="Working",M33,0))-Q33,0) -> 314258.08 | V33: =MAX(((V32)*(1+$B$10)+IF(B33="Working",E33,0))-R33,0) -> 49980 | W33: =MAX(((W32)*(1+$B$10)+IF(B33="Working",L33,0))-S33,0) -> 15300 | X33: =MAX(((X32)*(1+$B$10)+IF(B33="Working",F33,0))-T33,0) -> 0 | Y33: =U33+V33+W33+X33 -> 379538.08 | Z33: =IF(B33="Retired",MAX(O33-P33,0),0) -> 0 | AA33: =IF(B33="Working",IF(D33=0,0,N33/D33),0) -> 0.25359929 | AB33: =IF(AND($B$14>0,A33=$B$13),$B$14*($B$15+$B$18),0)+IF(AND($B$14>0,A33=$B$13),$B$24,0) -> 0 | AC33: =IF(OR($B$14<=0,A33<$B$13),0,IF(AND($B$14>0,$B$17>0,A33>=$B$13,A33<($B$13+$B$17)),IF($B$17<=0,0,IF($B$16=0,MAX($B$14*(1-$B$15),0)/$B$17,-PMT($B$16/12,$B$17*12,MAX($B$14*(1-$B$15),0))*12)),0)+AD33*($B$19+$B$20+$B$21)+$B$22+$B$23) -> 0 | AD33: =IF(AND($B$14>0,A33>=$B$13),$B$14*(1+$B$25)^(A33-$B$13),0) -> 0 | AE33: =IF(OR($B$14<=0,$B$17<=0,A33<$B$13,MIN(MAX((A33-$B$13+1)*12,0),$B$17*12)>=$B$17*12),0,IF($B$16=0,MAX(MAX($B$14*(1-$B$15),0)-(IF($B$17<=0,0,IF($B$16=0,MAX($B$14*(1-$B$15),0)/$B$17,-PMT($B$16/12,$B$17*12,MAX($B$14*(1-$B$15),0))*12))/12)*MIN(MAX((A33-$B$13+1)*12,0),$B$17*12),0),MAX(MAX($B$14*(1-$B$15),0)*(1+$B$16/12)^MIN(MAX((A33-$B$13+1)*12,0),$B$17*12)-(IF($B$17<=0,0,IF($B$16=0,MAX($B$14*(1-$B$15),0)/$B$17,-PMT($B$16/12,$B$17*12,MAX($B$14*(1-$B$15),0))*12))/12)*(((1+$B$16/12)^MIN(MAX((A33-$B$13+1)*12,0),$B$17*12)-1)/($B$16/12)),0))) -> 0 | AF33: =MAX(AD33-AE33,0) -> 0 | AG33: =Y33+AF33 -> 379538.08
A34: 3 | B34: =IF(AND(C34>0,A34<=$B$11),"Working","Retired") -> Working | C34: =N('Savings Projection'!$B$21) -> 675000 | D34: =IF(B34="Working",C34*$B$6,0) -> 506250 | E34: =IF(OR(B34="Retired",D34=0),0,MIN(D34,'Tax Assumptions'!$B$19)) -> 24500 | F34: =IF(B34="Working",N('Savings Projection'!$E$21),0) -> 0 | G34: =IF(B34="Working",N('Savings Projection'!$F$21),0) -> 0 | H34: =IF(D34=0,0,((LOOKUP(MAX(D34-E34-F34-'Tax Assumptions'!$B$8,0),'Tax Assumptions'!$F$9:$F$15,'Tax Assumptions'!$I$9:$I$15)+(MAX(D34-E34-F34-'Tax Assumptions'!$B$8,0)-LOOKUP(MAX(D34-E34-F34-'Tax Assumptions'!$B$8,0),'Tax Assumptions'!$F$9:$F$15,'Tax Assumptions'!$F$9:$F$15))*LOOKUP(MAX(D34-E34-F34-'Tax Assumptions'!$B$8,0),'Tax Assumptions'!$F$9:$F$15,'Tax Assumptions'!$H$9:$H$15))+(MIN(MAX(D34-F34,0),'Tax Assumptions'!$B$11)*'Tax Assumptions'!$B$10)+(MAX(D34-F34,0)*'Tax Assumptions'!$B$12)+(MAX(MAX(D34-F34,0)-'Tax Assumptions'!$B$14,0)*'Tax Assumptions'!$B$13)+(MIN(D34*'Tax Assumptions'!$B$15,'Tax Assumptions'!$B$16))+(MIN(D34*'Tax Assumptions'!$B$17,'Tax Assumptions'!$B$18))+(LOOKUP(MAX(D34-E34-'Tax Assumptions'!$B$9,0),'Tax Assumptions'!$K$9:$K$17,'Tax Assumptions'!$N$9:$N$17)+(MAX(D34-E34-'Tax Assumptions'!$B$9,0)-LOOKUP(MAX(D34-E34-'Tax Assumptions'!$B$9,0),'Tax Assumptions'!$K$9:$K$17,'Tax Assumptions'!$K$9:$K$17))*LOOKUP(MAX(D34-E34-'Tax Assumptions'!$B$9,0),'Tax Assumptions'!$K$9:$K$17,'Tax Assumptions'!$M$9:$M$17))+(LOOKUP(MAX(D34-E34-'Tax Assumptions'!$B$9,0),'Tax Assumptions'!$P$9:$P$12,'Tax Assumptions'!$S$9:$S$12)+(MAX(D34-E34-'Tax Assumptions'!$B$9,0)-LOOKUP(MAX(D34-E34-'Tax Assumptions'!$B$9,0),'Tax Assumptions'!$P$9:$P$12,'Tax Assumptions'!$P$9:$P$12))*LOOKUP(MAX(D34-E34-'Tax Assumptions'!$B$9,0),'Tax Assumptions'!$P$9:$P$12,'Tax Assumptions'!$R$9:$R$12)))*$B$7) -> 209873.33 | I34: =IF(B34="Working",D34-E34-F34-G34-H34,0) -> 271876.67 | J34: =IF(B34="Working",N('Savings Projection'!$S$21)*$B$8,0) -> 82750.2 | K34: =IF(B34="Working",N('Savings Projection'!$T$21)*$B$9,0) -> 50392.75 | L34: =IF(B34="Working",MIN(MAX(I34-J34-K34-AB34-AC34,0),'Tax Assumptions'!$B$20),0) -> 7500 | M34: =IF(B34="Working",I34-J34-K34-L34-AB34-AC34,0) -> 131233.72 | N34: =IF(B34="Working",M34+L34+E34+F34,-P34) -> 163233.72 | O34: =IF(B34="Retired",$B$12+AB34+AC34,0) -> 0 | P34: =Q34+R34+S34+T34 -> 0 | Q34: =IF(B34="Retired",MIN(((U33)*(1+$B$10)+IF(B34="Working",M34,0)),O34),0) -> 0 | R34: =IF(B34="Retired",MIN(MAX(O34-Q34,0),((V33)*(1+$B$10)+IF(B34="Working",E34,0))),0) -> 0 | S34: =IF(B34="Retired",MIN(MAX(O34-Q34-R34,0),((W33)*(1+$B$10)+IF(B34="Working",L34,0))),0) -> 0 | T34: =IF(B34="Retired",MIN(MAX(O34-Q34-R34-S34,0),((X33)*(1+$B$10)+IF(B34="Working",F34,0))),0) -> 0 | U34: =MAX(((U33)*(1+$B$10)+IF(B34="Working",M34,0))-Q34,0) -> 458062.12 | V34: =MAX(((V33)*(1+$B$10)+IF(B34="Working",E34,0))-R34,0) -> 76479.2 | W34: =MAX(((W33)*(1+$B$10)+IF(B34="Working",L34,0))-S34,0) -> 23412 | X34: =MAX(((X33)*(1+$B$10)+IF(B34="Working",F34,0))-T34,0) -> 0 | Y34: =U34+V34+W34+X34 -> 557953.32 | Z34: =IF(B34="Retired",MAX(O34-P34,0),0) -> 0 | AA34: =IF(B34="Working",IF(D34=0,0,N34/D34),0) -> 0.32243698 | AB34: =IF(AND($B$14>0,A34=$B$13),$B$14*($B$15+$B$18),0)+IF(AND($B$14>0,A34=$B$13),$B$24,0) -> 0 | AC34: =IF(OR($B$14<=0,A34<$B$13),0,IF(AND($B$14>0,$B$17>0,A34>=$B$13,A34<($B$13+$B$17)),IF($B$17<=0,0,IF($B$16=0,MAX($B$14*(1-$B$15),0)/$B$17,-PMT($B$16/12,$B$17*12,MAX($B$14*(1-$B$15),0))*12)),0)+AD34*($B$19+$B$20+$B$21)+$B$22+$B$23) -> 0 | AD34: =IF(AND($B$14>0,A34>=$B$13),$B$14*(1+$B$25)^(A34-$B$13),0) -> 0 | AE34: =IF(OR($B$14<=0,$B$17<=0,A34<$B$13,MIN(MAX((A34-$B$13+1)*12,0),$B$17*12)>=$B$17*12),0,IF($B$16=0,MAX(MAX($B$14*(1-$B$15),0)-(IF($B$17<=0,0,IF($B$16=0,MAX($B$14*(1-$B$15),0)/$B$17,-PMT($B$16/12,$B$17*12,MAX($B$14*(1-$B$15),0))*12))/12)*MIN(MAX((A34-$B$13+1)*12,0),$B$17*12),0),MAX(MAX($B$14*(1-$B$15),0)*(1+$B$16/12)^MIN(MAX((A34-$B$13+1)*12,0),$B$17*12)-(IF($B$17<=0,0,IF($B$16=0,MAX($B$14*(1-$B$15),0)/$B$17,-PMT($B$16/12,$B$17*12,MAX($B$14*(1-$B$15),0))*12))/12)*(((1+$B$16/12)^MIN(MAX((A34-$B$13+1)*12,0),$B$17*12)-1)/($B$16/12)),0))) -> 0 | AF34: =MAX(AD34-AE34,0) -> 0 | AG34: =Y34+AF34 -> 557953.32
A35: 4 | B35: =IF(AND(C35>0,A35<=$B$11),"Working","Retired") -> Working | C35: =N('Savings Projection'!$B$22) -> 750000 | D35: =IF(B35="Working",C35*$B$6,0) -> 562500 | E35: =IF(OR(B35="Retired",D35=0),0,MIN(D35,'Tax Assumptions'!$B$19)) -> 24500 | F35: =IF(B35="Working",N('Savings Projection'!$E$22),0) -> 0 | G35: =IF(B35="Working",N('Savings Projection'!$F$22),0) -> 0 | H35: =IF(D35=0,0,((LOOKUP(MAX(D35-E35-F35-'Tax Assumptions'!$B$8,0),'Tax Assumptions'!$F$9:$F$15,'Tax Assumptions'!$I$9:$I$15)+(MAX(D35-E35-F35-'Tax Assumptions'!$B$8,0)-LOOKUP(MAX(D35-E35-F35-'Tax Assumptions'!$B$8,0),'Tax Assumptions'!$F$9:$F$15,'Tax Assumptions'!$F$9:$F$15))*LOOKUP(MAX(D35-E35-F35-'Tax Assumptions'!$B$8,0),'Tax Assumptions'!$F$9:$F$15,'Tax Assumptions'!$H$9:$H$15))+(MIN(MAX(D35-F35,0),'Tax Assumptions'!$B$11)*'Tax Assumptions'!$B$10)+(MAX(D35-F35,0)*'Tax Assumptions'!$B$12)+(MAX(MAX(D35-F35,0)-'Tax Assumptions'!$B$14,0)*'Tax Assumptions'!$B$13)+(MIN(D35*'Tax Assumptions'!$B$15,'Tax Assumptions'!$B$16))+(MIN(D35*'Tax Assumptions'!$B$17,'Tax Assumptions'!$B$18))+(LOOKUP(MAX(D35-E35-'Tax Assumptions'!$B$9,0),'Tax Assumptions'!$K$9:$K$17,'Tax Assumptions'!$N$9:$N$17)+(MAX(D35-E35-'Tax Assumptions'!$B$9,0)-LOOKUP(MAX(D35-E35-'Tax Assumptions'!$B$9,0),'Tax Assumptions'!$K$9:$K$17,'Tax Assumptions'!$K$9:$K$17))*LOOKUP(MAX(D35-E35-'Tax Assumptions'!$B$9,0),'Tax Assumptions'!$K$9:$K$17,'Tax Assumptions'!$M$9:$M$17))+(LOOKUP(MAX(D35-E35-'Tax Assumptions'!$B$9,0),'Tax Assumptions'!$P$9:$P$12,'Tax Assumptions'!$S$9:$S$12)+(MAX(D35-E35-'Tax Assumptions'!$B$9,0)-LOOKUP(MAX(D35-E35-'Tax Assumptions'!$B$9,0),'Tax Assumptions'!$P$9:$P$12,'Tax Assumptions'!$P$9:$P$12))*LOOKUP(MAX(D35-E35-'Tax Assumptions'!$B$9,0),'Tax Assumptions'!$P$9:$P$12,'Tax Assumptions'!$R$9:$R$12)))*$B$7) -> 237997.79 | I35: =IF(B35="Working",D35-E35-F35-G35-H35,0) -> 300002.21 | J35: =IF(B35="Working",N('Savings Projection'!$S$22)*$B$8,0) -> 85232.706 | K35: =IF(B35="Working",N('Savings Projection'!$T$22)*$B$9,0) -> 51904.532 | L35: =IF(B35="Working",MIN(MAX(I35-J35-K35-AB35-AC35,0),'Tax Assumptions'!$B$20),0) -> 7500 | M35: =IF(B35="Working",I35-J35-K35-L35-AB35-AC35,0) -> 155364.97 | N35: =IF(B35="Working",M35+L35+E35+F35,-P35) -> 187364.97 | O35: =IF(B35="Retired",$B$12+AB35+AC35,0) -> 0 | P35: =Q35+R35+S35+T35 -> 0 | Q35: =IF(B35="Retired",MIN(((U34)*(1+$B$10)+IF(B35="Working",M35,0)),O35),0) -> 0 | R35: =IF(B35="Retired",MIN(MAX(O35-Q35,0),((V34)*(1+$B$10)+IF(B35="Working",E35,0))),0) -> 0 | S35: =IF(B35="Retired",MIN(MAX(O35-Q35-R35,0),((W34)*(1+$B$10)+IF(B35="Working",L35,0))),0) -> 0 | T35: =IF(B35="Retired",MIN(MAX(O35-Q35-R35-S35,0),((X34)*(1+$B$10)+IF(B35="Working",F35,0))),0) -> 0 | U35: =MAX(((U34)*(1+$B$10)+IF(B35="Working",M35,0))-Q35,0) -> 631749.58 | V35: =MAX(((V34)*(1+$B$10)+IF(B35="Working",E35,0))-R35,0) -> 104038.37 | W35: =MAX(((W34)*(1+$B$10)+IF(B35="Working",L35,0))-S35,0) -> 31848.48 | X35: =MAX(((X34)*(1+$B$10)+IF(B35="Working",F35,0))-T35,0) -> 0 | Y35: =U35+V35+W35+X35 -> 767636.42 | Z35: =IF(B35="Retired",MAX(O35-P35,0),0) -> 0 | AA35: =IF(B35="Working",IF(D35=0,0,N35/D35),0) -> 0.33309328 | AB35: =IF(AND($B$14>0,A35=$B$13),$B$14*($B$15+$B$18),0)+IF(AND($B$14>0,A35=$B$13),$B$24,0) -> 0 | AC35: =IF(OR($B$14<=0,A35<$B$13),0,IF(AND($B$14>0,$B$17>0,A35>=$B$13,A35<($B$13+$B$17)),IF($B$17<=0,0,IF($B$16=0,MAX($B$14*(1-$B$15),0)/$B$17,-PMT($B$16/12,$B$17*12,MAX($B$14*(1-$B$15),0))*12)),0)+AD35*($B$19+$B$20+$B$21)+$B$22+$B$23) -> 0 | AD35: =IF(AND($B$14>0,A35>=$B$13),$B$14*(1+$B$25)^(A35-$B$13),0) -> 0 | AE35: =IF(OR($B$14<=0,$B$17<=0,A35<$B$13,MIN(MAX((A35-$B$13+1)*12,0),$B$17*12)>=$B$17*12),0,IF($B$16=0,MAX(MAX($B$14*(1-$B$15),0)-(IF($B$17<=0,0,IF($B$16=0,MAX($B$14*(1-$B$15),0)/$B$17,-PMT($B$16/12,$B$17*12,MAX($B$14*(1-$B$15),0))*12))/12)*MIN(MAX((A35-$B$13+1)*12,0),$B$17*12),0),MAX(MAX($B$14*(1-$B$15),0)*(1+$B$16/12)^MIN(MAX((A35-$B$13+1)*12,0),$B$17*12)-(IF($B$17<=0,0,IF($B$16=0,MAX($B$14*(1-$B$15),0)/$B$17,-PMT($B$16/12,$B$17*12,MAX($B$14*(1-$B$15),0))*12))/12)*(((1+$B$16/12)^MIN(MAX((A35-$B$13+1)*12,0),$B$17*12)-1)/($B$16/12)),0))) -> 0 | AF35: =MAX(AD35-AE35,0) -> 0 | AG35: =Y35+AF35 -> 767636.42
A36: 5 | B36: =IF(AND(C36>0,A36<=$B$11),"Working","Retired") -> Working | C36: =N('Savings Projection'!$B$23) -> 953837.51 | D36: =IF(B36="Working",C36*$B$6,0) -> 715378.14 | E36: =IF(OR(B36="Retired",D36=0),0,MIN(D36,'Tax Assumptions'!$B$19)) -> 24500 | F36: =IF(B36="Working",N('Savings Projection'!$E$23),0) -> 0 | G36: =IF(B36="Working",N('Savings Projection'!$F$23),0) -> 0 | H36: =IF(D36=0,0,((LOOKUP(MAX(D36-E36-F36-'Tax Assumptions'!$B$8,0),'Tax Assumptions'!$F$9:$F$15,'Tax Assumptions'!$I$9:$I$15)+(MAX(D36-E36-F36-'Tax Assumptions'!$B$8,0)-LOOKUP(MAX(D36-E36-F36-'Tax Assumptions'!$B$8,0),'Tax Assumptions'!$F$9:$F$15,'Tax Assumptions'!$F$9:$F$15))*LOOKUP(MAX(D36-E36-F36-'Tax Assumptions'!$B$8,0),'Tax Assumptions'!$F$9:$F$15,'Tax Assumptions'!$H$9:$H$15))+(MIN(MAX(D36-F36,0),'Tax Assumptions'!$B$11)*'Tax Assumptions'!$B$10)+(MAX(D36-F36,0)*'Tax Assumptions'!$B$12)+(MAX(MAX(D36-F36,0)-'Tax Assumptions'!$B$14,0)*'Tax Assumptions'!$B$13)+(MIN(D36*'Tax Assumptions'!$B$15,'Tax Assumptions'!$B$16))+(MIN(D36*'Tax Assumptions'!$B$17,'Tax Assumptions'!$B$18))+(LOOKUP(MAX(D36-E36-'Tax Assumptions'!$B$9,0),'Tax Assumptions'!$K$9:$K$17,'Tax Assumptions'!$N$9:$N$17)+(MAX(D36-E36-'Tax Assumptions'!$B$9,0)-LOOKUP(MAX(D36-E36-'Tax Assumptions'!$B$9,0),'Tax Assumptions'!$K$9:$K$17,'Tax Assumptions'!$K$9:$K$17))*LOOKUP(MAX(D36-E36-'Tax Assumptions'!$B$9,0),'Tax Assumptions'!$K$9:$K$17,'Tax Assumptions'!$M$9:$M$17))+(LOOKUP(MAX(D36-E36-'Tax Assumptions'!$B$9,0),'Tax Assumptions'!$P$9:$P$12,'Tax Assumptions'!$S$9:$S$12)+(MAX(D36-E36-'Tax Assumptions'!$B$9,0)-LOOKUP(MAX(D36-E36-'Tax Assumptions'!$B$9,0),'Tax Assumptions'!$P$9:$P$12,'Tax Assumptions'!$P$9:$P$12))*LOOKUP(MAX(D36-E36-'Tax Assumptions'!$B$9,0),'Tax Assumptions'!$P$9:$P$12,'Tax Assumptions'!$R$9:$R$12)))*$B$7) -> 315146.3 | I36: =IF(B36="Working",D36-E36-F36-G36-H36,0) -> 375731.84 | J36: =IF(B36="Working",N('Savings Projection'!$S$23)*$B$8,0) -> 87789.687 | K36: =IF(B36="Working",N('Savings Projection'!$T$23)*$B$9,0) -> 53461.668 | L36: =IF(B36="Working",MIN(MAX(I36-J36-K36-AB36-AC36,0),'Tax Assumptions'!$B$20),0) -> 7500 | M36: =IF(B36="Working",I36-J36-K36-L36-AB36-AC36,0) -> 226980.48 | N36: =IF(B36="Working",M36+L36+E36+F36,-P36) -> 258980.48 | O36: =IF(B36="Retired",$B$12+AB36+AC36,0) -> 0 | P36: =Q36+R36+S36+T36 -> 0 | Q36: =IF(B36="Retired",MIN(((U35)*(1+$B$10)+IF(B36="Working",M36,0)),O36),0) -> 0 | R36: =IF(B36="Retired",MIN(MAX(O36-Q36,0),((V35)*(1+$B$10)+IF(B36="Working",E36,0))),0) -> 0 | S36: =IF(B36="Retired",MIN(MAX(O36-Q36-R36,0),((W35)*(1+$B$10)+IF(B36="Working",L36,0))),0) -> 0 | T36: =IF(B36="Retired",MIN(MAX(O36-Q36-R36-S36,0),((X35)*(1+$B$10)+IF(B36="Working",F36,0))),0) -> 0 | U36: =MAX(((U35)*(1+$B$10)+IF(B36="Working",M36,0))-Q36,0) -> 884000.04 | V36: =MAX(((V35)*(1+$B$10)+IF(B36="Working",E36,0))-R36,0) -> 132699.9 | W36: =MAX(((W35)*(1+$B$10)+IF(B36="Working",L36,0))-S36,0) -> 40622.419 | X36: =MAX(((X35)*(1+$B$10)+IF(B36="Working",F36,0))-T36,0) -> 0 | Y36: =U36+V36+W36+X36 -> 1057322.4 | Z36: =IF(B36="Retired",MAX(O36-P36,0),0) -> 0 | AA36: =IF(B36="Working",IF(D36=0,0,N36/D36),0) -> 0.36201901 | AB36: =IF(AND($B$14>0,A36=$B$13),$B$14*($B$15+$B$18),0)+IF(AND($B$14>0,A36=$B$13),$B$24,0) -> 0 | AC36: =IF(OR($B$14<=0,A36<$B$13),0,IF(AND($B$14>0,$B$17>0,A36>=$B$13,A36<($B$13+$B$17)),IF($B$17<=0,0,IF($B$16=0,MAX($B$14*(1-$B$15),0)/$B$17,-PMT($B$16/12,$B$17*12,MAX($B$14*(1-$B$15),0))*12)),0)+AD36*($B$19+$B$20+$B$21)+$B$22+$B$23) -> 0 | AD36: =IF(AND($B$14>0,A36>=$B$13),$B$14*(1+$B$25)^(A36-$B$13),0) -> 0 | AE36: =IF(OR($B$14<=0,$B$17<=0,A36<$B$13,MIN(MAX((A36-$B$13+1)*12,0),$B$17*12)>=$B$17*12),0,IF($B$16=0,MAX(MAX($B$14*(1-$B$15),0)-(IF($B$17<=0,0,IF($B$16=0,MAX($B$14*(1-$B$15),0)/$B$17,-PMT($B$16/12,$B$17*12,MAX($B$14*(1-$B$15),0))*12))/12)*MIN(MAX((A36-$B$13+1)*12,0),$B$17*12),0),MAX(MAX($B$14*(1-$B$15),0)*(1+$B$16/12)^MIN(MAX((A36-$B$13+1)*12,0),$B$17*12)-(IF($B$17<=0,0,IF($B$16=0,MAX($B$14*(1-$B$15),0)/$B$17,-PMT($B$16/12,$B$17*12,MAX($B$14*(1-$B$15),0))*12))/12)*(((1+$B$16/12)^MIN(MAX((A36-$B$13+1)*12,0),$B$17*12)-1)/($B$16/12)),0))) -> 0 | AF36: =MAX(AD36-AE36,0) -> 0 | AG36: =Y36+AF36 -> 1057322.4
A37: 6 | B37: =IF(AND(C37>0,A37<=$B$11),"Working","Retired") -> Working | C37: =N('Savings Projection'!$B$24) -> 1118900.7 | D37: =IF(B37="Working",C37*$B$6,0) -> 839175.5 | E37: =IF(OR(B37="Retired",D37=0),0,MIN(D37,'Tax Assumptions'!$B$19)) -> 24500 | F37: =IF(B37="Working",N('Savings Projection'!$E$24),0) -> 0 | G37: =IF(B37="Working",N('Savings Projection'!$F$24),0) -> 0 | H37: =IF(D37=0,0,((LOOKUP(MAX(D37-E37-F37-'Tax Assumptions'!$B$8,0),'Tax Assumptions'!$F$9:$F$15,'Tax Assumptions'!$I$9:$I$15)+(MAX(D37-E37-F37-'Tax Assumptions'!$B$8,0)-LOOKUP(MAX(D37-E37-F37-'Tax Assumptions'!$B$8,0),'Tax Assumptions'!$F$9:$F$15,'Tax Assumptions'!$F$9:$F$15))*LOOKUP(MAX(D37-E37-F37-'Tax Assumptions'!$B$8,0),'Tax Assumptions'!$F$9:$F$15,'Tax Assumptions'!$H$9:$H$15))+(MIN(MAX(D37-F37,0),'Tax Assumptions'!$B$11)*'Tax Assumptions'!$B$10)+(MAX(D37-F37,0)*'Tax Assumptions'!$B$12)+(MAX(MAX(D37-F37,0)-'Tax Assumptions'!$B$14,0)*'Tax Assumptions'!$B$13)+(MIN(D37*'Tax Assumptions'!$B$15,'Tax Assumptions'!$B$16))+(MIN(D37*'Tax Assumptions'!$B$17,'Tax Assumptions'!$B$18))+(LOOKUP(MAX(D37-E37-'Tax Assumptions'!$B$9,0),'Tax Assumptions'!$K$9:$K$17,'Tax Assumptions'!$N$9:$N$17)+(MAX(D37-E37-'Tax Assumptions'!$B$9,0)-LOOKUP(MAX(D37-E37-'Tax Assumptions'!$B$9,0),'Tax Assumptions'!$K$9:$K$17,'Tax Assumptions'!$K$9:$K$17))*LOOKUP(MAX(D37-E37-'Tax Assumptions'!$B$9,0),'Tax Assumptions'!$K$9:$K$17,'Tax Assumptions'!$M$9:$M$17))+(LOOKUP(MAX(D37-E37-'Tax Assumptions'!$B$9,0),'Tax Assumptions'!$P$9:$P$12,'Tax Assumptions'!$S$9:$S$12)+(MAX(D37-E37-'Tax Assumptions'!$B$9,0)-LOOKUP(MAX(D37-E37-'Tax Assumptions'!$B$9,0),'Tax Assumptions'!$P$9:$P$12,'Tax Assumptions'!$P$9:$P$12))*LOOKUP(MAX(D37-E37-'Tax Assumptions'!$B$9,0),'Tax Assumptions'!$P$9:$P$12,'Tax Assumptions'!$R$9:$R$12)))*$B$7) -> 379618.78 | I37: =IF(B37="Working",D37-E37-F37-G37-H37,0) -> 435056.72 | J37: =IF(B37="Working",N('Savings Projection'!$S$24)*$B$8,0) -> 92741.926 | K37: =IF(B37="Working",N('Savings Projection'!$T$24)*$B$9,0) -> 55065.519 | L37: =IF(B37="Working",MIN(MAX(I37-J37-K37-AB37-AC37,0),'Tax Assumptions'!$B$20),0) -> 7500 | M37: =IF(B37="Working",I37-J37-K37-L37-AB37-AC37,0) -> 279749.28 | N37: =IF(B37="Working",M37+L37+E37+F37,-P37) -> 311749.28 | O37: =IF(B37="Retired",$B$12+AB37+AC37,0) -> 0 | P37: =Q37+R37+S37+T37 -> 0 | Q37: =IF(B37="Retired",MIN(((U36)*(1+$B$10)+IF(B37="Working",M37,0)),O37),0) -> 0 | R37: =IF(B37="Retired",MIN(MAX(O37-Q37,0),((V36)*(1+$B$10)+IF(B37="Working",E37,0))),0) -> 0 | S37: =IF(B37="Retired",MIN(MAX(O37-Q37-R37,0),((W36)*(1+$B$10)+IF(B37="Working",L37,0))),0) -> 0 | T37: =IF(B37="Retired",MIN(MAX(O37-Q37-R37-S37,0),((X36)*(1+$B$10)+IF(B37="Working",F37,0))),0) -> 0 | U37: =MAX(((U36)*(1+$B$10)+IF(B37="Working",M37,0))-Q37,0) -> 1199109.3 | V37: =MAX(((V36)*(1+$B$10)+IF(B37="Working",E37,0))-R37,0) -> 162507.9 | W37: =MAX(((W36)*(1+$B$10)+IF(B37="Working",L37,0))-S37,0) -> 49747.316 | X37: =MAX(((X36)*(1+$B$10)+IF(B37="Working",F37,0))-T37,0) -> 0 | Y37: =U37+V37+W37+X37 -> 1411364.5 | Z37: =IF(B37="Retired",MAX(O37-P37,0),0) -> 0 | AA37: =IF(B37="Working",IF(D37=0,0,N37/D37),0) -> 0.37149473 | AB37: =IF(AND($B$14>0,A37=$B$13),$B$14*($B$15+$B$18),0)+IF(AND($B$14>0,A37=$B$13),$B$24,0) -> 0 | AC37: =IF(OR($B$14<=0,A37<$B$13),0,IF(AND($B$14>0,$B$17>0,A37>=$B$13,A37<($B$13+$B$17)),IF($B$17<=0,0,IF($B$16=0,MAX($B$14*(1-$B$15),0)/$B$17,-PMT($B$16/12,$B$17*12,MAX($B$14*(1-$B$15),0))*12)),0)+AD37*($B$19+$B$20+$B$21)+$B$22+$B$23) -> 0 | AD37: =IF(AND($B$14>0,A37>=$B$13),$B$14*(1+$B$25)^(A37-$B$13),0) -> 0 | AE37: =IF(OR($B$14<=0,$B$17<=0,A37<$B$13,MIN(MAX((A37-$B$13+1)*12,0),$B$17*12)>=$B$17*12),0,IF($B$16=0,MAX(MAX($B$14*(1-$B$15),0)-(IF($B$17<=0,0,IF($B$16=0,MAX($B$14*(1-$B$15),0)/$B$17,-PMT($B$16/12,$B$17*12,MAX($B$14*(1-$B$15),0))*12))/12)*MIN(MAX((A37-$B$13+1)*12,0),$B$17*12),0),MAX(MAX($B$14*(1-$B$15),0)*(1+$B$16/12)^MIN(MAX((A37-$B$13+1)*12,0),$B$17*12)-(IF($B$17<=0,0,IF($B$16=0,MAX($B$14*(1-$B$15),0)/$B$17,-PMT($B$16/12,$B$17*12,MAX($B$14*(1-$B$15),0))*12))/12)*(((1+$B$16/12)^MIN(MAX((A37-$B$13+1)*12,0),$B$17*12)-1)/($B$16/12)),0))) -> 0 | AF37: =MAX(AD37-AE37,0) -> 0 | AG37: =Y37+AF37 -> 1411364.5
A38: 7 | B38: =IF(AND(C38>0,A38<=$B$11),"Working","Retired") -> Working | C38: =N('Savings Projection'!$B$25) -> 1418318.4 | D38: =IF(B38="Working",C38*$B$6,0) -> 1063738.8 | E38: =IF(OR(B38="Retired",D38=0),0,MIN(D38,'Tax Assumptions'!$B$19)) -> 24500 | F38: =IF(B38="Working",N('Savings Projection'!$E$25),0) -> 0 | G38: =IF(B38="Working",N('Savings Projection'!$F$25),0) -> 0 | H38: =IF(D38=0,0,((LOOKUP(MAX(D38-E38-F38-'Tax Assumptions'!$B$8,0),'Tax Assumptions'!$F$9:$F$15,'Tax Assumptions'!$I$9:$I$15)+(MAX(D38-E38-F38-'Tax Assumptions'!$B$8,0)-LOOKUP(MAX(D38-E38-F38-'Tax Assumptions'!$B$8,0),'Tax Assumptions'!$F$9:$F$15,'Tax Assumptions'!$F$9:$F$15))*LOOKUP(MAX(D38-E38-F38-'Tax Assumptions'!$B$8,0),'Tax Assumptions'!$F$9:$F$15,'Tax Assumptions'!$H$9:$H$15))+(MIN(MAX(D38-F38,0),'Tax Assumptions'!$B$11)*'Tax Assumptions'!$B$10)+(MAX(D38-F38,0)*'Tax Assumptions'!$B$12)+(MAX(MAX(D38-F38,0)-'Tax Assumptions'!$B$14,0)*'Tax Assumptions'!$B$13)+(MIN(D38*'Tax Assumptions'!$B$15,'Tax Assumptions'!$B$16))+(MIN(D38*'Tax Assumptions'!$B$17,'Tax Assumptions'!$B$18))+(LOOKUP(MAX(D38-E38-'Tax Assumptions'!$B$9,0),'Tax Assumptions'!$K$9:$K$17,'Tax Assumptions'!$N$9:$N$17)+(MAX(D38-E38-'Tax Assumptions'!$B$9,0)-LOOKUP(MAX(D38-E38-'Tax Assumptions'!$B$9,0),'Tax Assumptions'!$K$9:$K$17,'Tax Assumptions'!$K$9:$K$17))*LOOKUP(MAX(D38-E38-'Tax Assumptions'!$B$9,0),'Tax Assumptions'!$K$9:$K$17,'Tax Assumptions'!$M$9:$M$17))+(LOOKUP(MAX(D38-E38-'Tax Assumptions'!$B$9,0),'Tax Assumptions'!$P$9:$P$12,'Tax Assumptions'!$S$9:$S$12)+(MAX(D38-E38-'Tax Assumptions'!$B$9,0)-LOOKUP(MAX(D38-E38-'Tax Assumptions'!$B$9,0),'Tax Assumptions'!$P$9:$P$12,'Tax Assumptions'!$P$9:$P$12))*LOOKUP(MAX(D38-E38-'Tax Assumptions'!$B$9,0),'Tax Assumptions'!$P$9:$P$12,'Tax Assumptions'!$R$9:$R$12)))*$B$7) -> 496569.21 | I38: =IF(B38="Working",D38-E38-F38-G38-H38,0) -> 542669.63 | J38: =IF(B38="Working",N('Savings Projection'!$S$25)*$B$8,0) -> 95524.184 | K38: =IF(B38="Working",N('Savings Projection'!$T$25)*$B$9,0) -> 56717.484 | L38: =IF(B38="Working",MIN(MAX(I38-J38-K38-AB38-AC38,0),'Tax Assumptions'!$B$20),0) -> 7500 | M38: =IF(B38="Working",I38-J38-K38-L38-AB38-AC38,0) -> 382927.96 | N38: =IF(B38="Working",M38+L38+E38+F38,-P38) -> 414927.96 | O38: =IF(B38="Retired",$B$12+AB38+AC38,0) -> 0 | P38: =Q38+R38+S38+T38 -> 0 | Q38: =IF(B38="Retired",MIN(((U37)*(1+$B$10)+IF(B38="Working",M38,0)),O38),0) -> 0 | R38: =IF(B38="Retired",MIN(MAX(O38-Q38,0),((V37)*(1+$B$10)+IF(B38="Working",E38,0))),0) -> 0 | S38: =IF(B38="Retired",MIN(MAX(O38-Q38-R38,0),((W37)*(1+$B$10)+IF(B38="Working",L38,0))),0) -> 0 | T38: =IF(B38="Retired",MIN(MAX(O38-Q38-R38-S38,0),((X37)*(1+$B$10)+IF(B38="Working",F38,0))),0) -> 0 | U38: =MAX(((U37)*(1+$B$10)+IF(B38="Working",M38,0))-Q38,0) -> 1630001.7 | V38: =MAX(((V37)*(1+$B$10)+IF(B38="Working",E38,0))-R38,0) -> 193508.21 | W38: =MAX(((W37)*(1+$B$10)+IF(B38="Working",L38,0))-S38,0) -> 59237.209 | X38: =MAX(((X37)*(1+$B$10)+IF(B38="Working",F38,0))-T38,0) -> 0 | Y38: =U38+V38+W38+X38 -> 1882747.1 | Z38: =IF(B38="Retired",MAX(O38-P38,0),0) -> 0 | AA38: =IF(B38="Working",IF(D38=0,0,N38/D38),0) -> 0.39006563 | AB38: =IF(AND($B$14>0,A38=$B$13),$B$14*($B$15+$B$18),0)+IF(AND($B$14>0,A38=$B$13),$B$24,0) -> 0 | AC38: =IF(OR($B$14<=0,A38<$B$13),0,IF(AND($B$14>0,$B$17>0,A38>=$B$13,A38<($B$13+$B$17)),IF($B$17<=0,0,IF($B$16=0,MAX($B$14*(1-$B$15),0)/$B$17,-PMT($B$16/12,$B$17*12,MAX($B$14*(1-$B$15),0))*12)),0)+AD38*($B$19+$B$20+$B$21)+$B$22+$B$23) -> 0 | AD38: =IF(AND($B$14>0,A38>=$B$13),$B$14*(1+$B$25)^(A38-$B$13),0) -> 0 | AE38: =IF(OR($B$14<=0,$B$17<=0,A38<$B$13,MIN(MAX((A38-$B$13+1)*12,0),$B$17*12)>=$B$17*12),0,IF($B$16=0,MAX(MAX($B$14*(1-$B$15),0)-(IF($B$17<=0,0,IF($B$16=0,MAX($B$14*(1-$B$15),0)/$B$17,-PMT($B$16/12,$B$17*12,MAX($B$14*(1-$B$15),0))*12))/12)*MIN(MAX((A38-$B$13+1)*12,0),$B$17*12),0),MAX(MAX($B$14*(1-$B$15),0)*(1+$B$16/12)^MIN(MAX((A38-$B$13+1)*12,0),$B$17*12)-(IF($B$17<=0,0,IF($B$16=0,MAX($B$14*(1-$B$15),0)/$B$17,-PMT($B$16/12,$B$17*12,MAX($B$14*(1-$B$15),0))*12))/12)*(((1+$B$16/12)^MIN(MAX((A38-$B$13+1)*12,0),$B$17*12)-1)/($B$16/12)),0))) -> 0 | AF38: =MAX(AD38-AE38,0) -> 0 | AG38: =Y38+AF38 -> 1882747.1
